[
  {
    "post_text": "Political Science Major ðŸŽ“\n\nDemographics\n\nWhite\nMale\n0-50k\nPrivate School\nAcademics\n\n1590 SAT\n8 AP's\n3.87 UW\n4.2 W\nExtracurriculars\n\n1. Student Body President\n\n2. Varsity Rower\n\n3. Intern at Congresswomen's Office\n\n4. Researcher and Presenter\n\n5. Peer Tutor/English Tutor/Worker\n\n6. Yale Young Global Scholars\n\n7. Intern at PwC Sydney Office\n\n8. Camp Counselor at Native American school\n\n9. Pre-college programs\n\n10. Co-founder of a digital magazine\n\nAwards\n\n1. N/A\n\nAcceptances\n\n1. Georgetown\n\n2. Notre Dame\n\n3. Villanova University\n\n4. UNC\n\n5. UVA\n\n6. Umich\n\n7. UPenn\n\n8. Rice University\n\n9. WashU\n\n10. Yale\n\n11. Princeton\n\n12. Williams\n\n13. Amherst\n\n14. Middlebury\n\n15. NYU Stern\n\n16. Dartmouth\n\n17. College of the Holy Cross\n\n18. Boston College\n\n19. Northeastern\n\n20. Emory",
    "structured_profile": {
      "demographics": {
        "gender": "Male",
        "race_ethnicity": "White",
        "residence": null,
        "income_bracket": "0-50k",
        "type_of_school": "Private School",
        "hooks": null,
        "intended_majors": "Political Science"
      },
      "academics": {
        "gpa": { "unweighted": 3.87, "weighted": 4.2 },
        "course_count": {
          "honors": null,
          "ap": 8,
          "ib": null,
          "dual_enrollment": null
        },
        "senior_year_course_load": null
      },
      "standardized_testing": {
        "sat_i": { "total": 1590, "reading_writing": null, "math": null },
        "act": null
      },
      "extracurriculars": [
        "Student Body President",
        "Varsity Rower",
        "Intern at Congresswomen's Office",
        "Researcher and Presenter",
        "Peer Tutor/English Tutor/Worker",
        "Yale Young Global Scholars",
        "Intern at PwC Sydney Office",
        "Camp Counselor at Native American school",
        "Pre-college programs",
        "Co-founder of a digital magazine"
      ],
      "awards_honors": [],
      "letters_of_recommendation": null,
      "essays": null,
      "decisions": {
        "acceptances": [
          { "university": "Georgetown", "decision_plan": "N/A" },
          { "university": "Notre Dame", "decision_plan": "N/A" },
          { "university": "Villanova University", "decision_plan": "N/A" },
          { "university": "UNC", "decision_plan": "N/A" },
          { "university": "UVA", "decision_plan": "N/A" },
          { "university": "Umich", "decision_plan": "N/A" },
          { "university": "UPenn", "decision_plan": "N/A" },
          { "university": "Rice University", "decision_plan": "N/A" },
          { "university": "WashU", "decision_plan": "N/A" },
          { "university": "Yale", "decision_plan": "N/A" },
          { "university": "Princeton", "decision_plan": "N/A" },
          { "university": "Williams", "decision_plan": "N/A" },
          { "university": "Amherst", "decision_plan": "N/A" },
          { "university": "Middlebury", "decision_plan": "N/A" },
          { "university": "NYU Stern", "decision_plan": "N/A" },
          { "university": "Dartmouth", "decision_plan": "N/A" },
          { "university": "College of the Holy Cross", "decision_plan": "N/A" },
          { "university": "Boston College", "decision_plan": "N/A" },
          { "university": "Northeastern", "decision_plan": "N/A" },
          { "university": "Emory", "decision_plan": "N/A" }
        ],
        "waitlists": null,
        "rejections": null
      },
      "additional_information": null
    }
  },

  {
    "post_text": "Political Science Major ðŸŽ“\n\nDemographics\n\nAsian\nNon-Binary\n50k-100k\nPublic School\nAcademics\n\n1540 SAT\n3.76 UW\nExtracurriculars\n\n1. Taking care of family members\n\n2. Model UN President\n\n3. Campaign Intern for 6 election campaigns\n\n4. Director at a long-standing political nonprofit\n\n5. Student council president\n\n6. Summer Program attendee\n\n7. Youth Advisory Chair at large labour education nonprofit\n\n8. Orchestra player at city youth orchestra & street busker\n\n9. Captain for Relay for Life\n\n10. Volunteer Coach & Public Outreach/Marketing director at a figure skating non-profit\n\nAwards\n\n1. Scholastic Art & Writing Gold Key\n\n2. City-wide creative writing contest winner\n\n3. MUN awards\n\n4. Best dressed\n\n5. Canadian scholarship semi-finalist\n\nAcceptances\n\n1. UChicago",
    "structured_profile": {
      "demographics": {
        "gender": "Non-Binary",
        "race_ethnicity": "Asian",
        "residence": null,
        "income_bracket": "50k-100k",
        "type_of_school": "Public School",
        "hooks": null,
        "intended_majors": "Political Science"
      },
      "academics": {
        "gpa": {
          "unweighted": 3.76,
          "weighted": null
        },
        "course_count": null,
        "senior_year_course_load": null
      },
      "standardized_testing": {
        "sat_i": {
          "total": 1540,
          "reading_writing": null,
          "math": null
        },
        "act": null
      },
      "extracurriculars": [
        "Taking care of family members",
        "Model UN President",
        "Campaign Intern for 6 election campaigns",
        "Director at a long-standing political nonprofit",
        "Student council president",
        "Summer Program attendee",
        "Youth Advisory Chair at large labour education nonprofit",
        "Orchestra player at city youth orchestra & street busker",
        "Captain for Relay for Life",
        "Volunteer Coach & Public Outreach/Marketing director at a figure skating non-profit"
      ],
      "awards_honors": [
        "Scholastic Art & Writing Gold Key",
        "City-wide creative writing contest winner",
        "MUN awards",
        "Best dressed",
        "Canadian scholarship semi-finalist"
      ],
      "letters_of_recommendation": null,
      "essays": null,
      "decisions": {
        "acceptances": [
          {
            "university": "UChicago",
            "decision_plan": "N/A"
          }
        ],
        "waitlists": null,
        "rejections": null
      },
      "additional_information": null
    }
  },

  {
    "post_text": "Bioengineering Major ðŸŽ“\n\nDemographics\n\nAsian\nMale\n200k+\nPublic School\nAcademics\n\n1540 SAT\n9 AP's\n4 UW\n4.1268 W\nExtracurriculars\n\n1. Science Olympiad: Captain\n\n2. Treasurer\n\n3. Secretary. Research Intern. Cello: school chamber\n\n4. regions top orchestra. Science Honors Society: President. School Newspaper: Managing Editor. Suicide Awareness Club: Treasurer. Spikeball Club: Cofounder. AAPI Cultural Heritage club: K-pop dancer. Model United Nations: delegate. Lifting.\n\nAwards\n\n1. Science Olympiad big invitational medal\n\n2. Science Olympiad states medal\n\n3. National Merit Semifinalist\n\nAcceptances\n\n1. Binghamton\n\n2. UPenn",
    "structured_profile": {
      "demographics": {
        "gender": "Male",
        "race_ethnicity": "Asian",
        "residence": null,
        "income_bracket": "200k+",
        "type_of_school": "Public School",
        "hooks": null,
        "intended_majors": "Bioengineering"
      },
      "academics": {
        "gpa": {
          "unweighted": 4.0,
          "weighted": 4.1268
        },
        "course_count": {
          "honors": null,
          "ap": 9,
          "ib": null,
          "dual_enrollment": null
        },
        "senior_year_course_load": null
      },
      "standardized_testing": {
        "sat_i": {
          "total": 1540,
          "reading_writing": null,
          "math": null
        },
        "act": null
      },
      "extracurriculars": [
        "Science Olympiad: Captain, Treasurer, Secretary",
        "Research Intern",
        "Cello: school chamber",
        "Cello: regions top orchestra",
        "Science Honors Society: President",
        "School Newspaper: Managing Editor",
        "Suicide Awareness Club: Treasurer",
        "Spikeball Club: Cofounder",
        "AAPI Cultural Heritage club: K-pop dancer",
        "Model United Nations: delegate",
        "Lifting"
      ],
      "awards_honors": [
        "Science Olympiad big invitational medal",
        "Science Olympiad states medal",
        "National Merit Semifinalist"
      ],
      "letters_of_recommendation": null,
      "essays": null,
      "decisions": {
        "acceptances": [
          {
            "university": "Binghamton",
            "decision_plan": "N/A"
          },
          {
            "university": "UPenn",
            "decision_plan": "N/A"
          }
        ],
        "waitlists": null,
        "rejections": null
      },
      "additional_information": null
    }
  },

  {
    "post_text": "Molecular Biology Major ðŸŽ“\n\nDemographics\n\nAsian\nMale\n0-50k\nPublic School\nAcademics\n\n35 ACT\n11 AP's\n3.99 UW\n4.5 W\nExtracurriculars\n\n1. Research Internship at Northwestern University\n\n2. Founder of Biology Club\n\n3. Captain of Science Olympiad team\n\n4. Only high school volunteer at a local hospital\n\n5. Drummer/Leader for a Rock Band\n\nAwards\n\n1. COMAP HiMCM Meritorious\n\n2. Science Olympiad State 1st place in an event\n\n3. Science Olympiad Regional 2nd place in a different event\n\n4. High Honor Roll x3\n\n5. NHS\n\nAcceptances\n\n1. Rutgers University - Newark\n\n2. Pittsburgh University\n\n3. Duke University",
    "structured_profile": {
      "demographics": {
        "gender": "Male",
        "race_ethnicity": "Asian",
        "residence": null,
        "income_bracket": "0-50k",
        "type_of_school": "Public School",
        "hooks": null,
        "intended_majors": "Molecular Biology"
      },
      "academics": {
        "gpa": {
          "unweighted": 3.99,
          "weighted": 4.5
        },
        "course_count": {
          "honors": null,
          "ap": 11,
          "ib": null,
          "dual_enrollment": null
        },
        "senior_year_course_load": null
      },
      "standardized_testing": {
        "sat_i": null,
        "act": 35
      },
      "extracurriculars": [
        "Research Internship at Northwestern University",
        "Founder of Biology Club",
        "Captain of Science Olympiad team",
        "Only high school volunteer at a local hospital",
        "Drummer/Leader for a Rock Band"
      ],
      "awards_honors": [
        "COMAP HiMCM Meritorious",
        "Science Olympiad State 1st place in an event",
        "Science Olympiad Regional 2nd place in a different event",
        "High Honor Roll x3",
        "NHS"
      ],
      "letters_of_recommendation": null,
      "essays": null,
      "decisions": {
        "acceptances": [
          {
            "university": "Rutgers University - Newark",
            "decision_plan": "N/A"
          },
          {
            "university": "Pittsburgh University",
            "decision_plan": "N/A"
          },
          {
            "university": "Duke University",
            "decision_plan": "N/A"
          }
        ],
        "waitlists": null,
        "rejections": null
      },
      "additional_information": null
    }
  },

  {
    "post_text": "Government Major ðŸŽ“\n\nDemographics\n\nWhite\nMale\n200k+\nPublic School\nAcademics\n\n35 ACT\n13 AP's\n3.92 W\nExtracurriculars\n\n1. President Speech & Debate\n\n2. Debate Captain\n\n3. Legislative Intern\n\n4. Intern Local County Democratic Committee\n\n5. Fellow for a National advocacy organization\n\n6. Political social media organization\n\n7. Research\n\n8. Head of Building FTC Robotics Team 9th and 10th grade\n\nAwards\n\n1. Top 5 in state for debate event\n\n2. NSDA All-State\n\n3. State Seal Of Biliteracy - Anticipated\n\n4. AP Scholar With Distinction\n\n5. National Honor Society\n\n6. National Spanish Honor Society\n\nAcceptances\n\n1. Binghamton\n\n2. Dartmouth",
    "structured_profile": {
      "demographics": {
        "gender": "Male",
        "race_ethnicity": "White",
        "residence": null,
        "income_bracket": "200k+",
        "type_of_school": "Public School",
        "hooks": null,
        "intended_majors": "Government"
      },
      "academics": {
        "gpa": {
          "unweighted": null,
          "weighted": 3.92
        },
        "course_count": {
          "honors": null,
          "ap": 13,
          "ib": null,
          "dual_enrollment": null
        },
        "senior_year_course_load": null
      },
      "standardized_testing": {
        "sat_i": null,
        "act": 35
      },
      "extracurriculars": [
        "President Speech & Debate",
        "Debate Captain",
        "Legislative Intern",
        "Intern Local County Democratic Committee",
        "Fellow for a National advocacy organization",
        "Political social media organization",
        "Research",
        "Head of Building FTC Robotics Team 9th and 10th grade"
      ],
      "awards_honors": [
        "Top 5 in state for debate event",
        "NSDA All-State",
        "State Seal Of Biliteracy - Anticipated",
        "AP Scholar With Distinction",
        "National Honor Society",
        "National Spanish Honor Society"
      ],
      "letters_of_recommendation": null,
      "essays": null,
      "decisions": {
        "acceptances": [
          {
            "university": "Binghamton",
            "decision_plan": "N/A"
          },
          {
            "university": "Dartmouth",
            "decision_plan": "N/A"
          }
        ],
        "waitlists": null,
        "rejections": null
      },
      "additional_information": null
    }
  },

  {
    "post_text": "Environmental Science Major ðŸŽ“\n\nDemographics\n\nAsian\nMale\n0-50k\nPrivate School\nAcademics\n\n1560 SAT\n3 AP's\n4 UW\n4.7 W\nExtracurriculars\n\n1. Co-lead of local environmental organization\n\n2. Art core team member for national environmental organization\n\n3. Researcher with professor at local college (buoy data mapping)\n\n4. Researcher with professor at local college (lithium-ion batteries)\n\n5. Debate captain\n\n6. Debate non-profit member\n\n7. Curriculum editor\n\n8. ESG researcher\n\n9. Research with local air sensing station\n\n10. School environmental group leader\n\nAwards\n\n1. NYT writing competition winner\n\n2. Intl poetry contest finalist\n\n3. National essay contest honorable mention\n\n4. 2x state debate champion\n\n5. National debate award\n\nAcceptances\n\n1. Brown",
    "structured_profile": {
      "demographics": {
        "gender": "Male",
        "race_ethnicity": "Asian",
        "residence": null,
        "income_bracket": "0-50k",
        "type_of_school": "Private School",
        "hooks": null,
        "intended_majors": "Environmental Science"
      },
      "academics": {
        "gpa": {
          "unweighted": 4.0,
          "weighted": 4.7
        },
        "course_count": {
          "honors": null,
          "ap": 3,
          "ib": null,
          "dual_enrollment": null
        },
        "senior_year_course_load": null
      },
      "standardized_testing": {
        "sat_i": {
          "total": 1560,
          "reading_writing": null,
          "math": null
        },
        "act": null
      },
      "extracurriculars": [
        "Co-lead of local environmental organization",
        "Art core team member for national environmental organization",
        "Researcher with professor at local college (buoy data mapping)",
        "Researcher with professor at local college (lithium-ion batteries)",
        "Debate captain",
        "Debate non-profit member",
        "Curriculum editor",
        "ESG researcher",
        "Research with local air sensing station",
        "School environmental group leader"
      ],
      "awards_honors": [
        "NYT writing competition winner",
        "Intl poetry contest finalist",
        "National essay contest honorable mention",
        "2x state debate champion",
        "National debate award"
      ],
      "letters_of_recommendation": null,
      "essays": null,
      "decisions": {
        "acceptances": [
          {
            "university": "Brown",
            "decision_plan": "RD"
          }
        ],
        "waitlists": null,
        "rejections": null
      },
      "additional_information": null
    }
  },

  {
    "post_text": "Neuroscience Major ðŸŽ“\n\nDemographics\n\nAsian\nFemale\n0-50k\nPublic School\nAcademics\n\n29 ACT\n12 AP's\n3.76 UW\n4.11 W\nExtracurriculars\n\n1. iyna summer program dual enrollment\n\n2. wrote a grant proposal\n\n3. own research: systematic review\n\n4. period poverty initiative co-founder/director of outreach\n\n5. national beta chapter president\n\n6. unicef chapter president\n\n7. volunteering at a suicide prevention hotline\n\n8. volunteer at a hospice\n\n9. ylc at make-a-wish\n\n10. marketing internship\n\n11. badminton classes\n\nAwards\n\n1. DECA: 2nd in region\n\n2. 10th in state\n\n3. TEDx Speaker\n\n4. AP Scholar with Honors\n\n5. academic awards by school\n\n6. certifications\n\nAcceptances\n\n1. Augusta\n\n2. Mercer\n\n3. Wayne State\n\n4. Dominican University\n\n5. USFCA\n\n6. GSU Honors\n\n7. Stony Brook\n\n8. Rutgers\n\n9. OXFORD COLLEGE @ EMORY ED1",
    "structured_profile": {
      "demographics": {
        "gender": "Female",
        "race_ethnicity": "Asian",
        "residence": null,
        "income_bracket": "0-50k",
        "type_of_school": "Public School",
        "hooks": null,
        "intended_majors": "Neuroscience"
      },
      "academics": {
        "gpa": {
          "unweighted": 3.76,
          "weighted": 4.11
        },
        "course_count": {
          "honors": null,
          "ap": 12,
          "ib": null,
          "dual_enrollment": null
        },
        "senior_year_course_load": null
      },
      "standardized_testing": {
        "sat_i": null,
        "act": 29
      },
      "extracurriculars": [
        "iyna summer program dual enrollment",
        "Wrote a grant proposal",
        "Own research: systematic review",
        "Period poverty initiative co-founder/director of outreach",
        "National beta chapter president",
        "Unicef chapter president",
        "Volunteering at a suicide prevention hotline",
        "Volunteer at a hospice",
        "YLC at Make-A-Wish",
        "Marketing internship",
        "Badminton classes"
      ],
      "awards_honors": [
        "DECA: 2nd in region",
        "10th in state",
        "TEDx Speaker",
        "AP Scholar with Honors",
        "Academic awards by school",
        "Certifications"
      ],
      "letters_of_recommendation": null,
      "essays": null,
      "decisions": {
        "acceptances": [
          {
            "university": "Augusta",
            "decision_plan": "N/A"
          },
          {
            "university": "Mercer",
            "decision_plan": "N/A"
          },
          {
            "university": "Wayne State",
            "decision_plan": "N/A"
          },
          {
            "university": "Dominican University",
            "decision_plan": "N/A"
          },
          {
            "university": "USFCA",
            "decision_plan": "N/A"
          },
          {
            "university": "GSU Honors",
            "decision_plan": "N/A"
          },
          {
            "university": "Stony Brook",
            "decision_plan": "N/A"
          },
          {
            "university": "Rutgers",
            "decision_plan": "N/A"
          },
          {
            "university": "OXFORD COLLEGE @ EMORY",
            "decision_plan": "ED"
          }
        ],
        "waitlists": null,
        "rejections": null
      },
      "additional_information": null
    }
  },

  {
    "post_text": "Biology Major ðŸŽ“\n\nDemographics\n\nAsian\nFemale\n200k+\nPublic School\nAcademics\n\n1550 SAT\n36 ACT\n3.35 UW\n3.851 W\nExtracurriculars\n\n1. Extremely talented handler of venomous reptiles (i.e snakes\n\n2. lizards\n\n3. etc)400k on instagram from this\n\nAwards\n\n1. N/A\n\nAcceptances\n\n1. MIT",
    "structured_profile": {
      "demographics": {
        "gender": "Female",
        "race_ethnicity": "Asian",
        "residence": null,
        "income_bracket": "200k+",
        "type_of_school": "Public School",
        "hooks": null,
        "intended_majors": "Biology"
      },
      "academics": {
        "gpa": {
          "unweighted": 3.35,
          "weighted": 3.851
        },
        "course_count": null,
        "senior_year_course_load": null
      },
      "standardized_testing": {
        "sat_i": {
          "total": 1550,
          "reading_writing": null,
          "math": null
        },
        "act": 36
      },
      "extracurriculars": [
        "Extremely talented handler of venomous reptiles (i.e snakes, lizards, etc) 400k on instagram from this"
      ],
      "awards_honors": null,
      "letters_of_recommendation": null,
      "essays": null,
      "decisions": {
        "acceptances": [
          {
            "university": "MIT",
            "decision_plan": "N/A"
          }
        ],
        "waitlists": null,
        "rejections": null
      },
      "additional_information": null
    }
  },

  {
    "post_text": "Computer Science Major ðŸŽ“\n\nDemographics\n\nAsian\nMale\n200k+\nPublic School\nAcademics\n\n1530 SAT\n9 AP's\n3.94 UW\nExtracurriculars\n\n1. Selective MIT summer program\n\n2. Research under MIT professor\n\n3. All-state band\n\n4. President of programming club\n\n5. Science bowl captain\n\n6. Tutoring club head of STEM\n\n7. Internship at large data company\n\n8. Secretary of Model UN club\n\n9. Kumon job\n\n10. Assortment of personal projects on GitHub\n\nAwards\n\n1. ISEF qualified\n\n2. Science bowl national qualified\n\n3. USACO silver\n\n4. National Merit\n\n5. Random Model UN awards\n\nAcceptances\n\n1. Deferred MIT",
    "structured_profile": {
      "demographics": {
        "gender": "Male",
        "race_ethnicity": "Asian",
        "residence": null,
        "income_bracket": "200k+",
        "type_of_school": "Public School",
        "hooks": null,
        "intended_majors": "Computer Science"
      },
      "academics": {
        "gpa": {
          "unweighted": 3.94,
          "weighted": null
        },
        "course_count": {
          "honors": null,
          "ap": 9,
          "ib": null,
          "dual_enrollment": null
        },
        "senior_year_course_load": null
      },
      "standardized_testing": {
        "sat_i": {
          "total": 1530,
          "reading_writing": null,
          "math": null
        },
        "act": null
      },
      "extracurriculars": [
        "Selective MIT summer program",
        "Research under MIT professor",
        "All-state band",
        "President of programming club",
        "Science bowl captain",
        "Tutoring club head of STEM",
        "Internship at large data company",
        "Secretary of Model UN club",
        "Kumon job",
        "Assortment of personal projects on GitHub"
      ],
      "awards_honors": [
        "ISEF qualified",
        "Science bowl national qualified",
        "USACO silver",
        "National Merit",
        "Random Model UN awards"
      ],
      "letters_of_recommendation": null,
      "essays": null,
      "decisions": null,
      "additional_information": "Deferred MIT"
    }
  },

  {
    "post_text": "N/A Major ðŸŽ“\n\nDemographics\n\nAsian\nMale\n100k-200k\nPrivate School\nAcademics\n\n1570 SAT\n3.83 UW\nExtracurriculars\n\n1. Passion Project/Music Producer\n\n2. Persuasive Marketing Research\n\n3. Co-Founder & CMO of social app\n\n4. Marketing Intern\n\n5. Co-Founder & Director of non-profit\n\n6. Co-Founder & CMO of media platform\n\n7. Jazz Band Bass Player\n\n8. President & Co-Founder\n\n9. Entrepreneurship Club\n\n10. Restaurant Team Member\n\n11. Varsity Tennis Captain\n\nAwards\n\n1. finalist for int business comp\n\n2. semi-finalist for another int business comp\n\n3. Scholastic Arts & Writing Gold Key\n\nAcceptances\n\n1. Duke",
    "structured_profile": {
      "demographics": {
        "gender": "Male",
        "race_ethnicity": "Asian",
        "residence": null,
        "income_bracket": "100k-200k",
        "type_of_school": "Private School",
        "hooks": null,
        "intended_majors": null
      },
      "academics": {
        "gpa": {
          "unweighted": 3.83,
          "weighted": null
        },
        "course_count": null,
        "senior_year_course_load": null
      },
      "standardized_testing": {
        "sat_i": {
          "total": 1570,
          "reading_writing": null,
          "math": null
        },
        "act": null
      },
      "extracurriculars": [
        "Passion Project/Music Producer",
        "Persuasive Marketing Research",
        "Co-Founder & CMO of social app",
        "Marketing Intern",
        "Co-Founder & Director of non-profit",
        "Co-Founder & CMO of media platform",
        "Jazz Band Bass Player",
        "President & Co-Founder",
        "Entrepreneurship Club",
        "Restaurant Team Member",
        "Varsity Tennis Captain"
      ],
      "awards_honors": [
        "finalist for int business comp",
        "semi-finalist for another int business comp",
        "Scholastic Arts & Writing Gold Key"
      ],
      "letters_of_recommendation": null,
      "essays": null,
      "decisions": {
        "acceptances": [
          {
            "university": "Duke",
            "decision_plan": "RD"
          }
        ],
        "waitlists": null,
        "rejections": null
      },
      "additional_information": null
    }
  },

  {
    "post_text": "Theater Major ðŸŽ“\n\nDemographics\n\nWhite\nFemale\n50k-100k\nPrivate School\nAcademics\n\n1250 SAT\n3.8 UW\nExtracurriculars\n\n1. Work Program Head\n\n2. Stage Manager/Theater Tech/Stagehand\n\n3. Diabetes Camp Counselor\n\n4. Lead Viola Player in Musical Ensemble\n\n5. School Tour Guide\n\n6. All School Trip Planning Committee\n\n7. Student Agriculture Head\n\n8. Leader of Fiber Arts Club\n\n9. Information/Tourist Booth Attendant\n\n10. Volunteering with organizing and distributing winter coats to kids in my community\n\nAwards\n\n1. National Rural and Small Town Recognition Program\n\n2. Girl Scout Silver Award\n\nAcceptances\n\n1. Lesley University\n\n2. Nazareth University\n\n3. Montclair State University\n\n4. Suny Oswego\n\n5. SKIDMORE COLLEGE",
    "structured_profile": {
      "demographics": {
        "gender": "Female",
        "race_ethnicity": "White",
        "residence": null,
        "income_bracket": "50k-100k",
        "type_of_school": "Private School",
        "hooks": null,
        "intended_majors": "Theater"
      },
      "academics": {
        "gpa": {
          "unweighted": 3.8,
          "weighted": null
        },
        "course_count": null,
        "senior_year_course_load": null
      },
      "standardized_testing": {
        "sat_i": {
          "total": 1250,
          "reading_writing": null,
          "math": null
        },
        "act": null
      },
      "extracurriculars": [
        "Work Program Head",
        "Stage Manager/Theater Tech/Stagehand",
        "Diabetes Camp Counselor",
        "Lead Viola Player in Musical Ensemble",
        "School Tour Guide",
        "All School Trip Planning Committee",
        "Student Agriculture Head",
        "Leader of Fiber Arts Club",
        "Information/Tourist Booth Attendant",
        "Volunteering with organizing and distributing winter coats to kids in my community"
      ],
      "awards_honors": [
        "National Rural and Small Town Recognition Program",
        "Girl Scout Silver Award"
      ],
      "letters_of_recommendation": null,
      "essays": null,
      "decisions": {
        "acceptances": [
          {
            "university": "Lesley University",
            "decision_plan": "N/A"
          },
          {
            "university": "Nazareth University",
            "decision_plan": "N/A"
          },
          {
            "university": "Montclair State University",
            "decision_plan": "N/A"
          },
          {
            "university": "Suny Oswego",
            "decision_plan": "N/A"
          },
          {
            "university": "SKIDMORE COLLEGE",
            "decision_plan": "N/A"
          }
        ],
        "waitlists": null,
        "rejections": null
      },
      "additional_information": null
    }
  },

  {
    "post_text": "Computer Science Major ðŸŽ“\n\nDemographics\n\nAfrican American\nFemale\n100k-200k\nPublic School\nAcademics\n\n34 ACT\n5 AP's\n3.96 UW\n4.53 W\nExtracurriculars\n\n1. CS Club Founder and President\n\n2. Orchestra and Solo Violin\n\n3. Mock Trial Attorney\n\n4. Selective Summer Program at MIT\n\n5. Math Instructor\n\n6. Volunteer Math and Physics Tutor\n\n7. Software Engineering Group Project\n\n8. Summer Externship\n\n9. Published a fictional book on Amazon\n\n10. MIT's fly-in (WISE)\n\nAwards\n\n1. Commended Student\n\n2. National African American Recognition Program\n\n3. Won local engineering competition 2x\n\n4. AP Scholar with Distinction\n\n5. Student of the Month\n\nAcceptances\n\n1. THE Ohio State University\n\n2. Case Western Reserve University\n\n3. MIT",
    "structured_profile": {
      "demographics": {
        "gender": "Female",
        "race_ethnicity": "African American",
        "residence": null,
        "income_bracket": "100k-200k",
        "type_of_school": "Public School",
        "hooks": null,
        "intended_majors": "Computer Science"
      },
      "academics": {
        "gpa": {
          "unweighted": 3.96,
          "weighted": 4.53
        },
        "course_count": {
          "honors": null,
          "ap": 5,
          "ib": null,
          "dual_enrollment": null
        },
        "senior_year_course_load": null
      },
      "standardized_testing": {
        "sat_i": null,
        "act": 34
      },
      "extracurriculars": [
        "CS Club Founder and President",
        "Orchestra and Solo Violin",
        "Mock Trial Attorney",
        "Selective Summer Program at MIT",
        "Math Instructor",
        "Volunteer Math and Physics Tutor",
        "Software Engineering Group Project",
        "Summer Externship",
        "Published a fictional book on Amazon",
        "MIT's fly-in (WISE)"
      ],
      "awards_honors": [
        "Commended Student",
        "National African American Recognition Program",
        "Won local engineering competition 2x",
        "AP Scholar with Distinction",
        "Student of the Month"
      ],
      "letters_of_recommendation": null,
      "essays": null,
      "decisions": {
        "acceptances": [
          {
            "university": "THE Ohio State University",
            "decision_plan": "N/A"
          },
          {
            "university": "Case Western Reserve University",
            "decision_plan": "N/A"
          },
          {
            "university": "MIT",
            "decision_plan": "N/A"
          }
        ],
        "waitlists": null,
        "rejections": null
      },
      "additional_information": null
    }
  },

  {
    "post_text": "Physics Major ðŸŽ“\n\nDemographics\n\nWhite\nMale\n0-50k\nPublic School\nAcademics\n\n35 ACT\n6 AP's\n3.95 UW\n4 W\nExtracurriculars\n\n1. Varsity Soccer 2 years\n\n2. co captain\n\n3. second team all conference\n\n4. Speech team 2 years\n\n5. state gold medal\n\n6. FIRST Robotics 5 years\n\n7. team captain\n\n8. runner up in an off season comp\n\n9. School play for a year\n\nAwards\n\n1. National Merit Semifinalist\n\n2. Honors Math competition Gold Medal\n\n3. UWP Math contest Gold Medal\n\nAcceptances\n\n1. Northwestern",
    "structured_profile": {
      "demographics": {
        "gender": "Male",
        "race_ethnicity": "White",
        "residence": null,
        "income_bracket": "0-50k",
        "type_of_school": "Public School",
        "hooks": null,
        "intended_majors": "Physics"
      },
      "academics": {
        "gpa": {
          "unweighted": 3.95,
          "weighted": 4.0
        },
        "course_count": {
          "honors": null,
          "ap": 6,
          "ib": null,
          "dual_enrollment": null
        },
        "senior_year_course_load": null
      },
      "standardized_testing": {
        "sat_i": null,
        "act": 35
      },
      "extracurriculars": [
        "Varsity Soccer (2 years, co-captain, second team all-conference)",
        "Speech team (2 years, state gold medal)",
        "FIRST Robotics (5 years, team captain, runner up in an off season comp)",
        "School play (1 year)"
      ],
      "awards_honors": [
        "National Merit Semifinalist",
        "Honors Math competition Gold Medal",
        "UWP Math contest Gold Medal"
      ],
      "letters_of_recommendation": null,
      "essays": null,
      "decisions": {
        "acceptances": [
          {
            "university": "Northwestern",
            "decision_plan": "N/A"
          }
        ],
        "waitlists": null,
        "rejections": null
      },
      "additional_information": null
    }
  },

  {
    "post_text": "Engineering Major ðŸŽ“\n\nDemographics\n\nAsian\nMale\n0-50k\nPublic School\nAcademics\n\n1590 SAT\n13 AP's\n4.6 W\nExtracurriculars\n\n1. Big impactful materials science research project that gained investors and won awards\n\n2. Research at T-3 University in mat sci\n\n3. Startup in research with 3-digit user count and small investments\n\n4. Research at local uni with 1st author published and won science fair awards\n\n5. Research leader with NASA in a winning competition\n\n6. Research at local uni with upcoming first author publication\n\n7. International community service project co-founded\n\n8. State research-access pipeline organization founder\n\n9. Robotics participation in world qualifiers\n\n10. Sport participation\n\nAwards\n\n1. Something in the same level of Regeneron STS/ISEF Final Award Winner - national\n\n2. NASA Competition winner - national\n\n3. First Author and Science recognition - intl.\n\n4. Won some startup/investment fellowship - intl.\n\n5. Placed high in physics competition - intl.\n\n6. Coke Semi Finalists and state humanitarian awards for MIT\n\nAcceptances\n\n1. MIT",
    "structured_profile": {
      "demographics": {
        "gender": "Male",
        "race_ethnicity": "Asian",
        "residence": null,
        "income_bracket": "0-50k",
        "type_of_school": "Public School",
        "hooks": null,
        "intended_majors": "Engineering"
      },
      "academics": {
        "gpa": {
          "unweighted": null,
          "weighted": 4.6
        },
        "course_count": {
          "honors": null,
          "ap": 13,
          "ib": null,
          "dual_enrollment": null
        },
        "senior_year_course_load": null
      },
      "standardized_testing": {
        "sat_i": {
          "total": 1590,
          "reading_writing": null,
          "math": null
        },
        "act": null
      },
      "extracurriculars": [
        "Big impactful materials science research project that gained investors and won awards",
        "Research at T-3 University in mat sci",
        "Startup in research with 3-digit user count and small investments",
        "Research at local uni with 1st author published and won science fair awards",
        "Research leader with NASA in a winning competition",
        "Research at local uni with upcoming first author publication",
        "International community service project co-founded",
        "State research-access pipeline organization founder",
        "Robotics participation in world qualifiers",
        "Sport participation"
      ],
      "awards_honors": [
        "Something in the same level of Regeneron STS/ISEF Final Award Winner - national",
        "NASA Competition winner - national",
        "First Author and Science recognition - intl.",
        "Won some startup/investment fellowship - intl.",
        "Placed high in physics competition - intl.",
        "Coke Semi Finalists and state humanitarian awards for MIT"
      ],
      "letters_of_recommendation": null,
      "essays": null,
      "decisions": {
        "acceptances": [
          {
            "university": "MIT",
            "decision_plan": "N/A"
          }
        ],
        "waitlists": null,
        "rejections": null
      },
      "additional_information": null
    }
  },

  {
    "post_text": "Computer Science Major ðŸŽ“\n\nDemographics\n\nAsian\nMale\n0-50k\nPrivate School\nAcademics\n\n1530 SAT\n2 AP's\n3.64 UW\nExtracurriculars\n\n1. Head Boy\n\n2. Student Council\n\n3. Pres\n\n4. CS Club\n\n5. Researcher\n\n6. Open Source Developer\n\n7. Paid Frontend Engineering Intern\n\n8. Lead organizer of Regional hackathon\n\n9. Founder of Stem Club\n\n10. Captain of Swim Team\n\n11. Senior member of school's art club\n\n12. VC Analyst\n\n13. Paid Software Eng at a healthcare startup\n\nAwards\n\n1. Apple's WWDC Swift student challenge global winner\n\n2. Regional Runner-up and Global Finalist Honorable Mention at NASA SpaceApps Challenge 2022\n\n3. HackTheNorth\n\n4. UWaterloo EdgeML runner up\n\n5. Google Code-in Global Finalist\n\n6. Best Project in state at **REDACTED**\n\n7. Scholar Award\n\n8. Excellence in Computers\n\n9. Special Achievement Award\n\nAcceptances\n\n1. MIT\n\n2. Stanford\n\n3. Harvard\n\n4. Berkeley\n\n5. Cornell\n\n6. Duke\n\n7. Northwestern\n\n8. GaTech\n\n9. UIUC\n\n10. Purdue\n\n11. Dartmouth",
    "structured_profile": {
      "demographics": {
        "gender": "Male",
        "race_ethnicity": "Asian",
        "residence": null,
        "income_bracket": "0-50k",
        "type_of_school": "Private School",
        "hooks": null,
        "intended_majors": "Computer Science"
      },
      "academics": {
        "gpa": {
          "unweighted": 3.64,
          "weighted": null
        },
        "course_count": {
          "honors": null,
          "ap": 2,
          "ib": null,
          "dual_enrollment": null
        },
        "senior_year_course_load": null
      },
      "standardized_testing": {
        "sat_i": {
          "total": 1530,
          "reading_writing": null,
          "math": null
        },
        "act": null
      },
      "extracurriculars": [
        "Head Boy",
        "Student Council",
        "President of CS Club",
        "Researcher",
        "Open Source Developer",
        "Paid Frontend Engineering Intern",
        "Lead organizer of Regional hackathon",
        "Founder of Stem Club",
        "Captain of Swim Team",
        "Senior member of school's art club",
        "VC Analyst",
        "Paid Software Eng at a healthcare startup"
      ],
      "awards_honors": [
        "Apple's WWDC Swift student challenge global winner",
        "Regional Runner-up and Global Finalist Honorable Mention at NASA SpaceApps Challenge 2022",
        "HackTheNorth",
        "UWaterloo EdgeML runner up",
        "Google Code-in Global Finalist",
        "Best Project in state at **REDACTED**",
        "Scholar Award",
        "Excellence in Computers",
        "Special Achievement Award"
      ],
      "letters_of_recommendation": null,
      "essays": null,
      "decisions": {
        "acceptances": [
          {
            "university": "MIT",
            "decision_plan": "N/A"
          },
          {
            "university": "Stanford",
            "decision_plan": "N/A"
          },
          {
            "university": "Harvard",
            "decision_plan": "N/A"
          },
          {
            "university": "Berkeley",
            "decision_plan": "N/A"
          },
          {
            "university": "Cornell",
            "decision_plan": "N/A"
          },
          {
            "university": "Duke",
            "decision_plan": "N/A"
          },
          {
            "university": "Northwestern",
            "decision_plan": "N/A"
          },
          {
            "university": "GaTech",
            "decision_plan": "N/A"
          },
          {
            "university": "UIUC",
            "decision_plan": "N/A"
          },
          {
            "university": "Purdue",
            "decision_plan": "N/A"
          },
          {
            "university": "Dartmouth",
            "decision_plan": "N/A"
          }
        ],
        "waitlists": null,
        "rejections": null
      },
      "additional_information": null
    }
  },

  {
    "post_text": "Computer Science Major ðŸŽ“\n\nDemographics\n\nAsian\nMale\n200k+\nPublic School\nAcademics\n\n1590 SAT\n36 ACT\n19 AP's\n4 UW\n4.98 W\nExtracurriculars\n\n1. Independent Research on genetics & health disparities\n\n2. Co-Founder/Developer of AI web app\n\n3. President of STEM competition club & Head Coach of MS chapter of club\n\n4. Speech & Debate\n\n5. Co-President of Math Team & Math Honors Society\n\n6. Clarinet Player & member of Youth Orchestra\n\n7. Co-President of World Cultures Club\n\n8. Volunteer at local nursing home\n\n9. Caretaker for Grandma\n\nAwards\n\n1. Coca-Cola Scholars Semifinalist\n\n2. 3x TOC Qualifier\n\n3. Runner Up at State Science Research Competition\n\n4. 2x Statistics Award at Science Fair\n\n5. 3rd Place Winner in Video Contest on Teen Mental Health\n\nAcceptances\n\n1. UPenn M&T (wharton + engineering)",
    "structured_profile": {
      "demographics": {
        "gender": "Male",
        "race_ethnicity": "Asian",
        "residence": null,
        "income_bracket": "200k+",
        "type_of_school": "Public School",
        "hooks": null,
        "intended_majors": "Computer Science"
      },
      "academics": {
        "gpa": {
          "unweighted": 4.0,
          "weighted": 4.98
        },
        "course_count": {
          "honors": null,
          "ap": 19,
          "ib": null,
          "dual_enrollment": null
        },
        "senior_year_course_load": null
      },
      "standardized_testing": {
        "sat_i": {
          "total": 1590,
          "reading_writing": null,
          "math": null
        },
        "act": 36
      },
      "extracurriculars": [
        "Independent Research on genetics & health disparities",
        "Co-Founder/Developer of AI web app",
        "President of STEM competition club & Head Coach of MS chapter of club",
        "Speech & Debate",
        "Co-President of Math Team & Math Honors Society",
        "Clarinet Player & member of Youth Orchestra",
        "Co-President of World Cultures Club",
        "Volunteer at local nursing home",
        "Caretaker for Grandma"
      ],
      "awards_honors": [
        "Coca-Cola Scholars Semifinalist",
        "3x TOC Qualifier",
        "Runner Up at State Science Research Competition",
        "2x Statistics Award at Science Fair",
        "3rd Place Winner in Video Contest on Teen Mental Health"
      ],
      "letters_of_recommendation": null,
      "essays": null,
      "decisions": {
        "acceptances": [
          {
            "university": "UPenn M&T (wharton + engineering)",
            "decision_plan": "N/A"
          }
        ],
        "waitlists": null,
        "rejections": null
      },
      "additional_information": null
    }
  },

  {
    "post_text": "Computer Science Major ðŸŽ“\n\nDemographics\n\nAsian\nFemale\n200k+\nPrivate School\nAcademics\n\n1550 SAT\n34 ACT\n14 AP's\n4 UW\n4.7 W\nExtracurriculars\n\n1. Music (violin)\n\n2. Game development\n\n3. COSMOS summer program\n\n4. Pop music performance group\n\n5. Research assistant for linguistics lab\n\n6. Japanese Saturday school\n\n7. Creative writing\n\n8. Music composition\n\n9. Community Service\n\n10. Journalism\n\nAwards\n\n1. NMS semifinalist\n\n2. North American Computational Linguistics Olympiad\n\n3. Scholastic Art and Writing (honorable mentions)\n\n4. NHS\n\n5. AP scholar with distinction\n\nAcceptances\n\n1. MIT\n\n2. Drexel",
    "structured_profile": {
      "demographics": {
        "gender": "Female",
        "race_ethnicity": "Asian",
        "residence": null,
        "income_bracket": "200k+",
        "type_of_school": "Private School",
        "hooks": null,
        "intended_majors": "Computer Science"
      },
      "academics": {
        "gpa": {
          "unweighted": 4.0,
          "weighted": 4.7
        },
        "course_count": {
          "honors": null,
          "ap": 14,
          "ib": null,
          "dual_enrollment": null
        },
        "senior_year_course_load": null
      },
      "standardized_testing": {
        "sat_i": {
          "total": 1550,
          "reading_writing": null,
          "math": null
        },
        "act": 34
      },
      "extracurriculars": [
        "Music (violin)",
        "Game development",
        "COSMOS summer program",
        "Pop music performance group",
        "Research assistant for linguistics lab",
        "Japanese Saturday school",
        "Creative writing",
        "Music composition",
        "Community Service",
        "Journalism"
      ],
      "awards_honors": [
        "NMS semifinalist",
        "North American Computational Linguistics Olympiad",
        "Scholastic Art and Writing (honorable mentions)",
        "NHS",
        "AP scholar with distinction"
      ],
      "letters_of_recommendation": null,
      "essays": null,
      "decisions": {
        "acceptances": [
          {
            "university": "MIT",
            "decision_plan": "N/A"
          },
          {
            "university": "Drexel",
            "decision_plan": "N/A"
          }
        ],
        "waitlists": null,
        "rejections": null
      },
      "additional_information": null
    }
  },

  {
    "post_text": "Computer Science Major ðŸŽ“\n\nDemographics\n\nAsian\nMale\n200k+\nPublic School\nAcademics\n\n1550 SAT\n10 AP's\n4 UW\nExtracurriculars\n\n1. Research internship at a national laboratory\n\n2. State science fair research project\n\n3. Research project with a professor on formal proofs and verification of algorithms\n\n4. Internship at a local software company\n\n5. President of competitive programming club at high school\n\n6. Science Olympiad\n\n7. Paid mathematics summer camp on graph theory\n\n8. Paid AI summer camp\n\n9. FIRST robotics\n\n10. Volunteering at various coding events\n\nAwards\n\n1. USA Computing Olympiad (USACO) Gold Division\n\n2. State science fair first place\n\n3. Congressional App Challenge\n\n4. National Merit commended\n\nAcceptances\n\n1. Rice University",
    "structured_profile": {
      "demographics": {
        "gender": "Male",
        "race_ethnicity": "Asian",
        "residence": null,
        "income_bracket": "200k+",
        "type_of_school": "Public School",
        "hooks": null,
        "intended_majors": "Computer Science"
      },
      "academics": {
        "gpa": {
          "unweighted": 4.0,
          "weighted": null
        },
        "course_count": {
          "honors": null,
          "ap": 10,
          "ib": null,
          "dual_enrollment": null
        },
        "senior_year_course_load": null
      },
      "standardized_testing": {
        "sat_i": {
          "total": 1550,
          "reading_writing": null,
          "math": null
        },
        "act": null
      },
      "extracurriculars": [
        "Research internship at a national laboratory",
        "State science fair research project",
        "Research project with a professor on formal proofs and verification of algorithms",
        "Internship at a local software company",
        "President of competitive programming club at high school",
        "Science Olympiad",
        "Paid mathematics summer camp on graph theory",
        "Paid AI summer camp",
        "FIRST robotics",
        "Volunteering at various coding events"
      ],
      "awards_honors": [
        "USA Computing Olympiad (USACO) Gold Division",
        "State science fair first place",
        "Congressional App Challenge",
        "National Merit commended"
      ],
      "letters_of_recommendation": null,
      "essays": null,
      "decisions": {
        "acceptances": [
          {
            "university": "Rice University",
            "decision_plan": "N/A"
          }
        ],
        "waitlists": null,
        "rejections": null
      },
      "additional_information": null
    }
  },

  {
    "post_text": "Biology Major ðŸŽ“\n\nDemographics\n\nWhite\nMale\n50k-100k\nPublic School\nAcademics\n\n1440 SAT\n34 ACT\n2 AP's\n4 UW\nExtracurriculars\n\n1. National Beta Club (President\n\n2. Historian\n\n3. Reporter)\n\n4. Theater (Leading role)\n\n5. Class President\n\n6. Choir (Bass Vocal Section Leader)\n\n7. HOSA (Vice President)\n\n8. Environmental Sustainability Club (Founder\n\n9. President)\n\n10. Tennis\n\n11. Vanderbilt Summer Academy\n\n12. Art Club (President)\n\n13. Student Advisory Council Member\n\nAwards\n\n1. Valedictorian\n\n2. 3rd place National Beta Convention Drawing\n\n3. 5th place National Beta Convention On-site Drawing\n\n4. 2nd and 3rd place National Beta Convention Show Choir\n\nAcceptances\n\n1. UTM\n\n2. University of Memphis\n\n3. Mississippi State University\n\n4. Ole Miss\n\n5. UTK\n\n6. MTSU\n\n7. APSU\n\n8. Vanderbilt",
    "structured_profile": {
      "demographics": {
        "gender": "Male",
        "race_ethnicity": "White",
        "residence": null,
        "income_bracket": "50k-100k",
        "type_of_school": "Public School",
        "hooks": null,
        "intended_majors": "Biology"
      },
      "academics": {
        "gpa": {
          "unweighted": 4.0,
          "weighted": null
        },
        "course_count": {
          "honors": null,
          "ap": 2,
          "ib": null,
          "dual_enrollment": null
        },
        "senior_year_course_load": null
      },
      "standardized_testing": {
        "sat_i": {
          "total": 1440,
          "reading_writing": null,
          "math": null
        },
        "act": 34
      },
      "extracurriculars": [
        "National Beta Club (President, Historian, Reporter)",
        "Theater (Leading role)",
        "Class President",
        "Choir (Bass Vocal Section Leader)",
        "HOSA (Vice President)",
        "Environmental Sustainability Club (Founder, President)",
        "Tennis",
        "Vanderbilt Summer Academy",
        "Art Club (President)",
        "Student Advisory Council Member"
      ],
      "awards_honors": [
        "Valedictorian",
        "3rd place National Beta Convention Drawing",
        "5th place National Beta Convention On-site Drawing",
        "2nd and 3rd place National Beta Convention Show Choir"
      ],
      "letters_of_recommendation": null,
      "essays": null,
      "decisions": {
        "acceptances": [
          {
            "university": "UTM",
            "decision_plan": "N/A"
          },
          {
            "university": "University of Memphis",
            "decision_plan": "N/A"
          },
          {
            "university": "Mississippi State University",
            "decision_plan": "N/A"
          },
          {
            "university": "Ole Miss",
            "decision_plan": "N/A"
          },
          {
            "university": "UTK",
            "decision_plan": "N/A"
          },
          {
            "university": "MTSU",
            "decision_plan": "N/A"
          },
          {
            "university": "APSU",
            "decision_plan": "N/A"
          },
          {
            "university": "Vanderbilt",
            "decision_plan": "N/A"
          }
        ],
        "waitlists": null,
        "rejections": null
      },
      "additional_information": null
    }
  },

  {
    "post_text": "Computer Science Major ðŸŽ“\n\nDemographics\n\nAsian\nMale\n200k+\nPublic School\nAcademics\n\n1540 SAT\n2 AP's\n4 UW\nExtracurriculars\n\n1. Private Violin Lessons\n\n2. School Tennis Team\n\n3. Video Game Coding Project\n\n4. Made a Website\n\n5. In an orchestra for a year\n\n6. Learned Java and Python\n\n7. Learned Piano on my own\n\n8. Cultural Cooking\n\n9. Mountain Biking for a Year\n\n10. Pickle Ball with Friends\n\nAwards\n\n1. N/A\n\nAcceptances\n\n1. ASU\n\n2. U of Arizona\n\n3. U of Pittsburgh\n\n4. U of Minnesota Twin Cities\n\n5. Rose-Hulman\n\n6. Oregon State\n\n7. Oregon State Honors College\n\n8. Northeastern",
    "structured_profile": {
      "demographics": {
        "gender": "Male",
        "race_ethnicity": "Asian",
        "residence": null,
        "income_bracket": "200k+",
        "type_of_school": "Public School",
        "hooks": null,
        "intended_majors": "Computer Science"
      },
      "academics": {
        "gpa": {
          "unweighted": 4.0,
          "weighted": null
        },
        "course_count": {
          "honors": null,
          "ap": 2,
          "ib": null,
          "dual_enrollment": null
        },
        "senior_year_course_load": null
      },
      "standardized_testing": {
        "sat_i": {
          "total": 1540,
          "reading_writing": null,
          "math": null
        },
        "act": null
      },
      "extracurriculars": [
        "Private Violin Lessons",
        "School Tennis Team",
        "Video Game Coding Project",
        "Made a Website",
        "In an orchestra for a year",
        "Learned Java and Python",
        "Learned Piano on my own",
        "Cultural Cooking",
        "Mountain Biking for a Year",
        "Pickle Ball with Friends"
      ],
      "awards_honors": [],
      "letters_of_recommendation": null,
      "essays": null,
      "decisions": {
        "acceptances": [
          {
            "university": "ASU",
            "decision_plan": "N/A"
          },
          {
            "university": "U of Arizona",
            "decision_plan": "N/A"
          },
          {
            "university": "U of Pittsburgh",
            "decision_plan": "N/A"
          },
          {
            "university": "U of Minnesota Twin Cities",
            "decision_plan": "N/A"
          },
          {
            "university": "Rose-Hulman",
            "decision_plan": "N/A"
          },
          {
            "university": "Oregon State",
            "decision_plan": "N/A"
          },
          {
            "university": "Oregon State Honors College",
            "decision_plan": "N/A"
          },
          {
            "university": "Northeastern",
            "decision_plan": "N/A"
          }
        ],
        "waitlists": null,
        "rejections": null
      },
      "additional_information": null
    }
  },

  {
    "post_text": "Psychology Major ðŸŽ“\n\nDemographics\n\nAsian\nFemale\n0-50k\nPublic School\nAcademics\n\n20 ACT\n3.96 UW\n4.64 W\nExtracurriculars\n\n1. Senior Class President\n\n2. President of Philosophy Club\n\n3. Vice President of NHS\n\n4. Shift-lead at cafe\n\n5. TRIO Upward Bound\n\n6. Social Justice Group\n\n7. Varsity Badminton Captain\n\nAwards\n\n1. Harvard Book Award\n\n2. School Award for IB Learner Profile Traits\n\nAcceptances\n\n1. University of Chicago",
    "structured_profile": {
      "demographics": {
        "gender": "Female",
        "race_ethnicity": "Asian",
        "residence": null,
        "income_bracket": "0-50k",
        "type_of_school": "Public School",
        "hooks": null,
        "intended_majors": "Psychology"
      },
      "academics": {
        "gpa": {
          "unweighted": 3.96,
          "weighted": 4.64
        },
        "course_count": null,
        "senior_year_course_load": null
      },
      "standardized_testing": {
        "sat_i": null,
        "act": 20
      },
      "extracurriculars": [
        "Senior Class President",
        "President of Philosophy Club",
        "Vice President of NHS",
        "Shift-lead at cafe",
        "TRIO Upward Bound",
        "Social Justice Group",
        "Varsity Badminton Captain"
      ],
      "awards_honors": [
        "Harvard Book Award",
        "School Award for IB Learner Profile Traits"
      ],
      "letters_of_recommendation": null,
      "essays": null,
      "decisions": {
        "acceptances": [
          {
            "university": "University of Chicago",
            "decision_plan": "N/A"
          }
        ],
        "waitlists": null,
        "rejections": null
      },
      "additional_information": null
    }
  },

  {
    "post_text": "Business Major ðŸŽ“\n\nDemographics\n\nAsian\nFemale\n50k-100k\nPublic School\nAcademics\n\n3 AP's\n4 UW\nExtracurriculars\n\n1. President & founder of a student managed fund\n\n2. President & Founder of a non-profit organization aimed to construct community libraries and promote reading habits\n\n3. President of a non-profit organization aimed to raise awareness on environmental protection\n\n4. 2 internships at a venture capital and a marketing agency\n\n5. 1 part-time job as a sale manager for a small startup\n\n6. Published 3 research papers on scientific journals\n\n7. Stock investor for 5 years\n\n8. Provide private tutor for A-Level Econ\n\n9. Mentored several teams to participate in business case competition\n\nAwards\n\n1. Bronze medalist - International Economics Olympiad (IEO)\n\n2. Bronze medalist and silver medalist - Vietnam National Economics Olympiad\n\n3. Runner up - Economics Category\n\n4. Immerse Education Essay Competition 2023\n\n5. Highly Commended Essay (Top 5%) - Economics Category\n\n6. Northeastern London Essay Competition 2023\n\n7. Bronze Medal - International Economics Olympiad Winter Challenge 2022\n\n8. Second Prize - BUV Innovation Competition 2021\n\n9. Finalist in Stevens Trading Day\n\n10. Top 200 teams in Wharton Investment Competition\n\nAcceptances\n\n1. Duke",
    "structured_profile": {
      "demographics": {
        "gender": "Female",
        "race_ethnicity": "Asian",
        "residence": null,
        "income_bracket": "50k-100k",
        "type_of_school": "Public School",
        "hooks": null,
        "intended_majors": "Business"
      },
      "academics": {
        "gpa": {
          "unweighted": 4.0,
          "weighted": null
        },
        "course_count": {
          "honors": null,
          "ap": 3,
          "ib": null,
          "dual_enrollment": null
        },
        "senior_year_course_load": null
      },
      "standardized_testing": null,
      "extracurriculars": [
        "President & founder of a student managed fund",
        "President & Founder of a non-profit organization aimed to construct community libraries and promote reading habits",
        "President of a non-profit organization aimed to raise awareness on environmental protection",
        "2 internships at a venture capital and a marketing agency",
        "1 part-time job as a sale manager for a small startup",
        "Published 3 research papers on scientific journals",
        "Stock investor for 5 years",
        "Provide private tutor for A-Level Econ",
        "Mentored several teams to participate in business case competition"
      ],
      "awards_honors": [
        "Bronze medalist - International Economics Olympiad (IEO)",
        "Bronze medalist and silver medalist - Vietnam National Economics Olympiad",
        "Runner up - Economics Category",
        "Immerse Education Essay Competition 2023",
        "Highly Commended Essay (Top 5%) - Economics Category",
        "Northeastern London Essay Competition 2023",
        "Bronze Medal - International Economics Olympiad Winter Challenge 2022",
        "Second Prize - BUV Innovation Competition 2021",
        "Finalist in Stevens Trading Day",
        "Top 200 teams in Wharton Investment Competition"
      ],
      "letters_of_recommendation": null,
      "essays": null,
      "decisions": {
        "acceptances": [
          {
            "university": "Duke",
            "decision_plan": "N/A"
          }
        ],
        "waitlists": null,
        "rejections": null
      },
      "additional_information": null
    }
  },

  {
    "post_text": "Economics Major ðŸŽ“\n\nDemographics\n\nAsian\nFemale\n50k-100k\nPublic School\nAcademics\n\n35 ACT\n12 AP's\n3.9 UW\n4.5 W\nExtracurriculars\n\n1. Singing opera for 12 years\n\n2. Prestigious camp for voice\n\n3. Choir officer\n\n4. Shift lead at work\n\n5. President of fundraising club\n\n6. President of political club\n\n7. Volunteer at church\n\n8. Member of selective choir\n\n9. Volunteer at food bank\n\nAwards\n\n1. #1 state wide for singing\n\n2. International ranking for singing\n\n3. Scholastic award\n\n4. Local art and writing award\n\nAcceptances\n\n1. Cornell University",
    "structured_profile": {
      "demographics": {
        "gender": "Female",
        "race_ethnicity": "Asian",
        "residence": null,
        "income_bracket": "50k-100k",
        "type_of_school": "Public School",
        "hooks": null,
        "intended_majors": "Economics"
      },
      "academics": {
        "gpa": {
          "unweighted": 3.9,
          "weighted": 4.5
        },
        "course_count": {
          "honors": null,
          "ap": 12,
          "ib": null,
          "dual_enrollment": null
        },
        "senior_year_course_load": null
      },
      "standardized_testing": {
        "sat_i": null,
        "act": 35
      },
      "extracurriculars": [
        "Singing opera for 12 years",
        "Prestigious camp for voice",
        "Choir officer",
        "Shift lead at work",
        "President of fundraising club",
        "President of political club",
        "Volunteer at church",
        "Member of selective choir",
        "Volunteer at food bank"
      ],
      "awards_honors": [
        "#1 state wide for singing",
        "International ranking for singing",
        "Scholastic award",
        "Local art and writing award"
      ],
      "letters_of_recommendation": null,
      "essays": null,
      "decisions": {
        "acceptances": [
          {
            "university": "Cornell University",
            "decision_plan": "N/A"
          }
        ],
        "waitlists": null,
        "rejections": null
      },
      "additional_information": null
    }
  },

  {
    "post_text": "Neuroscience Major ðŸŽ“\n\nDemographics\n\nAsian\nMale\n50k-100k\nPrivate School\nAcademics\n\n1540 SAT\n5 AP's\nExtracurriculars\n\n1. Academic prefect\n\n2. Asian student leadership council\n\n3. Summer cold email research internship in biochem\n\n4. Online cold mail research in neuroleadership\n\n5. Volunteer at hospital\n\n6. Varsity xc\n\n7. Research intern in bio\n\n8. HR for non-profit\n\n9. Singing hobby\n\nAwards\n\n1. AP European History Award\n\n2. Chinese III Award\n\n3. QuestBridge College Prep Scholars\n\n4. UK Biology Olympiad - Silver\n\n5. Regional bio competition top 15\n\nAcceptances\n\n1. Northwestern",
    "structured_profile": {
      "demographics": {
        "gender": "Male",
        "race_ethnicity": "Asian",
        "residence": null,
        "income_bracket": "50k-100k",
        "type_of_school": "Private School",
        "hooks": null,
        "intended_majors": "Neuroscience"
      },
      "academics": {
        "gpa": null,
        "course_count": {
          "honors": null,
          "ap": 5,
          "ib": null,
          "dual_enrollment": null
        },
        "senior_year_course_load": null
      },
      "standardized_testing": {
        "sat_i": {
          "total": 1540,
          "reading_writing": null,
          "math": null
        },
        "act": null
      },
      "extracurriculars": [
        "Academic prefect",
        "Asian student leadership council",
        "Summer cold email research internship in biochem",
        "Online cold mail research in neuroleadership",
        "Volunteer at hospital",
        "Varsity xc",
        "Research intern in bio",
        "HR for non-profit",
        "Singing hobby"
      ],
      "awards_honors": [
        "AP European History Award",
        "Chinese III Award",
        "QuestBridge College Prep Scholars",
        "UK Biology Olympiad - Silver",
        "Regional bio competition top 15"
      ],
      "letters_of_recommendation": null,
      "essays": null,
      "decisions": {
        "acceptances": [
          {
            "university": "Northwestern",
            "decision_plan": "N/A"
          }
        ],
        "waitlists": null,
        "rejections": null
      },
      "additional_information": null
    }
  },

  {
    "post_text": "Computer Science Major ðŸŽ“\n\nDemographics\n\nAsian\nFemale\n200k+\nPublic School\nAcademics\n\n1580 SAT\n12 AP's\n4 UW\n4.84 W\nExtracurriculars\n\n1. Gamedev club president\n\n2. GSA president\n\n3. Animation club president\n\n4. Queer culture club founder/co-president\n\n5. Hopkins Aspire intern\n\n6. Toastmasters speech club member\n\n7. AI organization intern\n\n8. Taekwondo student and eventual student instructor\n\n9. Python class volunteer instructor\n\nAwards\n\n1. President's Volunteer Award (Gold)\n\n2. NMSQT Semi-Finalist\n\n3. AP Scholar with Distinction\n\nAcceptances\n\n1. Cornell (Arts and Sciences)",
    "structured_profile": {
      "demographics": {
        "gender": "Female",
        "race_ethnicity": "Asian",
        "residence": null,
        "income_bracket": "200k+",
        "type_of_school": "Public School",
        "hooks": null,
        "intended_majors": "Computer Science"
      },
      "academics": {
        "gpa": {
          "unweighted": 4.0,
          "weighted": 4.84
        },
        "course_count": {
          "honors": null,
          "ap": 12,
          "ib": null,
          "dual_enrollment": null
        },
        "senior_year_course_load": null
      },
      "standardized_testing": {
        "sat_i": {
          "total": 1580,
          "reading_writing": null,
          "math": null
        },
        "act": null
      },
      "extracurriculars": [
        "Gamedev club president",
        "GSA president",
        "Animation club president",
        "Queer culture club founder/co-president",
        "Hopkins Aspire intern",
        "Toastmasters speech club member",
        "AI organization intern",
        "Taekwondo student and eventual student instructor",
        "Python class volunteer instructor"
      ],
      "awards_honors": [
        "President's Volunteer Award (Gold)",
        "NMSQT Semi-Finalist",
        "AP Scholar with Distinction"
      ],
      "letters_of_recommendation": null,
      "essays": null,
      "decisions": {
        "acceptances": [
          {
            "university": "Cornell (Arts and Sciences)",
            "decision_plan": "N/A"
          }
        ],
        "waitlists": null,
        "rejections": null
      },
      "additional_information": null
    }
  },

  {
    "post_text": "Mechanical Engineering Major ðŸŽ“\n\nDemographics\n\nWhite\nMale\n0-50k\nPublic School\nAcademics\n\n1500 SAT\n4 AP's\n3.8 UW\n4.49 W\nExtracurriculars\n\n1. 1. Captain of Social Studies Academic Super Bowl\n\n2. lead team to state finalist position (3 years)\n\n3. 2. Member of my cityâ€™s steering committee for our comprehensive plan (1 year)\n\n4. 3. Speech and Debate Co-Captain\n\n5. speech state finalist (3 years)\n\n6. 4. Spanish culture club (3 years)\n\n7. 5. Volunteer virtual SAT tutor (1 year)\n\n8. 6. Work as K-5 counselor after school during school year (2 years)\n\n9. 7. Work at flower center during summer breaks (2 years)\n\n10. 8. Shadowed two professional engineers in aerospace and civil engineering\n\n11. 9. Work as a cameraman at local go-karting events (1 year)\n\n12. 10. Schoolâ€™s prom committee\n\n13. coded a website that raised over 1000 for the event\n\nAwards\n\n1. NMSC commended student\n\n2. Speech state finalist\n\n3. Social Studies Academic Super Bowl state finalist\n\nAcceptances\n\n1. IU Bloomington\n\n2. Rose-Hulman\n\n3. University of Alabama\n\n4. Notre Dame\n\n5. Case Western Reserve",
    "structured_profile": {
      "demographics": {
        "gender": "Male",
        "race_ethnicity": "White",
        "residence": null,
        "income_bracket": "0-50k",
        "type_of_school": "Public School",
        "hooks": null,
        "intended_majors": "Mechanical Engineering"
      },
      "academics": {
        "gpa": {
          "unweighted": 3.8,
          "weighted": 4.49
        },
        "course_count": {
          "honors": null,
          "ap": 4,
          "ib": null,
          "dual_enrollment": null
        },
        "senior_year_course_load": null
      },
      "standardized_testing": {
        "sat_i": {
          "total": 1500,
          "reading_writing": null,
          "math": null
        },
        "act": null
      },
      "extracurriculars": [
        "Captain of Social Studies Academic Super Bowl (3 years), lead team to state finalist position",
        "Member of my cityâ€™s steering committee for our comprehensive plan (1 year)",
        "Speech and Debate Co-Captain (3 years), speech state finalist",
        "Spanish culture club (3 years)",
        "Volunteer virtual SAT tutor (1 year)",
        "Work as K-5 counselor after school during school year (2 years)",
        "Work at flower center during summer breaks (2 years)",
        "Shadowed two professional engineers in aerospace and civil engineering",
        "Work as a cameraman at local go-karting events (1 year)",
        "Schoolâ€™s prom committee, coded a website that raised over 1000 for the event"
      ],
      "awards_honors": [
        "NMSC commended student",
        "Speech state finalist",
        "Social Studies Academic Super Bowl state finalist"
      ],
      "letters_of_recommendation": null,
      "essays": null,
      "decisions": {
        "acceptances": [
          {
            "university": "IU Bloomington",
            "decision_plan": "N/A"
          },
          {
            "university": "Rose-Hulman",
            "decision_plan": "N/A"
          },
          {
            "university": "University of Alabama",
            "decision_plan": "N/A"
          },
          {
            "university": "Notre Dame",
            "decision_plan": "N/A"
          },
          {
            "university": "Case Western Reserve",
            "decision_plan": "N/A"
          }
        ],
        "waitlists": null,
        "rejections": null
      },
      "additional_information": null
    }
  },

  {
    "post_text": "Chemistry Major ðŸŽ“\n\nDemographics\n\nAsian\nFemale\n100k-200k\nPublic School\nAcademics\n\n1560 SAT\n15 AP's\n3.97 UW\nExtracurriculars\n\n1. Chemistry research\n\n2. independent research\n\n3. head of international online science journal\n\n4. organic chem summer program\n\n5. president of science club\n\n6. founder of chem club\n\n7. president of physics club\n\n8. red cross educational program coordinator\n\n9. red cross youth board\n\n10. spanish club co-pres\n\n11. water polo\n\n12. AVID tutor\n\n13. math tutor\n\n14. red cross club VP\n\n15. guitar\n\nAwards\n\n1. CA senate award for research\n\n2. presented at TED conference\n\n3. 2x PVSA gold\n\n4. national merit commended\n\n5. AP scholar w distinction\n\n6. school academic awards\n\nAcceptances\n\n1. Harvey Mudd",
    "structured_profile": {
      "demographics": {
        "gender": "Female",
        "race_ethnicity": "Asian",
        "residence": null,
        "income_bracket": "100k-200k",
        "type_of_school": "Public School",
        "hooks": null,
        "intended_majors": "Chemistry"
      },
      "academics": {
        "gpa": {
          "unweighted": 3.97,
          "weighted": null
        },
        "course_count": {
          "honors": null,
          "ap": 15,
          "ib": null,
          "dual_enrollment": null
        },
        "senior_year_course_load": null
      },
      "standardized_testing": {
        "sat_i": {
          "total": 1560,
          "reading_writing": null,
          "math": null
        },
        "act": null
      },
      "extracurriculars": [
        "Chemistry research",
        "independent research",
        "head of international online science journal",
        "organic chem summer program",
        "president of science club",
        "founder of chem club",
        "president of physics club",
        "red cross educational program coordinator",
        "red cross youth board",
        "spanish club co-pres",
        "water polo",
        "AVID tutor",
        "math tutor",
        "red cross club VP",
        "guitar"
      ],
      "awards_honors": [
        "CA senate award for research",
        "presented at TED conference",
        "2x PVSA gold",
        "national merit commended",
        "AP scholar w distinction",
        "school academic awards"
      ],
      "letters_of_recommendation": null,
      "essays": null,
      "decisions": {
        "acceptances": [
          {
            "university": "Harvey Mudd",
            "decision_plan": "N/A"
          }
        ],
        "waitlists": null,
        "rejections": null
      },
      "additional_information": null
    }
  },

  {
    "post_text": "Psychology Major ðŸŽ“\n\nDemographics\n\nWhite\nFemale\n50k-100k\nPublic School\nAcademics\n\n1390 SAT\n6 AP's\n4 UW\nExtracurriculars\n\n1. Founder/president/writer/editor of school newspaper\n\n2. Playwright/director\n\n3. Actor/puppet design\n\n4. Co-pres GSA\n\n5. StuGov elected rep\n\n6. Music\n\n7. Work\n\n8. International volunteer\n\n9. School theatre department secretary\n\n10. Variety of other social justice clubs\n\nAwards\n\n1. Seal of Biliteracy (Latin)\n\n2. Couple of class awards for math/english\n\n3. Yale book award\n\nAcceptances\n\n1. Brown University",
    "structured_profile": {
      "demographics": {
        "gender": "Female",
        "race_ethnicity": "White",
        "residence": null,
        "income_bracket": "50k-100k",
        "type_of_school": "Public School",
        "hooks": null,
        "intended_majors": "Psychology"
      },
      "academics": {
        "gpa": {
          "unweighted": 4.0,
          "weighted": null
        },
        "course_count": {
          "honors": null,
          "ap": 6,
          "ib": null,
          "dual_enrollment": null
        },
        "senior_year_course_load": null
      },
      "standardized_testing": {
        "sat_i": {
          "total": 1390,
          "reading_writing": null,
          "math": null
        },
        "act": null
      },
      "extracurriculars": [
        "Founder/president/writer/editor of school newspaper",
        "Playwright/director",
        "Actor/puppet design",
        "Co-pres GSA",
        "StuGov elected rep",
        "Music",
        "Work",
        "International volunteer",
        "School theatre department secretary",
        "Variety of other social justice clubs"
      ],
      "awards_honors": [
        "Seal of Biliteracy (Latin)",
        "Couple of class awards for math/english",
        "Yale book award"
      ],
      "letters_of_recommendation": null,
      "essays": null,
      "decisions": {
        "acceptances": [
          {
            "university": "Brown University",
            "decision_plan": "N/A"
          }
        ],
        "waitlists": null,
        "rejections": null
      },
      "additional_information": null
    }
  },

  {
    "post_text": "Mathematics Major ðŸŽ“\n\nDemographics\n\nWhite\nMale\n0-50k\nPublic School\nAcademics\n\n34 ACT\n9 AP's\n4 UW\n4.78 W\nExtracurriculars\n\n1. Cuber (solves Rubik's Cubes in competitions & teaches)\n\n2. BBYO (rebuilt Jewish youth group after COVID)\n\n3. Taekwondo (second degree black belt)\n\n4. Religious school teacher/Bar Mitzvah tutor\n\n5. Interfaith Atlanta Youth (founded advocacy group)\n\n6. Math team co-president\n\n7. Sleepaway camp counselor\n\n8. Fencing (epee fencer)\n\n9. Leader's for Tomorrow participant\n\n10. Religious minority club participant\n\nAwards\n\n1. GA certificate of merit\n\n2. AP scholar with distinction '22/'23 & AP scholar '21\n\n3. NHS\n\n4. Math team competition awards\n\n5. Lettered in fencing\n\n6. Three Jewish involvement awards\n\n7. IB Extended Essay on Rubik's cube solves\n\nAcceptances\n\n1. GA tech\n\n2. Vanderbilt",
    "structured_profile": {
      "demographics": {
        "gender": "Male",
        "race_ethnicity": "White",
        "residence": null,
        "income_bracket": "0-50k",
        "type_of_school": "Public School",
        "hooks": null,
        "intended_majors": "Mathematics"
      },
      "academics": {
        "gpa": {
          "unweighted": 4.0,
          "weighted": 4.78
        },
        "course_count": {
          "honors": null,
          "ap": 9,
          "ib": null,
          "dual_enrollment": null
        },
        "senior_year_course_load": null
      },
      "standardized_testing": {
        "sat_i": null,
        "act": 34
      },
      "extracurriculars": [
        "Cuber (solves Rubik's Cubes in competitions & teaches)",
        "BBYO (rebuilt Jewish youth group after COVID)",
        "Taekwondo (second degree black belt)",
        "Religious school teacher/Bar Mitzvah tutor",
        "Interfaith Atlanta Youth (founded advocacy group)",
        "Math team co-president",
        "Sleepaway camp counselor",
        "Fencing (epee fencer)",
        "Leader's for Tomorrow participant",
        "Religious minority club participant"
      ],
      "awards_honors": [
        "GA certificate of merit",
        "AP scholar with distinction '22/'23",
        "AP scholar '21",
        "NHS",
        "Math team competition awards",
        "Lettered in fencing",
        "Three Jewish involvement awards",
        "IB Extended Essay on Rubik's cube solves"
      ],
      "letters_of_recommendation": null,
      "essays": null,
      "decisions": {
        "acceptances": [
          {
            "university": "Georgia Tech",
            "decision_plan": "N/A"
          },
          {
            "university": "Vanderbilt",
            "decision_plan": "N/A"
          }
        ],
        "waitlists": null,
        "rejections": null
      },
      "additional_information": null
    }
  },

  {
    "post_text": "Classics Major ðŸŽ“\n\nDemographics\n\nAfrican American\nFemale\n200k+\nPrivate School\nAcademics\n\n1590 SAT\n7 AP's\n3.95 UW\n4 W\nExtracurriculars\n\n1. Youth Chorus (local and international performances)\n\n2. Private voice and piano lessons\n\n3. Summer voice/opera institute\n\n4. Latin immersion trip to Italy\n\n5. Relay for Life\n\n6. Byzantine Greek Summer program\n\n7. Recitals in local productions\n\nAwards\n\n1. Individual singing and choral competitions\n\n2. National Latin and Greek Exams\n\n3. Major academic award\n\nAcceptances\n\n1. Yale",
    "structured_profile": {
      "demographics": {
        "gender": "Female",
        "race_ethnicity": "African American",
        "residence": null,
        "income_bracket": "200k+",
        "type_of_school": "Private School",
        "hooks": null,
        "intended_majors": "Classics"
      },
      "academics": {
        "gpa": {
          "unweighted": 3.95,
          "weighted": 4.0
        },
        "course_count": {
          "honors": null,
          "ap": 7,
          "ib": null,
          "dual_enrollment": null
        },
        "senior_year_course_load": null
      },
      "standardized_testing": {
        "sat_i": {
          "total": 1590,
          "reading_writing": null,
          "math": null
        },
        "act": null
      },
      "extracurriculars": [
        "Youth Chorus (local and international performances)",
        "Private voice and piano lessons",
        "Summer voice/opera institute",
        "Latin immersion trip to Italy",
        "Relay for Life",
        "Byzantine Greek Summer program",
        "Recitals in local productions"
      ],
      "awards_honors": [
        "Individual singing and choral competitions",
        "National Latin and Greek Exams",
        "Major academic award"
      ],
      "letters_of_recommendation": null,
      "essays": null,
      "decisions": {
        "acceptances": [
          {
            "university": "Yale",
            "decision_plan": "N/A"
          }
        ],
        "waitlists": null,
        "rejections": null
      },
      "additional_information": null
    }
  },

  {
    "post_text": "Civil Engineering Major ðŸŽ“\n\nDemographics\n\nWhite\nNon-Binary\n0-50k\nPublic School\nAcademics\n\n1330 SAT\n17 AP's\n3.7 UW\n3.756 W\nExtracurriculars\n\n1. Summer camp counselor\n\n2. NHS member\n\n3. Engineering Club member\n\n4. NEHS Officer\n\n5. English Club Officer\n\n6. Engineering Lab Assistant\n\n7. various community service\n\n8. internship\n\n9. pilot of a 1-year engineering program\n\n10. softball player\n\nAwards\n\n1. High Honor roll\n\n2. JV Captain\n\n3. Engineering Lab Assistant\n\n4. Officer holdings\n\nAcceptances\n\n1. Seton Hall\n\n2. Drexel University\n\n3. SUNY Buffalo\n\n4. University of Delaware\n\n5. Hofstra University\n\n6. SUNYPoly\n\n7. SUNY Binghamton\n\n8. Virginia Tech\n\n9. UMass Amherst\n\n10. Northeastern\n\n11. Worcester Polytechnic Institute\n\n12. Rochester Institute of Technology\n\n13. SUNY Stony Brook",
    "structured_profile": {
      "demographics": {
        "gender": "Non-Binary",
        "race_ethnicity": "White",
        "residence": null,
        "income_bracket": "0-50k",
        "type_of_school": "Public School",
        "hooks": null,
        "intended_majors": "Civil Engineering"
      },
      "academics": {
        "gpa": {
          "unweighted": 3.7,
          "weighted": 3.756
        },
        "course_count": {
          "honors": null,
          "ap": 17,
          "ib": null,
          "dual_enrollment": null
        },
        "senior_year_course_load": null
      },
      "standardized_testing": {
        "sat_i": {
          "total": 1330,
          "reading_writing": null,
          "math": null
        },
        "act": null
      },
      "extracurriculars": [
        "Summer camp counselor",
        "NHS member",
        "Engineering Club member",
        "NEHS Officer",
        "English Club Officer",
        "Engineering Lab Assistant",
        "various community service",
        "internship",
        "pilot of a 1-year engineering program",
        "softball player"
      ],
      "awards_honors": [
        "High Honor roll",
        "JV Captain",
        "Engineering Lab Assistant",
        "Officer holdings"
      ],
      "letters_of_recommendation": null,
      "essays": null,
      "decisions": {
        "acceptances": [
          {
            "university": "Seton Hall",
            "decision_plan": "N/A"
          },
          {
            "university": "Drexel University",
            "decision_plan": "N/A"
          },
          {
            "university": "SUNY Buffalo",
            "decision_plan": "N/A"
          },
          {
            "university": "University of Delaware",
            "decision_plan": "N/A"
          },
          {
            "university": "Hofstra University",
            "decision_plan": "N/A"
          },
          {
            "university": "SUNY Poly",
            "decision_plan": "N/A"
          },
          {
            "university": "SUNY Binghamton",
            "decision_plan": "N/A"
          },
          {
            "university": "Virginia Tech",
            "decision_plan": "N/A"
          },
          {
            "university": "UMass Amherst",
            "decision_plan": "N/A"
          },
          {
            "university": "Northeastern",
            "decision_plan": "N/A"
          },
          {
            "university": "Worcester Polytechnic Institute",
            "decision_plan": "N/A"
          },
          {
            "university": "Rochester Institute of Technology",
            "decision_plan": "N/A"
          },
          {
            "university": "SUNY Stony Brook",
            "decision_plan": "N/A"
          }
        ],
        "waitlists": null,
        "rejections": null
      },
      "additional_information": null
    }
  },

  {
    "post_text": "N/A Major ðŸŽ“\n\nDemographics\n\nOther\nNon-Binary\n200k+\nPublic School\nAcademics\n\n1600 SAT\n6 AP's\n3.98 UW\n4.9 W\nExtracurriculars\n\n1. Varsity sport\n\n2. Athletic club founder\n\n3. Art club founder\n\n4. Volunteer tutor\n\n5. Private tutor\n\n6. Religious volunteer work\n\n7. E-sports competitor\n\n8. random job 1\n\n9. random job 2\n\n10. CS club member\n\nAwards\n\n1. NMS semifinalist\n\n2. National writing award\n\n3. School writing award\n\n4. Regional math competition individual winner\n\n5. Other school award\n\nAcceptances\n\n1. Northwestern",
    "structured_profile": {
      "demographics": {
        "gender": "Non-Binary",
        "race_ethnicity": null,
        "residence": null,
        "income_bracket": "200k+",
        "type_of_school": "Public School",
        "hooks": null,
        "intended_majors": null
      },
      "academics": {
        "gpa": {
          "unweighted": 3.98,
          "weighted": 4.9
        },
        "course_count": {
          "honors": null,
          "ap": 6,
          "ib": null,
          "dual_enrollment": null
        },
        "senior_year_course_load": null
      },
      "standardized_testing": {
        "sat_i": {
          "total": 1600,
          "reading_writing": null,
          "math": null
        },
        "act": null
      },
      "extracurriculars": [
        "Varsity sport",
        "Athletic club founder",
        "Art club founder",
        "Volunteer tutor",
        "Private tutor",
        "Religious volunteer work",
        "E-sports competitor",
        "random job 1",
        "random job 2",
        "CS club member"
      ],
      "awards_honors": [
        "NMS semifinalist",
        "National writing award",
        "School writing award",
        "Regional math competition individual winner",
        "Other school award"
      ],
      "letters_of_recommendation": null,
      "essays": null,
      "decisions": {
        "acceptances": [
          {
            "university": "Northwestern",
            "decision_plan": "N/A"
          }
        ],
        "waitlists": null,
        "rejections": null
      },
      "additional_information": null
    }
  },

  {
    "post_text": "Mathematics Major ðŸŽ“\n\nDemographics\n\nHispanic\nFemale\n0-50k\nPublic School\nAcademics\n\n1400 SAT\n6 AP's\n3.99 UW\nExtracurriculars\n\n1. #1 part-time job for 2 years\n\n2. #2 volunteer at a rescue for all of high school\n\n3. #3 NHS\n\n4. #4 writing tutoring\n\n5. #5 robotics\n\n6. #6 art club\n\nAwards\n\n1. One national award\n\nAcceptances\n\n1. Northeastern Boston campus",
    "structured_profile": {
      "demographics": {
        "gender": "Female",
        "race_ethnicity": "Hispanic",
        "residence": null,
        "income_bracket": "0-50k",
        "type_of_school": "Public School",
        "hooks": null,
        "intended_majors": "Mathematics"
      },
      "academics": {
        "gpa": {
          "unweighted": 3.99,
          "weighted": null
        },
        "course_count": {
          "honors": null,
          "ap": 6,
          "ib": null,
          "dual_enrollment": null
        },
        "senior_year_course_load": null
      },
      "standardized_testing": {
        "sat_i": {
          "total": 1400,
          "reading_writing": null,
          "math": null
        },
        "act": null
      },
      "extracurriculars": [
        "Part-time job for 2 years",
        "Volunteer at a rescue for all of high school",
        "NHS",
        "Writing tutoring",
        "Robotics",
        "Art club"
      ],
      "awards_honors": ["One national award"],
      "letters_of_recommendation": null,
      "essays": null,
      "decisions": {
        "acceptances": [
          {
            "university": "Northeastern University",
            "decision_plan": "N/A"
          }
        ],
        "waitlists": null,
        "rejections": null
      },
      "additional_information": null
    }
  },

  {
    "post_text": "Economics Major ðŸŽ“\n\nDemographics\n\nAsian\nFemale\n50k-100k\nPrivate School\nAcademics\n\n1600 SAT\n5 AP's\n4 UW\nExtracurriculars\n\n1. Speech and Debate (novice trainer\n\n2. States\n\n3. Nats)\n\n4. Co-Leader of AAPI Affinity Group\n\n5. Co-Leader of Science Olympiad team\n\n6. President of Honor Council\n\n7. Costume Crew\n\n8. Summer Camp Volunteer\n\n9. Math Modeling team\n\n10. Art Instagram\n\n11. Summer Camp Counselor\n\n12. Video Game Designer\n\nAwards\n\n1. Top 5 in International Latin Translation Contest\n\n2. National Latin Exam/National Myth Exam placements\n\n3. local math competition\n\n4. Science Olympiad placements\n\n5. National Merit Semifinalist\n\nAcceptances\n\n1. Brown",
    "structured_profile": {
      "demographics": {
        "gender": "Female",
        "race_ethnicity": "Asian",
        "residence": null,
        "income_bracket": "50k-100k",
        "type_of_school": "Private School",
        "hooks": null,
        "intended_majors": "Economics"
      },
      "academics": {
        "gpa": {
          "unweighted": 4.0,
          "weighted": null
        },
        "course_count": {
          "honors": null,
          "ap": 5,
          "ib": null,
          "dual_enrollment": null
        },
        "senior_year_course_load": null
      },
      "standardized_testing": {
        "sat_i": {
          "total": 1600,
          "reading_writing": null,
          "math": null
        },
        "act": null
      },
      "extracurriculars": [
        "Speech and Debate (novice trainer, States, Nats)",
        "Co-Leader of AAPI Affinity Group",
        "Co-Leader of Science Olympiad team",
        "President of Honor Council",
        "Costume Crew",
        "Summer Camp Volunteer",
        "Math Modeling team",
        "Art Instagram",
        "Summer Camp Counselor",
        "Video Game Designer"
      ],
      "awards_honors": [
        "Top 5 in International Latin Translation Contest",
        "National Latin Exam/National Myth Exam placements",
        "local math competition",
        "Science Olympiad placements",
        "National Merit Semifinalist"
      ],
      "letters_of_recommendation": null,
      "essays": null,
      "decisions": {
        "acceptances": [
          {
            "university": "Brown",
            "decision_plan": "N/A"
          }
        ],
        "waitlists": null,
        "rejections": null
      },
      "additional_information": null
    }
  },

  {
    "post_text": "Biology Major ðŸŽ“\n\nDemographics\n\nAfrican American\nFemale\n50k-100k\nPrivate School\nAcademics\n\n3 AP's\n4 W\nExtracurriculars\n\n1. Orchestra (7 years\n\n2. section leader)\n\n3. Pops Orchestra (section leader)\n\n4. Top Youth Orchestra in my area\n\n5. Black Student Union Social Media Coordinator\n\n6. Work Study job (rare at my boarding school)\n\n7. International Student Union Allyship Director\n\n8. Advanced Bio Tutor\n\n9. Formed a quartet dedicated to uplifting minority musicians\n\n10. Diversity\n\n11. Equity\n\n12. and Inclusion Student Voice Team\n\n13. Youth in Government\n\nAwards\n\n1. National African American Recognition Program\n\n2. School scholarship\n\n3. Best Musician\n\n4. Best Cellist\n\n5. Honor Roll\n\nAcceptances\n\n1. MSU\n\n2. OSU\n\n3. Fordham\n\n4. Uchicago",
    "structured_profile": {
      "demographics": {
        "gender": "Female",
        "race_ethnicity": "African American",
        "residence": null,
        "income_bracket": "50k-100k",
        "type_of_school": "Private School",
        "hooks": null,
        "intended_majors": "Biology"
      },
      "academics": {
        "gpa": {
          "unweighted": null,
          "weighted": 4.0
        },
        "course_count": {
          "honors": null,
          "ap": 3,
          "ib": null,
          "dual_enrollment": null
        },
        "senior_year_course_load": null
      },
      "standardized_testing": null,
      "extracurriculars": [
        "Orchestra (7 years, section leader)",
        "Pops Orchestra (section leader)",
        "Top Youth Orchestra in my area",
        "Black Student Union Social Media Coordinator",
        "Work Study job (rare at my boarding school)",
        "International Student Union Allyship Director",
        "Advanced Bio Tutor",
        "Formed a quartet dedicated to uplifting minority musicians",
        "Diversity, Equity, and Inclusion Student Voice Team",
        "Youth in Government"
      ],
      "awards_honors": [
        "National African American Recognition Program",
        "School scholarship",
        "Best Musician",
        "Best Cellist",
        "Honor Roll"
      ],
      "letters_of_recommendation": null,
      "essays": null,
      "decisions": {
        "acceptances": [
          {
            "university": "MSU",
            "decision_plan": "N/A"
          },
          {
            "university": "OSU",
            "decision_plan": "N/A"
          },
          {
            "university": "Fordham",
            "decision_plan": "N/A"
          },
          {
            "university": "Uchicago",
            "decision_plan": "N/A"
          }
        ],
        "waitlists": null,
        "rejections": null
      },
      "additional_information": null
    }
  },

  {
    "post_text": "Mechanical Engineering Major ðŸŽ“\n\nDemographics\n\nWhite\nMale\n100k-200k\nPublic School\nAcademics\n\n1560 SAT\n14 AP's\n3.9 UW\nExtracurriculars\n\n1. Created platform for college counseling\n\n2. Project Dev. Intern\n\n3. Engineering and ML research at a local college\n\n4. VP of Varsity Robotics\n\n5. Book Author\n\n6. Speech Captain of Varsity Debate\n\n7. President of the local chapter of a national speech organization\n\n8. Dancer\n\n9. Sector president of trafficking prevention non-profit\n\n10. Region representative of international education non-profit\n\n11. Developed a smart glass module for eye dryness\n\n12. Federal government agency youth partner/board member\n\n13. Paralympic Sports Tournaments Lead\n\n14. Social Media influencer\n\n15. School club officer\n\n16. Charity Basketball tournament\n\nAwards\n\n1. 2nd place HOSA international\n\n2. 3rd place DECA international\n\n3. White House Summit nominee\n\n4. Gold Presidential Service Award\n\n5. National Film Competition Finalist\n\n6. 3X video production awards from nationwide film festivals\n\nAcceptances\n\n1. A&M\n\n2. UT Austin\n\n3. Baylor\n\n4. UT Dallas",
    "structured_profile": {
      "demographics": {
        "gender": "Male",
        "race_ethnicity": "White",
        "residence": null,
        "income_bracket": "100k-200k",
        "type_of_school": "Public School",
        "hooks": null,
        "intended_majors": "Mechanical Engineering"
      },
      "academics": {
        "gpa": {
          "unweighted": 3.9,
          "weighted": null
        },
        "course_count": {
          "honors": null,
          "ap": 14,
          "ib": null,
          "dual_enrollment": null
        },
        "senior_year_course_load": null
      },
      "standardized_testing": {
        "sat_i": {
          "total": 1560,
          "reading_writing": null,
          "math": null
        },
        "act": null
      },
      "extracurriculars": [
        "Created platform for college counseling",
        "Project Dev. Intern",
        "Engineering and ML research at a local college",
        "VP of Varsity Robotics",
        "Book Author",
        "Speech Captain of Varsity Debate",
        "President of the local chapter of a national speech organization",
        "Dancer",
        "Sector president of trafficking prevention non-profit",
        "Region representative of international education non-profit",
        "Developed a smart glass module for eye dryness",
        "Federal government agency youth partner/board member",
        "Paralympic Sports Tournaments Lead",
        "Social Media influencer",
        "School club officer",
        "Charity Basketball tournament"
      ],
      "awards_honors": [
        "2nd place HOSA international",
        "3rd place DECA international",
        "White House Summit nominee",
        "Gold Presidential Service Award",
        "National Film Competition Finalist",
        "3X video production awards from nationwide film festivals"
      ],
      "letters_of_recommendation": null,
      "essays": null,
      "decisions": {
        "acceptances": [
          {
            "university": "A&M",
            "decision_plan": "N/A"
          },
          {
            "university": "UT Austin",
            "decision_plan": "N/A"
          },
          {
            "university": "Baylor",
            "decision_plan": "N/A"
          },
          {
            "university": "UT Dallas",
            "decision_plan": "N/A"
          }
        ],
        "waitlists": null,
        "rejections": null
      },
      "additional_information": null
    }
  },

  {
    "post_text": "Political Science Major ðŸŽ“\n\nDemographics\n\nHispanic\nMale\n0-50k\nPrivate School\nAcademics\n\n34 ACT\n18 AP's\n4 UW\n4.37 W\nExtracurriculars\n\n1. Family Responsibilities (25 hrs per week)\n\n2. Quizbowl (Captain) (6 hrs per week)\n\n3. Computer Maintenance Operator at Healthcare Clinic (6 hrs)\n\n4. State Youth Cabinet with Senator (2 hrs)\n\n5. Spanish Tutoring Club (1 hr)\n\n6. Computer Builder and Troubleshooter (3 hrs)\n\n7. Program at UChicago\n\n8. Beta Club (1 hr)\n\n9. Blog Writing (1 hr)\n\nAwards\n\n1. NMSF/ Gates Semi-Finalist\n\n2. HSF Scholar\n\n3. National Spanish Exam Level 6: Silver/ Seal of Biliteracy in English and Spanish\n\n4. Quizbowl State Championship Runner-up\n\n5. National Hispanic Recognition Award\n\nAcceptances\n\n1. UChicago",
    "structured_profile": {
      "demographics": {
        "gender": "Male",
        "race_ethnicity": "Hispanic",
        "residence": null,
        "income_bracket": "0-50k",
        "type_of_school": "Private School",
        "hooks": null,
        "intended_majors": "Political Science"
      },
      "academics": {
        "gpa": {
          "unweighted": 4.0,
          "weighted": 4.37
        },
        "course_count": {
          "honors": null,
          "ap": 18,
          "ib": null,
          "dual_enrollment": null
        },
        "senior_year_course_load": null
      },
      "standardized_testing": {
        "sat_i": null,
        "act": 34
      },
      "extracurriculars": [
        "Family Responsibilities (25 hrs per week)",
        "Quizbowl (Captain) (6 hrs per week)",
        "Computer Maintenance Operator at Healthcare Clinic (6 hrs)",
        "State Youth Cabinet with Senator (2 hrs)",
        "Spanish Tutoring Club (1 hr)",
        "Computer Builder and Troubleshooter (3 hrs)",
        "Program at UChicago",
        "Beta Club (1 hr)",
        "Blog Writing (1 hr)"
      ],
      "awards_honors": [
        "NMSF/ Gates Semi-Finalist",
        "HSF Scholar",
        "National Spanish Exam Level 6: Silver/ Seal of Biliteracy in English and Spanish",
        "Quizbowl State Championship Runner-up",
        "National Hispanic Recognition Award"
      ],
      "letters_of_recommendation": null,
      "essays": null,
      "decisions": {
        "acceptances": [
          {
            "university": "UChicago",
            "decision_plan": "N/A"
          }
        ],
        "waitlists": null,
        "rejections": null
      },
      "additional_information": null
    }
  },

  {
    "post_text": "Economics Major ðŸŽ“\n\nDemographics\n\nAsian\nMale\n200k+\nPrivate School\nAcademics\n\n780 SAT\n6 AP's\n4 UW\n4.44 W\nExtracurriculars\n\n1. Research w Cornell PHD\n\n2. Founded an NGO\n\n3. Internship at Fintech VC\n\n4. AI project with American students\n\n5. Student leader at volunteering club\n\n6. Guitar for 12 years\n\nAwards\n\n1. Second in Harvard MUN\n\n2. 3rd in National Entrepreneurship contest\n\n3. National Rank 10th Board exams\n\n4. Physics olympiad distinction\n\n5. John Locke finalist\n\nAcceptances\n\n1. Uchicago",
    "structured_profile": {
      "demographics": {
        "gender": "Male",
        "race_ethnicity": "Asian",
        "residence": null,
        "income_bracket": "200k+",
        "type_of_school": "Private School",
        "hooks": null,
        "intended_majors": "Economics"
      },
      "academics": {
        "gpa": {
          "unweighted": 4.0,
          "weighted": 4.44
        },
        "course_count": {
          "honors": null,
          "ap": 6,
          "ib": null,
          "dual_enrollment": null
        },
        "senior_year_course_load": null
      },
      "standardized_testing": {
        "sat_i": {
          "total": null,
          "reading_writing": null,
          "math": null
        },
        "act": null
      },
      "extracurriculars": [
        "Research w Cornell PHD",
        "Founded an NGO",
        "Internship at Fintech VC",
        "AI project with American students",
        "Student leader at volunteering club",
        "Guitar for 12 years"
      ],
      "awards_honors": [
        "Second in Harvard MUN",
        "3rd in National Entrepreneurship contest",
        "National Rank 10th Board exams",
        "Physics olympiad distinction",
        "John Locke finalist"
      ],
      "letters_of_recommendation": null,
      "essays": null,
      "decisions": {
        "acceptances": [
          {
            "university": "Uchicago",
            "decision_plan": "N/A"
          }
        ],
        "waitlists": null,
        "rejections": null
      },
      "additional_information": null
    }
  },

  {
    "post_text": "N/A Major ðŸŽ“\n\nDemographics\n\nAsian\nMale\n100k-200k\nPublic School\nAcademics\n\n5 AP's\n3.8 UW\n4.2 W\nExtracurriculars\n\n1. Debate Club\n\n2. Internship at Firm\n\n3. Board Position\n\nAwards\n\n1. Ran a Business and Charity\n\nAcceptances\n\n1. UPenn\n\n2. Princeton\n\n3. Columbia\n\n4. NYU Stern\n\n5. Emory\n\n6. Northeastern\n\n7. JHU\n\n8. Georgetown",
    "structured_profile": {
      "demographics": {
        "gender": "Male",
        "race_ethnicity": "Asian",
        "residence": null,
        "income_bracket": "100k-200k",
        "type_of_school": "Public School",
        "hooks": null,
        "intended_majors": null
      },
      "academics": {
        "gpa": {
          "unweighted": 3.8,
          "weighted": 4.2
        },
        "course_count": {
          "honors": null,
          "ap": 5,
          "ib": null,
          "dual_enrollment": null
        },
        "senior_year_course_load": null
      },
      "standardized_testing": null,
      "extracurriculars": [
        "Debate Club",
        "Internship at Firm",
        "Board Position"
      ],
      "awards_honors": ["Ran a Business and Charity"],
      "letters_of_recommendation": null,
      "essays": null,
      "decisions": {
        "acceptances": [
          {
            "university": "UPenn",
            "decision_plan": "N/A"
          },
          {
            "university": "Princeton",
            "decision_plan": "N/A"
          },
          {
            "university": "Columbia",
            "decision_plan": "N/A"
          },
          {
            "university": "NYU Stern",
            "decision_plan": "N/A"
          },
          {
            "university": "Emory",
            "decision_plan": "N/A"
          },
          {
            "university": "Northeastern",
            "decision_plan": "N/A"
          },
          {
            "university": "JHU",
            "decision_plan": "N/A"
          },
          {
            "university": "Georgetown",
            "decision_plan": "N/A"
          }
        ],
        "waitlists": null,
        "rejections": null
      },
      "additional_information": null
    }
  },

  {
    "post_text": "Environmental Science Major ðŸŽ“\n\nDemographics\n\nWhite\nMale\n0-50k\nPublic School\nAcademics\n\n1450 SAT\nFull AP's\n4.6 W\nExtracurriculars\n\n1. Mock trial\n\n2. culture clubs\n\n3. volunteering at the daily bread\n\n4. worked at a voice of baltimore youth magazine\n\n5. did murals around the city\n\n6. youthworks type stuff\n\n7. played cello on scholarship for Peabody\n\n8. free educational programs\n\nAwards\n\n1. N/A\n\nAcceptances\n\n1. UMBC\n\n2. Syracuse\n\n3. UPitt",
    "structured_profile": {
      "demographics": {
        "gender": "Male",
        "race_ethnicity": "White",
        "residence": null,
        "income_bracket": "0-50k",
        "type_of_school": "Public School",
        "hooks": null,
        "intended_majors": "Environmental Science"
      },
      "academics": {
        "gpa": {
          "unweighted": null,
          "weighted": 4.6
        },
        "course_count": {
          "honors": null,
          "ap": null,
          "ib": null,
          "dual_enrollment": null
        },
        "senior_year_course_load": null
      },
      "standardized_testing": {
        "sat_i": {
          "total": 1450,
          "reading_writing": null,
          "math": null
        },
        "act": null
      },
      "extracurriculars": [
        "Mock trial",
        "Culture clubs",
        "Volunteering at the daily bread",
        "Worked at a voice of baltimore youth magazine",
        "Did murals around the city",
        "Youthworks type stuff",
        "Played cello on scholarship for Peabody",
        "Free educational programs"
      ],
      "awards_honors": [],
      "letters_of_recommendation": null,
      "essays": null,
      "decisions": {
        "acceptances": [
          {
            "university": "UMBC",
            "decision_plan": "N/A"
          },
          {
            "university": "Syracuse",
            "decision_plan": "N/A"
          },
          {
            "university": "UPitt",
            "decision_plan": "N/A"
          }
        ],
        "waitlists": null,
        "rejections": null
      },
      "additional_information": null
    }
  },

  {
    "post_text": "Environmental Science Major ðŸŽ“\n\nDemographics\n\nAsian\nMale\n200k+\nPublic School\nAcademics\n\n36 ACT\n17 AP's\n4 UW\n4.73 W\nExtracurriculars\n\n1. Research\n\n2. President of Student Environmental Organization\n\n3. Founder/Vice Pres of debate club\n\n4. Political Campaigner\n\n5. Summer Intern in ecology\n\n6. Team Captain of HS Tennis Team\n\n7. President of Environmental Club at HS\n\n8. Blogger for environmental science\n\n9. Attended competitive summer program\n\n10. Youth Health Board Member\n\nAwards\n\n1. National geographic award from science fair\n\n2. 1st place @ state for SciOly competition\n\n3. Attended state's gov school for science\n\nAcceptances\n\n1. UPenn",
    "structured_profile": {
      "demographics": {
        "gender": "Male",
        "race_ethnicity": "Asian",
        "residence": null,
        "income_bracket": "200k+",
        "type_of_school": "Public School",
        "hooks": null,
        "intended_majors": "Environmental Science"
      },
      "academics": {
        "gpa": {
          "unweighted": 4.0,
          "weighted": 4.73
        },
        "course_count": {
          "honors": null,
          "ap": 17,
          "ib": null,
          "dual_enrollment": null
        },
        "senior_year_course_load": null
      },
      "standardized_testing": {
        "sat_i": null,
        "act": 36
      },
      "extracurriculars": [
        "Research",
        "President of Student Environmental Organization",
        "Founder/Vice Pres of debate club",
        "Political Campaigner",
        "Summer Intern in ecology",
        "Team Captain of HS Tennis Team",
        "President of Environmental Club at HS",
        "Blogger for environmental science",
        "Attended competitive summer program",
        "Youth Health Board Member"
      ],
      "awards_honors": [
        "National geographic award from science fair",
        "1st place @ state for SciOly competition",
        "Attended state's gov school for science"
      ],
      "letters_of_recommendation": null,
      "essays": null,
      "decisions": {
        "acceptances": [
          {
            "university": "UPenn",
            "decision_plan": "N/A"
          }
        ],
        "waitlists": null,
        "rejections": null
      },
      "additional_information": null
    }
  },

  {
    "post_text": "Ethics Major ðŸŽ“\n\nDemographics\n\nWhite\nMale\n200k+\nPrivate School\nAcademics\n\n36 ACT\n11 AP's\n3.96 UW\n4.76 W\nExtracurriculars\n\n1. Team Captain/Member (Attorney and Witness) School Mock Trial\n\n2. Voter Protection Outreach Intern (State Democratic Party)\n\n3. Operations Intern - sole HS student (State Democratic Party)\n\n4. Co-Founder/Team Captain (Global Affairs Competition)\n\n5. Exchange Participant/Cultural Ambassador (State Department Exchange)\n\n6. Student Participant Yale Young Global Scholars\n\n7. Vice President/Senator (School)\n\n8. Campaign Intern - sole HS student on staff (State Senator Name)\n\n9. Co-Chair/National Liason (State HS Democrats)\n\n10. Participant (Club Name)\n\nAwards\n\n1. Won 1st place in MN state (School Mock Trial)\n\n2. Williams Book Award\n\n3. Profiles in Courage Top 10% of submissions\n\n4. National Honors Society\n\n5. Student of the Month (English and History)\n\nAcceptances\n\n1. Yale",
    "structured_profile": {
      "demographics": {
        "gender": "Male",
        "race_ethnicity": "White",
        "residence": null,
        "income_bracket": "200k+",
        "type_of_school": "Private School",
        "hooks": null,
        "intended_majors": "Ethics"
      },
      "academics": {
        "gpa": {
          "unweighted": 3.96,
          "weighted": 4.76
        },
        "course_count": {
          "honors": null,
          "ap": 11,
          "ib": null,
          "dual_enrollment": null
        },
        "senior_year_course_load": null
      },
      "standardized_testing": {
        "sat_i": null,
        "act": 36
      },
      "extracurriculars": [
        "Team Captain/Member (Attorney and Witness) School Mock Trial",
        "Voter Protection Outreach Intern (State Democratic Party)",
        "Operations Intern - sole HS student (State Democratic Party)",
        "Co-Founder/Team Captain (Global Affairs Competition)",
        "Exchange Participant/Cultural Ambassador (State Department Exchange)",
        "Student Participant Yale Young Global Scholars",
        "Vice President/Senator (School)",
        "Campaign Intern - sole HS student on staff (State Senator Name)",
        "Co-Chair/National Liason (State HS Democrats)",
        "Participant (Club Name)"
      ],
      "awards_honors": [
        "Won 1st place in MN state (School Mock Trial)",
        "Williams Book Award",
        "Profiles in Courage Top 10% of submissions",
        "National Honors Society",
        "Student of the Month (English and History)"
      ],
      "letters_of_recommendation": null,
      "essays": null,
      "decisions": {
        "acceptances": [
          {
            "university": "Yale",
            "decision_plan": "N/A"
          }
        ],
        "waitlists": null,
        "rejections": null
      },
      "additional_information": null
    }
  },

  {
    "post_text": "Business Major ðŸŽ“\n\nDemographics\n\nAsian\nFemale\n0-50k\nPublic School\nAcademics\n\n1540 SAT\n13 AP's\n4 UW\n4.78 W\nExtracurriculars\n\n1. President of in-school stock exchange club\n\n2. President of in-school econ club\n\n3. Summer internship at Loreal as a finance intern\n\n4. Writer for an account with over 200k followers\n\n5. School district's student member of the board cluster representative\n\n6. Human rights commission student ambassador\n\n7. Chief intern at a non-profit music organization\n\n8. English Tutor of a non-profit\n\n9. Hostess at a restaurant\n\n10. Attended Wharton's LBW program\n\n11. Interned at Women's Federation\n\n12. Participated in Wharton's Investment Competition for 2 years\n\nAwards\n\n1. GYEC US FINAL ROUND 3RD PRIZE\n\n2. GYEC US FINAL ROUND GRAND PRIZE WINNER+GLOBAL FINALIST\n\n3. YIS STOCK PITCH COMPETITION STATE WINNER+GLOBAL SEMIFINALIST\n\n4. YIS SHARK TANK COMPETITION THIRD PRIZE\n\n5. PRESIDENT'S VOLUNTEER GOLD AWARD\n\nAcceptances\n\n1. Wharton",
    "structured_profile": {
      "demographics": {
        "gender": "Female",
        "race_ethnicity": "Asian",
        "residence": null,
        "income_bracket": "0-50k",
        "type_of_school": "Public School",
        "hooks": null,
        "intended_majors": "Business"
      },
      "academics": {
        "gpa": {
          "unweighted": 4.0,
          "weighted": 4.78
        },
        "course_count": {
          "honors": null,
          "ap": 13,
          "ib": null,
          "dual_enrollment": null
        },
        "senior_year_course_load": null
      },
      "standardized_testing": {
        "sat_i": {
          "total": 1540,
          "reading_writing": null,
          "math": null
        },
        "act": null
      },
      "extracurriculars": [
        "President of in-school stock exchange club",
        "President of in-school econ club",
        "Summer internship at Loreal as a finance intern",
        "Writer for an account with over 200k followers",
        "School district's student member of the board cluster representative",
        "Human rights commission student ambassador",
        "Chief intern at a non-profit music organization",
        "English Tutor of a non-profit",
        "Hostess at a restaurant",
        "Attended Wharton's LBW program",
        "Interned at Women's Federation",
        "Participated in Wharton's Investment Competition for 2 years"
      ],
      "awards_honors": [
        "GYEC US FINAL ROUND 3RD PRIZE",
        "GYEC US FINAL ROUND GRAND PRIZE WINNER+GLOBAL FINALIST",
        "YIS STOCK PITCH COMPETITION STATE WINNER+GLOBAL SEMIFINALIST",
        "YIS SHARK TANK COMPETITION THIRD PRIZE",
        "PRESIDENT'S VOLUNTEER GOLD AWARD"
      ],
      "letters_of_recommendation": null,
      "essays": null,
      "decisions": {
        "acceptances": [
          {
            "university": "Wharton",
            "decision_plan": "N/A"
          }
        ],
        "waitlists": null,
        "rejections": null
      },
      "additional_information": null
    }
  },

  {
    "post_text": "English Major ðŸŽ“\n\nDemographics\n\nAsian\nFemale\n200k+\nPublic School\nAcademics\n\n1580 SAT\n35 ACT\n9 AP's\n4 UW\n4.47 W\nExtracurriculars\n\n1. Lincoln-Douglas Head Coach\n\n2. President HS Instrumental Music Council\n\n3. Published Author/Independent Creative Writer\n\n4. Piano Coach/Teacher\n\n5. Lead Volunteer local library Teen Volunteer Program\n\n6. Vice President HS Literary Arts Club\n\n7. Varsity Debater HS Speech and Debate Team\n\n8. Pianist Performance and competition\n\n9. Volunteer/Secretary regional AAPI association Summer Camp\n\n10. 1st Red Belt Tang Soo Do\n\nAwards\n\n1. Statewide award for completing arts-focused summer program in creative writing\n\n2. 2nd place prestigious regional music competition\n\n3. National Merit Semifinalist\n\n4. Teen Ink Editor's Choice 2 time recipient\n\n5. Regional newspaper flash fiction contest Honorable Mention\n\nAcceptances\n\n1. Arizona State University\n\n2. Brown University",
    "structured_profile": {
      "demographics": {
        "gender": "Female",
        "race_ethnicity": "Asian",
        "residence": null,
        "income_bracket": "200k+",
        "type_of_school": "Public School",
        "hooks": null,
        "intended_majors": "English"
      },
      "academics": {
        "gpa": {
          "unweighted": 4.0,
          "weighted": 4.47
        },
        "course_count": {
          "honors": null,
          "ap": 9,
          "ib": null,
          "dual_enrollment": null
        },
        "senior_year_course_load": null
      },
      "standardized_testing": {
        "sat_i": {
          "total": 1580,
          "reading_writing": null,
          "math": null
        },
        "act": 35
      },
      "extracurriculars": [
        "Lincoln-Douglas Head Coach",
        "President HS Instrumental Music Council",
        "Published Author/Independent Creative Writer",
        "Piano Coach/Teacher",
        "Lead Volunteer local library Teen Volunteer Program",
        "Vice President HS Literary Arts Club",
        "Varsity Debater HS Speech and Debate Team",
        "Pianist Performance and competition",
        "Volunteer/Secretary regional AAPI association Summer Camp",
        "1st Red Belt Tang Soo Do"
      ],
      "awards_honors": [
        "Statewide award for completing arts-focused summer program in creative writing",
        "2nd place prestigious regional music competition",
        "National Merit Semifinalist",
        "Teen Ink Editor's Choice 2 time recipient",
        "Regional newspaper flash fiction contest Honorable Mention"
      ],
      "letters_of_recommendation": null,
      "essays": null,
      "decisions": {
        "acceptances": [
          {
            "university": "Arizona State University",
            "decision_plan": "N/A"
          },
          {
            "university": "Brown University",
            "decision_plan": "N/A"
          }
        ],
        "waitlists": null,
        "rejections": null
      },
      "additional_information": null
    }
  },

  {
    "post_text": "Computer Science Major ðŸŽ“\n\nDemographics\n\nWhite\nMale\n100k-200k\nPublic School\nAcademics\n\n36 ACT\n11 AP's\n4 UW\n4.6 W\nExtracurriculars\n\n1. Founder & President of school Computer Science Club\n\n2. Piano for ~7 years\n\n3. Community service for local organization\n\n4. Music production\n\n5. Programming\n\n6. Worked for family business\n\n7. Peer tutoring\n\n8. 2-week summer program at a university\n\n9. Science Olympiad\n\n10. week-long summer community service trip\n\nAwards\n\n1. National Merit Semifinalist\n\n2. Junior Marshal\n\n3. 2nd place in a local piano competition\n\n4. AP Scholar with Distinction\n\n5. Random honor societies\n\nAcceptances\n\n1. Penn",
    "structured_profile": {
      "demographics": {
        "gender": "Male",
        "race_ethnicity": "White",
        "residence": null,
        "income_bracket": "100k-200k",
        "type_of_school": "Public School",
        "hooks": null,
        "intended_majors": "Computer Science"
      },
      "academics": {
        "gpa": {
          "unweighted": 4.0,
          "weighted": 4.6
        },
        "course_count": {
          "honors": null,
          "ap": 11,
          "ib": null,
          "dual_enrollment": null
        },
        "senior_year_course_load": null
      },
      "standardized_testing": {
        "sat_i": null,
        "act": 36
      },
      "extracurriculars": [
        "Founder & President of school Computer Science Club",
        "Piano for ~7 years",
        "Community service for local organization",
        "Music production",
        "Programming",
        "Worked for family business",
        "Peer tutoring",
        "2-week summer program at a university",
        "Science Olympiad",
        "week-long summer community service trip"
      ],
      "awards_honors": [
        "National Merit Semifinalist",
        "Junior Marshal",
        "2nd place in a local piano competition",
        "AP Scholar with Distinction",
        "Random honor societies"
      ],
      "letters_of_recommendation": null,
      "essays": null,
      "decisions": {
        "acceptances": [
          {
            "university": "Penn",
            "decision_plan": "N/A"
          }
        ],
        "waitlists": null,
        "rejections": null
      },
      "additional_information": null
    }
  },

  {
    "post_text": "Data Science Major ðŸŽ“\n\nDemographics\n\nWhite\nMale\n100k-200k\nPublic School\nAcademics\n\n1600 SAT\n6 AP's\nExtracurriculars\n\n1. CS initiative\n\n2. Columbia research internship\n\n3. Princeton research internship\n\n4. History org volunteer\n\n5. Founded cultural school journal/magazine\n\n6. DEI involvement\n\n7. Rare instrument\n\n8. Pres of school hack-a-thon\n\n9. Startup internship\n\n10. Varsity fencing captain\n\nAwards\n\n1. 6-7 peer reviewed research papers and associated conference presentations\n\n2. Humanities-related comp 1st individually internationally\n\n3. 6x AIME Qual\n\n4. 2x Humanities essay comp 3rd\n\nAcceptances\n\n1. Columbia\n\n2. Penn State",
    "structured_profile": {
      "demographics": {
        "gender": "Male",
        "race_ethnicity": "White",
        "residence": null,
        "income_bracket": "100k-200k",
        "type_of_school": "Public School",
        "hooks": null,
        "intended_majors": "Data Science"
      },
      "academics": {
        "gpa": null,
        "course_count": {
          "honors": null,
          "ap": 6,
          "ib": null,
          "dual_enrollment": null
        },
        "senior_year_course_load": null
      },
      "standardized_testing": {
        "sat_i": {
          "total": 1600,
          "reading_writing": null,
          "math": null
        },
        "act": null
      },
      "extracurriculars": [
        "CS initiative",
        "Columbia research internship",
        "Princeton research internship",
        "History org volunteer",
        "Founded cultural school journal/magazine",
        "DEI involvement",
        "Rare instrument",
        "Pres of school hack-a-thon",
        "Startup internship",
        "Varsity fencing captain"
      ],
      "awards_honors": [
        "6-7 peer reviewed research papers and associated conference presentations",
        "Humanities-related comp 1st individually internationally",
        "6x AIME Qual",
        "2x Humanities essay comp 3rd"
      ],
      "letters_of_recommendation": null,
      "essays": null,
      "decisions": {
        "acceptances": [
          {
            "university": "Columbia",
            "decision_plan": "N/A"
          },
          {
            "university": "Penn State",
            "decision_plan": "N/A"
          }
        ],
        "waitlists": null,
        "rejections": null
      },
      "additional_information": null
    }
  },

  {
    "post_text": "Public Affairs Major ðŸŽ“\n\nDemographics\n\nAsian\nFemale\n0-50k\nPublic School\nAcademics\n\n1540 SAT\n35 ACT\n14 AP's\n4 UW\n4.8 W\nExtracurriculars\n\n1. Black Belt in Taekwondo (volunteered 100 hours\n\n2. instructed kids\n\n3. performed at festivals\n\n4. refereed at local tournament)\n\n5. President/VP of Honors Society (CSF/NHS)\n\n6. Research Assistant for PHD student\n\n7. Intern at old art school (made spreadsheets)\n\n8. Crochet (gifts for friends/family\n\n9. donate to women's shelters)\n\nAwards\n\n1. Attended free summer program at local private uni\n\n2. PVSA for Taekwondo (Silver)\n\n3. 3rd Degree Black Belt cert-kukkiwon\n\n4. national merit commended (1440 PSAT)\n\n5. student of the year awards\n\nAcceptances\n\n1. Brown",
    "structured_profile": {
      "demographics": {
        "gender": "Female",
        "race_ethnicity": "Asian",
        "residence": null,
        "income_bracket": "0-50k",
        "type_of_school": "Public School",
        "hooks": null,
        "intended_majors": "Public Affairs"
      },
      "academics": {
        "gpa": {
          "unweighted": 4.0,
          "weighted": 4.8
        },
        "course_count": {
          "honors": null,
          "ap": 14,
          "ib": null,
          "dual_enrollment": null
        },
        "senior_year_course_load": null
      },
      "standardized_testing": {
        "sat_i": {
          "total": 1540,
          "reading_writing": null,
          "math": null
        },
        "act": 35
      },
      "extracurriculars": [
        "Black Belt in Taekwondo (volunteered 100 hours, instructed kids, performed at festivals, refereed at local tournament)",
        "President/VP of Honors Society (CSF/NHS)",
        "Research Assistant for PHD student",
        "Intern at old art school (made spreadsheets)",
        "Crochet (gifts for friends/family, donate to women's shelters)"
      ],
      "awards_honors": [
        "Attended free summer program at local private uni",
        "PVSA for Taekwondo (Silver)",
        "3rd Degree Black Belt cert-kukkiwon",
        "National Merit Commended (1440 PSAT)",
        "Student of the Year awards"
      ],
      "letters_of_recommendation": null,
      "essays": null,
      "decisions": {
        "acceptances": [
          {
            "university": "Brown",
            "decision_plan": "N/A"
          }
        ],
        "waitlists": null,
        "rejections": null
      },
      "additional_information": null
    }
  },

  {
    "post_text": "Business Major ðŸŽ“\n\nDemographics\n\nAsian\nMale\n100k-200k\nPrivate School\nAcademics\n\n1500 SAT\n35 ACT\n6 AP's\n3.96 UW\n4.25 W\nExtracurriculars\n\n1. Swim coach for local summer swim team of 120+ swimmers\n\n2. President of school DECA chapter\n\n3. Debate competitor\n\n4. Language tutor for school Chinese program\n\n5. Student academic committee member\n\n6. Self-employed private swim instructor\n\n7. Family restaurant server/busser\n\n8. School investing club participant\n\n9. School math modeling club participant\n\nAwards\n\n1. Division champs as head coach of swim team\n\n2. National Merit Semifinalist\n\n3. AP Scholar with Distinction\n\nAcceptances\n\n1. NYU Stern",
    "structured_profile": {
      "demographics": {
        "gender": "Male",
        "race_ethnicity": "Asian",
        "residence": null,
        "income_bracket": "100k-200k",
        "type_of_school": "Private School",
        "hooks": null,
        "intended_majors": "Business"
      },
      "academics": {
        "gpa": {
          "unweighted": 3.96,
          "weighted": 4.25
        },
        "course_count": {
          "honors": null,
          "ap": 6,
          "ib": null,
          "dual_enrollment": null
        },
        "senior_year_course_load": null
      },
      "standardized_testing": {
        "sat_i": {
          "total": 1500,
          "reading_writing": null,
          "math": null
        },
        "act": 35
      },
      "extracurriculars": [
        "Swim coach for local summer swim team of 120+ swimmers",
        "President of school DECA chapter",
        "Debate competitor",
        "Language tutor for school Chinese program",
        "Student academic committee member",
        "Self-employed private swim instructor",
        "Family restaurant server/busser",
        "School investing club participant",
        "School math modeling club participant"
      ],
      "awards_honors": [
        "Division champs as head coach of swim team",
        "National Merit Semifinalist",
        "AP Scholar with Distinction"
      ],
      "letters_of_recommendation": null,
      "essays": null,
      "decisions": {
        "acceptances": [
          {
            "university": "NYU Stern",
            "decision_plan": "N/A"
          }
        ],
        "waitlists": null,
        "rejections": null
      },
      "additional_information": null
    }
  },

  {
    "post_text": "Computer Science Major ðŸŽ“\n\nDemographics\n\nAsian\nMale\n100k-200k\nPublic School\nAcademics\n\n1560 SAT\n13 AP's\n4 UW\nExtracurriculars\n\n1. Corporation - Co-Founder & CTO\n\n2. Non-Profit - Founder & CEO\n\n3. Non-profit - Lead Volunteer\n\n4. Research - Summer Student Research Assistant at Stanford\n\n5. Congressional Campaign Intern - Youth Team Leader\n\n6. Robotics - Programming Team Lead\n\n7. Hiking Enthusiast\n\n8. Car Enthusiast\n\nAwards\n\n1. Presidential Volunteer Service Award - Lifetime\n\n2. Leadership Award\n\n3. FIRST Inspire Award for Robotics\n\nAcceptances\n\n1. Stanford",
    "structured_profile": {
      "demographics": {
        "gender": "Male",
        "race_ethnicity": "Asian",
        "residence": null,
        "income_bracket": "100k-200k",
        "type_of_school": "Public School",
        "hooks": null,
        "intended_majors": "Computer Science"
      },
      "academics": {
        "gpa": {
          "unweighted": 4.0,
          "weighted": null
        },
        "course_count": {
          "honors": null,
          "ap": 13,
          "ib": null,
          "dual_enrollment": null
        },
        "senior_year_course_load": null
      },
      "standardized_testing": {
        "sat_i": {
          "total": 1560,
          "reading_writing": null,
          "math": null
        },
        "act": null
      },
      "extracurriculars": [
        "Corporation - Co-Founder & CTO",
        "Non-Profit - Founder & CEO",
        "Non-profit - Lead Volunteer",
        "Research - Summer Student Research Assistant at Stanford",
        "Congressional Campaign Intern - Youth Team Leader",
        "Robotics - Programming Team Lead",
        "Hiking Enthusiast",
        "Car Enthusiast"
      ],
      "awards_honors": [
        "Presidential Volunteer Service Award - Lifetime",
        "Leadership Award",
        "FIRST Inspire Award for Robotics"
      ],
      "letters_of_recommendation": null,
      "essays": null,
      "decisions": {
        "acceptances": [
          {
            "university": "Stanford",
            "decision_plan": "N/A"
          }
        ],
        "waitlists": null,
        "rejections": null
      },
      "additional_information": null
    }
  },

  {
    "post_text": "Mathematics Major ðŸŽ“\n\nDemographics\n\nAsian\nMale\n0-50k\nPublic School\nAcademics\n\n1570 SAT\n12 AP's\n4 UW\n4.311 W\nExtracurriculars\n\n1. Track\n\n2. Tutoring\n\n3. Activist Organization\n\nAwards\n\n1. Track awards\n\n2. Club soccer awards\n\n3. AP Scholar with Distinction\n\n4. Academic Decathlon awards\n\nAcceptances\n\n1. MIT",
    "structured_profile": {
      "demographics": {
        "gender": "Male",
        "race_ethnicity": "Asian",
        "residence": null,
        "income_bracket": "0-50k",
        "type_of_school": "Public School",
        "hooks": null,
        "intended_majors": "Mathematics"
      },
      "academics": {
        "gpa": {
          "unweighted": 4.0,
          "weighted": 4.311
        },
        "course_count": {
          "honors": null,
          "ap": 12,
          "ib": null,
          "dual_enrollment": null
        },
        "senior_year_course_load": null
      },
      "standardized_testing": {
        "sat_i": {
          "total": 1570,
          "reading_writing": null,
          "math": null
        },
        "act": null
      },
      "extracurriculars": ["Track", "Tutoring", "Activist Organization"],
      "awards_honors": [
        "Track awards",
        "Club soccer awards",
        "AP Scholar with Distinction",
        "Academic Decathlon awards"
      ],
      "letters_of_recommendation": null,
      "essays": null,
      "decisions": {
        "acceptances": [
          {
            "university": "MIT",
            "decision_plan": "N/A"
          }
        ],
        "waitlists": null,
        "rejections": null
      },
      "additional_information": null
    }
  },

  {
    "post_text": "Economics Major ðŸŽ“\n\nDemographics\n\nAsian\nMale\n0-50k\nPrivate School\nAcademics\n\n1500 SAT\n0 AP's\nExtracurriculars\n\n1. Founder | CEO\n\n2. Edtech platform for students with learning difficulties; Senior Regional Head (Youngest Leader) advocating Women's Health & Welfare; Head Boy liaising between students & teachers; Authored Paper in Educational Research on COVID impact on EdTech; Epidemiology and Clinical Research Assistant under Stanford University Researcher; Journalist and Writer for National Newspaper; Field Hockey\n\n3. Varsity Captain with multiple medals; Lead Guitarist with professional degree; Senior Volunteer in medical camps\n\nAwards\n\n1. Founder | Editor-in-Chief\n\n2. Published Psychological Thriller Novel; National Olympiad Rank Under 500/150\n\n3. 000+; CBSE Clusters National Level Bronze Medalist; Scholar Badge (Valedictorian); Student of the Year; Best Lead Guitarist; Dartmouth Deferred\n\nAcceptances\n\n1. Temple\n\n2. Drexel\n\n3. U of Houston",
    "structured_profile": {
      "demographics": {
        "gender": "Male",
        "race_ethnicity": "Asian",
        "residence": null,
        "income_bracket": "0-50k",
        "type_of_school": "Private School",
        "hooks": null,
        "intended_majors": "Economics"
      },
      "academics": {
        "gpa": null,
        "course_count": {
          "honors": null,
          "ap": 0,
          "ib": null,
          "dual_enrollment": null
        },
        "senior_year_course_load": null
      },
      "standardized_testing": {
        "sat_i": {
          "total": 1500,
          "reading_writing": null,
          "math": null
        },
        "act": null
      },
      "extracurriculars": [
        "Founder | CEO (Edtech platform for students with learning difficulties)",
        "Senior Regional Head (Youngest Leader) advocating Women's Health & Welfare",
        "Head Boy liaising between students & teachers",
        "Authored Paper in Educational Research on COVID impact on EdTech",
        "Epidemiology and Clinical Research Assistant under Stanford University Researcher",
        "Journalist and Writer for National Newspaper",
        "Field Hockey Varsity Captain with multiple medals",
        "Lead Guitarist with professional degree",
        "Senior Volunteer in medical camps"
      ],
      "awards_honors": [
        "Published Psychological Thriller Novel",
        "National Olympiad Rank Under 500/150000+",
        "CBSE Clusters National Level Bronze Medalist",
        "Scholar Badge (Valedictorian)",
        "Student of the Year",
        "Best Lead Guitarist"
      ],
      "letters_of_recommendation": null,
      "essays": null,
      "decisions": {
        "acceptances": [
          {
            "university": "Temple",
            "decision_plan": "N/A"
          },
          {
            "university": "Drexel",
            "decision_plan": "N/A"
          },
          {
            "university": "U of Houston",
            "decision_plan": "N/A"
          }
        ],
        "waitlists": null,
        "rejections": null
      },
      "additional_information": null
    }
  },

  {
    "post_text": "Molecular Biology Major ðŸŽ“\n\nDemographics\n\nWhite\nMale\n0-50k\nPrivate School\nAcademics\n\n4 UW\n3.978 W\nExtracurriculars\n\n1. Founded a real-estate technology start-up\n\n2. Helped lead my countries first student-led REDACTED FUND\n\n3. Author of an almost published book on Bitcoin\n\n4. Government research\n\n5. Glioblastoma metastasis research\n\n6. Archaeology research\n\n7. Tutoring ADHD/accelerated learning kids\n\n8. Nationwide game show 4th place\n\n9. Photography\n\n10. Ran a highly profitable NFT arbitrage fund\n\nAwards\n\n1. 1 mark away from topping the state in Biology and Geography\n\n2. Won 8.5k at a prestigious pitching comp\n\n3. Offerred a 160k scholarship to national uni for bioengineering\n\n4. Top 5 highest achieving greek students in my state\n\n5. School award for topping bio\n\n6. school award for being one of the top art and sport students\n\nAcceptances\n\n1. Yale",
    "structured_profile": {
      "demographics": {
        "gender": "Male",
        "race_ethnicity": "White",
        "residence": null,
        "income_bracket": "0-50k",
        "type_of_school": "Private School",
        "hooks": null,
        "intended_majors": "Molecular Biology"
      },
      "academics": {
        "gpa": {
          "unweighted": 4.0,
          "weighted": 3.978
        },
        "course_count": null,
        "senior_year_course_load": null
      },
      "standardized_testing": null,
      "extracurriculars": [
        "Founded a real-estate technology start-up",
        "Helped lead my countries first student-led REDACTED FUND",
        "Author of an almost published book on Bitcoin",
        "Government research",
        "Glioblastoma metastasis research",
        "Archaeology research",
        "Tutoring ADHD/accelerated learning kids",
        "Nationwide game show 4th place",
        "Photography",
        "Ran a highly profitable NFT arbitrage fund"
      ],
      "awards_honors": [
        "1 mark away from topping the state in Biology and Geography",
        "Won 8.5k at a prestigious pitching comp",
        "Offerred a 160k scholarship to national uni for bioengineering",
        "Top 5 highest achieving greek students in my state",
        "School award for topping bio",
        "school award for being one of the top art and sport students"
      ],
      "letters_of_recommendation": null,
      "essays": null,
      "decisions": {
        "acceptances": [
          {
            "university": "Yale",
            "decision_plan": "N/A"
          }
        ],
        "waitlists": null,
        "rejections": null
      },
      "additional_information": null
    }
  },

  {
    "post_text": "Sociology Major ðŸŽ“\n\nDemographics\n\nAfrican American\nFemale\n50k-100k\nPublic School\nAcademics\n\n33 ACT\n7 AP's\n3.9732 W\nExtracurriculars\n\n1. Speech and Debate (4 years\n\n2. President)\n\n3. Research in Biosensors\n\n4. Founded Political Club\n\n5. Student Council VP\n\n6. Key Club LTG\n\n7. Community Cooking\n\n8. School Ambassador\n\nAwards\n\n1. NSDA Finalist\n\n2. State Runner-Up in Essay Contest\n\n3. State Champ in Speech Event\n\n4. College Board Recognition\n\nAcceptances\n\n1. University of Georgia\n\n2. Yale University",
    "structured_profile": {
      "demographics": {
        "gender": "Female",
        "race_ethnicity": "African American",
        "residence": null,
        "income_bracket": "50k-100k",
        "type_of_school": "Public School",
        "hooks": null,
        "intended_majors": "Sociology"
      },
      "academics": {
        "gpa": {
          "unweighted": null,
          "weighted": 3.9732
        },
        "course_count": {
          "honors": null,
          "ap": 7,
          "ib": null,
          "dual_enrollment": null
        },
        "senior_year_course_load": null
      },
      "standardized_testing": {
        "sat_i": null,
        "act": 33
      },
      "extracurriculars": [
        "Speech and Debate (4 years, President)",
        "Research in Biosensors",
        "Founded Political Club",
        "Student Council VP",
        "Key Club LTG",
        "Community Cooking",
        "School Ambassador"
      ],
      "awards_honors": [
        "NSDA Finalist",
        "State Runner-Up in Essay Contest",
        "State Champ in Speech Event",
        "College Board Recognition"
      ],
      "letters_of_recommendation": null,
      "essays": null,
      "decisions": {
        "acceptances": [
          {
            "university": "University of Georgia",
            "decision_plan": "N/A"
          },
          {
            "university": "Yale University",
            "decision_plan": "N/A"
          }
        ],
        "waitlists": null,
        "rejections": null
      },
      "additional_information": null
    }
  },

  {
    "post_text": "Statistical Science Major ðŸŽ“\n\nDemographics\n\nAsian\nFemale\n0-50k\nPublic School\nAcademics\n\n1530 SAT\n8 AP's\n3.92 UW\n4.58 W\nExtracurriculars\n\n1. Speech Mentor\n\n2. President of STEM Club\n\n3. President of French Club\n\n4. VP of NHS\n\n5. Bio-Med Summer Program\n\n6. Student Govt Summer Program\n\n7. TA\n\n8. Volunteer\n\n9. English Tutor\n\nAwards\n\n1. Speech State 6th Place & National Qualifier\n\n2. PSAT Commended Student\n\n3. AP Scholar with Distinction\n\n4. Honorable Mention - 2 State Art Competitions\n\n5. Regional 2-time Silver Key Winner - Scholastic Art Contest\n\nAcceptances\n\n1. Cornell",
    "structured_profile": {
      "demographics": {
        "gender": "Female",
        "race_ethnicity": "Asian",
        "residence": null,
        "income_bracket": "0-50k",
        "type_of_school": "Public School",
        "hooks": null,
        "intended_majors": "Statistical Science"
      },
      "academics": {
        "gpa": {
          "unweighted": 3.92,
          "weighted": 4.58
        },
        "course_count": {
          "honors": null,
          "ap": 8,
          "ib": null,
          "dual_enrollment": null
        },
        "senior_year_course_load": null
      },
      "standardized_testing": {
        "sat_i": {
          "total": 1530,
          "reading_writing": null,
          "math": null
        },
        "act": null
      },
      "extracurriculars": [
        "Speech Mentor",
        "President of STEM Club",
        "President of French Club",
        "VP of NHS",
        "Bio-Med Summer Program",
        "Student Govt Summer Program",
        "TA",
        "Volunteer",
        "English Tutor"
      ],
      "awards_honors": [
        "Speech State 6th Place & National Qualifier",
        "PSAT Commended Student",
        "AP Scholar with Distinction",
        "Honorable Mention - 2 State Art Competitions",
        "Regional 2-time Silver Key Winner - Scholastic Art Contest"
      ],
      "letters_of_recommendation": null,
      "essays": null,
      "decisions": {
        "acceptances": [
          {
            "university": "Cornell",
            "decision_plan": "N/A"
          }
        ],
        "waitlists": null,
        "rejections": null
      },
      "additional_information": null
    }
  },

  {
    "post_text": "Business Major ðŸŽ“\n\nDemographics\n\nAsian\nFemale\n0-50k\nPublic School\nAcademics\n\n1490 SAT\n0 AP's\n3.76 UW\nExtracurriculars\n\n1. Co-founder and Manager of sustainable Start-up business\n\n2. Research co-author\n\n3. Vice-president of project supporting underprivileged artists\n\n4. Vice-president of club providing emotional support\n\n5. Head of Communication of project about finance and investment for Gen Z\n\n6. Flyer at schoolâ€™s cheerleading club\n\n7. Internship at Marketing Department for large Joint Stock Corporation in Vietnam\n\n8. Content intern for start-up business\n\n9. Collaborator with PWC\n\nAwards\n\n1. N/A\n\nAcceptances\n\n1. Davidson College\n\n2. Purdue University\n\n3. University of Richmond\n\n4. University of Florida\n\n5. Macalester College\n\n6. Babson College\n\n7. Fordham University\n\n8. University of South Florida",
    "structured_profile": {
      "demographics": {
        "gender": "Female",
        "race_ethnicity": "Asian",
        "residence": null,
        "income_bracket": "0-50k",
        "type_of_school": "Public School",
        "hooks": null,
        "intended_majors": "Business"
      },
      "academics": {
        "gpa": {
          "unweighted": 3.76,
          "weighted": null
        },
        "course_count": {
          "honors": null,
          "ap": 0,
          "ib": null,
          "dual_enrollment": null
        },
        "senior_year_course_load": null
      },
      "standardized_testing": {
        "sat_i": {
          "total": 1490,
          "reading_writing": null,
          "math": null
        },
        "act": null
      },
      "extracurriculars": [
        "Co-founder and Manager of sustainable Start-up business",
        "Research co-author",
        "Vice-president of project supporting underprivileged artists",
        "Vice-president of club providing emotional support",
        "Head of Communication of project about finance and investment for Gen Z",
        "Flyer at schoolâ€™s cheerleading club",
        "Internship at Marketing Department for large Joint Stock Corporation in Vietnam",
        "Content intern for start-up business",
        "Collaborator with PWC"
      ],
      "awards_honors": null,
      "letters_of_recommendation": null,
      "essays": null,
      "decisions": {
        "acceptances": [
          {
            "university": "Davidson College",
            "decision_plan": "N/A"
          },
          {
            "university": "Purdue University",
            "decision_plan": "N/A"
          },
          {
            "university": "University of Richmond",
            "decision_plan": "N/A"
          },
          {
            "university": "University of Florida",
            "decision_plan": "N/A"
          },
          {
            "university": "Macalester College",
            "decision_plan": "N/A"
          },
          {
            "university": "Babson College",
            "decision_plan": "N/A"
          },
          {
            "university": "Fordham University",
            "decision_plan": "N/A"
          },
          {
            "university": "University of South Florida",
            "decision_plan": "N/A"
          }
        ],
        "waitlists": null,
        "rejections": null
      },
      "additional_information": null
    }
  },

  {
    "post_text": "Mechanical Engineering Major ðŸŽ“\n\nDemographics\n\nAsian\nFemale\n200k+\nPrivate School\nAcademics\n\n1530 SAT\n34 ACT\nExtracurriculars\n\n1. Summer internship at local university aerodynamics lab\n\n2. Trombone player\n\n3. Co-president of Engineering Society\n\n4. Guest Speaker at Feminism Society\n\n5. Leader of a Volunteer Program\n\n6. Assistant Coach for Taekwondo\n\n7. Head writer for aerospace engineering for school publication\n\n8. Royal Air Force cadet\n\n9. Lead tenor in school choir\n\n10. Customer service summer intern\n\nAwards\n\n1. Duke of Edinburgh Silver\n\n2. Intermediate Maths Challenge Gold\n\n3. Pink Kangaroo Merit\n\n4. Senior Maths Challenge Gold\n\n5. UK Chemistry Olympiad Silver\n\n6. Bebras Challenge Distinction\n\n7. Oxford Computing Challenge Qualifer\n\nAcceptances\n\n1. Princeton",
    "structured_profile": {
      "demographics": {
        "gender": "Female",
        "race_ethnicity": "Asian",
        "residence": null,
        "income_bracket": "200k+",
        "type_of_school": "Private School",
        "hooks": null,
        "intended_majors": "Mechanical Engineering"
      },
      "academics": null,
      "standardized_testing": {
        "sat_i": {
          "total": 1530,
          "reading_writing": null,
          "math": null
        },
        "act": 34
      },
      "extracurriculars": [
        "Summer internship at local university aerodynamics lab",
        "Trombone player",
        "Co-president of Engineering Society",
        "Guest Speaker at Feminism Society",
        "Leader of a Volunteer Program",
        "Assistant Coach for Taekwondo",
        "Head writer for aerospace engineering for school publication",
        "Royal Air Force cadet",
        "Lead tenor in school choir",
        "Customer service summer intern"
      ],
      "awards_honors": [
        "Duke of Edinburgh Silver",
        "Intermediate Maths Challenge Gold",
        "Pink Kangaroo Merit",
        "Senior Maths Challenge Gold",
        "UK Chemistry Olympiad Silver",
        "Bebras Challenge Distinction",
        "Oxford Computing Challenge Qualifer"
      ],
      "letters_of_recommendation": null,
      "essays": null,
      "decisions": {
        "acceptances": [
          {
            "university": "Princeton",
            "decision_plan": "N/A"
          }
        ],
        "waitlists": null,
        "rejections": null
      },
      "additional_information": null
    }
  },

  {
    "post_text": "Neuroscience Major ðŸŽ“\n\nDemographics\n\nAsian\nMale\n200k+\nPublic School\nAcademics\n\n1520 SAT\n23 ACT\n10 AP's\n4 UW\n4.5 W\nExtracurriculars\n\n1. Paid neuroimmunology research (significant research experience)\n\n2. Teach at local preschool\n\n3. Worked at pizza shop\n\n4. Founded school club\n\n5. Gardening\n\n6. Tutoring\n\n7. Teacher aide\n\n8. Hospital volunteering\n\nAwards\n\n1. 1. won national neuroscience competition\n\n2. 2. top 30 at national neuroscience competition\n\n3. 3. won state neuroscience competition\n\n4. 4. national merit semi finalist\n\n5. 5. N/A\n\nAcceptances\n\n1. Duke",
    "structured_profile": {
      "demographics": {
        "gender": "Male",
        "race_ethnicity": "Asian",
        "residence": null,
        "income_bracket": "200k+",
        "type_of_school": "Public School",
        "hooks": null,
        "intended_majors": "Neuroscience"
      },
      "academics": {
        "gpa": {
          "unweighted": 4.0,
          "weighted": 4.5
        },
        "course_count": {
          "honors": null,
          "ap": 10,
          "ib": null,
          "dual_enrollment": null
        },
        "senior_year_course_load": null
      },
      "standardized_testing": {
        "sat_i": {
          "total": 1520,
          "reading_writing": null,
          "math": null
        },
        "act": 23
      },
      "extracurriculars": [
        "Paid neuroimmunology research (significant research experience)",
        "Teach at local preschool",
        "Worked at pizza shop",
        "Founded school club",
        "Gardening",
        "Tutoring",
        "Teacher aide",
        "Hospital volunteering"
      ],
      "awards_honors": [
        "won national neuroscience competition",
        "top 30 at national neuroscience competition",
        "won state neuroscience competition",
        "national merit semi finalist"
      ],
      "letters_of_recommendation": null,
      "essays": null,
      "decisions": {
        "acceptances": [
          {
            "university": "Duke",
            "decision_plan": "N/A"
          }
        ],
        "waitlists": null,
        "rejections": null
      },
      "additional_information": null
    }
  },

  {
    "post_text": "Secondary Teaching Major ðŸŽ“\n\nDemographics\n\nOther\nMale\n0-50k\nPublic School\nAcademics\n\n1410 SAT\n7 AP's\n3.77 UW\n4.34 W\nExtracurriculars\n\n1. 2 years at fast food restaurant (asst. Manager\n\n2. trained 10 employees)\n\n3. Paid job as math tutor\n\n4. Leadership position in school service club\n\n5. Volunteer tutor\n\n6. Teacher Assistant in school\n\n7. Freshman mentor in school\n\n8. Cultural club member\n\n9. Family responsibilities\n\nAwards\n\n1. AP Scholar with Honor\n\n2. National African American Recognition\n\n3. Principalâ€™s List Honor Roll\n\nAcceptances\n\n1. Eastern Illinois University\n\n2. University of Iowa\n\n3. Augustana College",
    "structured_profile": {
      "demographics": {
        "gender": "Male",
        "race_ethnicity": "Other",
        "residence": null,
        "income_bracket": "0-50k",
        "type_of_school": "Public School",
        "hooks": null,
        "intended_majors": "Secondary Teaching Major"
      },
      "academics": {
        "gpa": {
          "unweighted": 3.77,
          "weighted": 4.34
        },
        "course_count": {
          "honors": null,
          "ap": 7,
          "ib": null,
          "dual_enrollment": null
        },
        "senior_year_course_load": null
      },
      "standardized_testing": {
        "sat_i": {
          "total": 1410,
          "reading_writing": null,
          "math": null
        },
        "act": null
      },
      "extracurriculars": [
        "2 years at fast food restaurant (asst. Manager trained 10 employees)",
        "Paid job as math tutor",
        "Leadership position in school service club",
        "Volunteer tutor",
        "Teacher Assistant in school",
        "Freshman mentor in school",
        "Cultural club member",
        "Family responsibilities"
      ],
      "awards_honors": [
        "AP Scholar with Honor",
        "National African American Recognition",
        "Principalâ€™s List Honor Roll"
      ],
      "letters_of_recommendation": null,
      "essays": null,
      "decisions": {
        "acceptances": [
          {
            "university": "Eastern Illinois University",
            "decision_plan": "N/A"
          },
          {
            "university": "University of Iowa",
            "decision_plan": "N/A"
          },
          {
            "university": "Augustana College",
            "decision_plan": "N/A"
          }
        ],
        "waitlists": null,
        "rejections": null
      },
      "additional_information": null
    }
  },

  {
    "post_text": "Sociology Major ðŸŽ“\n\nDemographics\n\nAsian\nFemale\n100k-200k\nPublic School\nAcademics\n\n1530 SAT\n35 ACT\n6 AP's\n4.34 W\nExtracurriculars\n\n1. Art Instagram with 5k+ followers\n\n2. Internship with local family lawyer\n\n3. Art director of school newspaper\n\n4. Personal research project with a PhD\n\n5. Cultural networking volunteer\n\n6. Freelance art commissions\n\n7. Tutoring\n\n8. Helped mom in civil case\n\n9. Graphic designer for local neurodiversity nonprofit\n\n10. CIT at local YMCA\n\nAwards\n\n1. National Merit Semifinalist\n\n2. AP Scholar with Distinction\n\n3. Scholastic Art & Writing Regional Gold & Silver Keys\n\n4. Honor Roll\n\n5. Member of French Honor Society\n\nAcceptances\n\n1. Smith\n\n2. Northeastern\n\n3. Wellesley\n\n4. Hamilton\n\n5. Mt Holyoke\n\n6. Vassar\n\n7. GW\n\n8. William & Mary\n\n9. BC\n\n10. BU\n\n11. Georgetown\n\n12. Vanderbilt\n\n13. Williams\n\n14. UPenn\n\n15. Columbia\n\n16. Barnard\n\n17. NYU",
    "structured_profile": {
      "demographics": {
        "gender": "Female",
        "race_ethnicity": "Asian",
        "residence": null,
        "income_bracket": "100k-200k",
        "type_of_school": "Public School",
        "hooks": null,
        "intended_majors": "Sociology"
      },
      "academics": {
        "gpa": {
          "unweighted": null,
          "weighted": 4.34
        },
        "course_count": {
          "honors": null,
          "ap": 6,
          "ib": null,
          "dual_enrollment": null
        },
        "senior_year_course_load": null
      },
      "standardized_testing": {
        "sat_i": {
          "total": 1530,
          "reading_writing": null,
          "math": null
        },
        "act": 35
      },
      "extracurriculars": [
        "Art Instagram with 5k+ followers",
        "Internship with local family lawyer",
        "Art director of school newspaper",
        "Personal research project with a PhD",
        "Cultural networking volunteer",
        "Freelance art commissions",
        "Tutoring",
        "Helped mom in civil case",
        "Graphic designer for local neurodiversity nonprofit",
        "CIT at local YMCA"
      ],
      "awards_honors": [
        "National Merit Semifinalist",
        "AP Scholar with Distinction",
        "Scholastic Art & Writing Regional Gold & Silver Keys",
        "Honor Roll",
        "Member of French Honor Society"
      ],
      "letters_of_recommendation": null,
      "essays": null,
      "decisions": {
        "acceptances": [
          {
            "university": "Smith",
            "decision_plan": "N/A"
          },
          {
            "university": "Northeastern",
            "decision_plan": "N/A"
          },
          {
            "university": "Wellesley",
            "decision_plan": "N/A"
          },
          {
            "university": "Hamilton",
            "decision_plan": "N/A"
          },
          {
            "university": "Mt Holyoke",
            "decision_plan": "N/A"
          },
          {
            "university": "Vassar",
            "decision_plan": "N/A"
          },
          {
            "university": "GW",
            "decision_plan": "N/A"
          },
          {
            "university": "William & Mary",
            "decision_plan": "N/A"
          },
          {
            "university": "BC",
            "decision_plan": "N/A"
          },
          {
            "university": "BU",
            "decision_plan": "N/A"
          },
          {
            "university": "Georgetown",
            "decision_plan": "N/A"
          },
          {
            "university": "Vanderbilt",
            "decision_plan": "N/A"
          },
          {
            "university": "Williams",
            "decision_plan": "N/A"
          },
          {
            "university": "UPenn",
            "decision_plan": "N/A"
          },
          {
            "university": "Columbia",
            "decision_plan": "N/A"
          },
          {
            "university": "Barnard",
            "decision_plan": "N/A"
          },
          {
            "university": "NYU",
            "decision_plan": "N/A"
          }
        ],
        "waitlists": null,
        "rejections": null
      },
      "additional_information": null
    }
  },

  {
    "post_text": "History Major ðŸŽ“\n\nDemographics\n\nWhite\nMale\n50k-100k\nPublic School\nAcademics\n\n1430 SAT\n36 ACT\n15 AP's\n3.96 UW\n4.49 W\nExtracurriculars\n\n1. Political lobbying\n\n2. Transcriber with the Library of Congress\n\n3. Member of redacted's Advisory council\n\n4. School ambassador\n\n5. Redacted Governance Council Member\n\n6. School's mock trial club\n\n7. Eagle Scout\n\n8. Redacted Fellow at Political Science focused company\n\n9. head editor for redacted\n\n10. cashier at redacted\n\nAwards\n\n1. Redacted Historical redacted Contest Finalist\n\n2. Senate Youth Program Finalist\n\n3. redacted student of the year\n\n4. Eagle Scout\n\n5. school nominee for honors program in mathematics\n\nAcceptances\n\n1. UGA\n\n2. University of Alabama\n\n3. Harvard",
    "structured_profile": {
      "demographics": {
        "gender": "Male",
        "race_ethnicity": "White",
        "residence": null,
        "income_bracket": "50k-100k",
        "type_of_school": "Public School",
        "hooks": null,
        "intended_majors": "History"
      },
      "academics": {
        "gpa": {
          "unweighted": 3.96,
          "weighted": 4.49
        },
        "course_count": {
          "honors": null,
          "ap": 15,
          "ib": null,
          "dual_enrollment": null
        },
        "senior_year_course_load": null
      },
      "standardized_testing": {
        "sat_i": {
          "total": 1430,
          "reading_writing": null,
          "math": null
        },
        "act": 36
      },
      "extracurriculars": [
        "Political lobbying",
        "Transcriber with the Library of Congress",
        "Member of redacted's Advisory council",
        "School ambassador",
        "Redacted Governance Council Member",
        "School's mock trial club",
        "Eagle Scout",
        "Redacted Fellow at Political Science focused company",
        "head editor for redacted",
        "cashier at redacted"
      ],
      "awards_honors": [
        "Redacted Historical redacted Contest Finalist",
        "Senate Youth Program Finalist",
        "redacted student of the year",
        "Eagle Scout",
        "school nominee for honors program in mathematics"
      ],
      "letters_of_recommendation": null,
      "essays": null,
      "decisions": {
        "acceptances": [
          {
            "university": "UGA",
            "decision_plan": "N/A"
          },
          {
            "university": "University of Alabama",
            "decision_plan": "N/A"
          },
          {
            "university": "Harvard",
            "decision_plan": "N/A"
          }
        ],
        "waitlists": null,
        "rejections": null
      },
      "additional_information": null
    }
  },

  {
    "post_text": "Game Design Major ðŸŽ“\n\nDemographics\n\nAsian\nFemale\n50k-100k\nPrivate School\nAcademics\n\n1540 SAT\n7 AP's\nExtracurriculars\n\n1. Founder and Head of School Club (9 - 12)\n\n2. Passion Project (Unfinished/continuing lol) (9 - 12)\n\n3. NYU Game Design Summer Program (10)\n\n4. Independent Research on Gacha Games (10)\n\n5. City Library Council Member and Editor for the Library's Teen Magazine (10 - 12)\n\n6. School Newspaper Writer + Year Book Illustrator (11 - 12)\n\n7. Tutoring Volunteer Service (Grade 9 - 12)\n\n8. 7Cups (9 - 12)\n\n9. School Ambassador (12) + Tutor (10 - 12)\n\n10. Flute player in school band (10 - 12)\n\nAwards\n\n1. Scholastic Art & Writing Awards (gold and silver keys\n\n2. honourable mentions)\n\n3. CCC Distinction (11)\n\n4. Award of Distinction (school level\n\n5. all years of high school)\n\nAcceptances\n\n1. NYU",
    "structured_profile": {
      "demographics": {
        "gender": "Female",
        "race_ethnicity": "Asian",
        "residence": null,
        "income_bracket": "50k-100k",
        "type_of_school": "Private School",
        "hooks": null,
        "intended_majors": "Game Design"
      },
      "academics": {
        "gpa": null,
        "course_count": {
          "honors": null,
          "ap": 7,
          "ib": null,
          "dual_enrollment": null
        },
        "senior_year_course_load": null
      },
      "standardized_testing": {
        "sat_i": {
          "total": 1540,
          "reading_writing": null,
          "math": null
        },
        "act": null
      },
      "extracurriculars": [
        "Founder and Head of School Club (9 - 12)",
        "Passion Project (Unfinished/continuing lol) (9 - 12)",
        "NYU Game Design Summer Program (10)",
        "Independent Research on Gacha Games (10)",
        "City Library Council Member and Editor for the Library's Teen Magazine (10 - 12)",
        "School Newspaper Writer + Year Book Illustrator (11 - 12)",
        "Tutoring Volunteer Service (Grade 9 - 12)",
        "7Cups (9 - 12)",
        "School Ambassador (12) + Tutor (10 - 12)",
        "Flute player in school band (10 - 12)"
      ],
      "awards_honors": [
        "Scholastic Art & Writing Awards (gold and silver keys, honourable mentions)",
        "CCC Distinction (11)",
        "Award of Distinction (school level, all years of high school)"
      ],
      "letters_of_recommendation": null,
      "essays": null,
      "decisions": {
        "acceptances": [
          {
            "university": "NYU",
            "decision_plan": "N/A"
          }
        ],
        "waitlists": null,
        "rejections": null
      },
      "additional_information": null
    }
  },

  {
    "post_text": "Biology Major ðŸŽ“\n\nDemographics\n\nAsian\nFemale\n200k+\nPublic School\nAcademics\n\n32 ACT\n9 AP's\n3.8 UW\n4.4 W\nExtracurriculars\n\n1. JV Basketball\n\n2. Concert Band\n\n3. Marching Band\n\n4. Jazz Band\n\n5. National Honor Society\n\n6. minimum wage job\n\nAwards\n\n1. Freshman of the Year in Concert Band\n\n2. Brass Player of the Year in Concert Band\n\n3. Freshman of the Year in Marching Band\n\n4. Freshman of the Year in Jazz Band\n\n5. Sophomore of the Year in Marching Band\n\n6. Sophomore of the Year in Jazz Band\n\n7. AP scholar with distinction\n\nAcceptances\n\n1. UCSD\n\n2. UCSB\n\n3. UCI\n\n4. UCD\n\n5. Cal Poly SLO\n\n6. UIUC",
    "structured_profile": {
      "demographics": {
        "gender": "Female",
        "race_ethnicity": "Asian",
        "residence": null,
        "income_bracket": "200k+",
        "type_of_school": "Public School",
        "hooks": null,
        "intended_majors": "Biology"
      },
      "academics": {
        "gpa": {
          "unweighted": 3.8,
          "weighted": 4.4
        },
        "course_count": {
          "honors": null,
          "ap": 9,
          "ib": null,
          "dual_enrollment": null
        },
        "senior_year_course_load": null
      },
      "standardized_testing": {
        "sat_i": null,
        "act": 32
      },
      "extracurriculars": [
        "JV Basketball",
        "Concert Band",
        "Marching Band",
        "Jazz Band",
        "National Honor Society",
        "minimum wage job"
      ],
      "awards_honors": [
        "Freshman of the Year in Concert Band",
        "Brass Player of the Year in Concert Band",
        "Freshman of the Year in Marching Band",
        "Freshman of the Year in Jazz Band",
        "Sophomore of the Year in Marching Band",
        "Sophomore of the Year in Jazz Band",
        "AP scholar with distinction"
      ],
      "letters_of_recommendation": null,
      "essays": null,
      "decisions": {
        "acceptances": [
          {
            "university": "UCSD",
            "decision_plan": "N/A"
          },
          {
            "university": "UCSB",
            "decision_plan": "N/A"
          },
          {
            "university": "UCI",
            "decision_plan": "N/A"
          },
          {
            "university": "UCD",
            "decision_plan": "N/A"
          },
          {
            "university": "Cal Poly SLO",
            "decision_plan": "N/A"
          },
          {
            "university": "UIUC",
            "decision_plan": "N/A"
          }
        ],
        "waitlists": null,
        "rejections": null
      },
      "additional_information": null
    }
  },

  {
    "post_text": "Electrical Engineering Major ðŸŽ“\n\nDemographics\n\nWhite\nFemale\n100k-200k\nPublic School\nAcademics\n\n1550 SAT\n13 AP's\n4 UW\nExtracurriculars\n\n1. Sport (captain)\n\n2. Summer research program\n\n3. Fundraising\n\n4. Volunteering\n\nAwards\n\n1. National Merit Semifinalist\n\nAcceptances\n\n1. MIT",
    "structured_profile": {
      "demographics": {
        "gender": "Female",
        "race_ethnicity": "White",
        "residence": null,
        "income_bracket": "100k-200k",
        "type_of_school": "Public School",
        "hooks": null,
        "intended_majors": "Electrical Engineering"
      },
      "academics": {
        "gpa": {
          "unweighted": 4.0,
          "weighted": null
        },
        "course_count": {
          "honors": null,
          "ap": 13,
          "ib": null,
          "dual_enrollment": null
        },
        "senior_year_course_load": null
      },
      "standardized_testing": {
        "sat_i": {
          "total": 1550,
          "reading_writing": null,
          "math": null
        },
        "act": null
      },
      "extracurriculars": [
        "Sport (captain)",
        "Summer research program",
        "Fundraising",
        "Volunteering"
      ],
      "awards_honors": ["National Merit Semifinalist"],
      "letters_of_recommendation": null,
      "essays": null,
      "decisions": {
        "acceptances": [
          {
            "university": "MIT",
            "decision_plan": "N/A"
          }
        ],
        "waitlists": null,
        "rejections": null
      },
      "additional_information": null
    }
  },

  {
    "post_text": "Political Science Major ðŸŽ“\n\nDemographics\n\nAsian\nFemale\n100k-200k\nPublic School\nAcademics\n\n1530 SAT\n12 AP's\n4 UW\n4.7 W\nExtracurriculars\n\n1. Legislative Intern\n\n2. Colorado State Senate\n\n3. Founder & President\n\n4. Harmony House (volunteer performance group that played for assisted living homes)\n\n5. Assistant Chief People Officer\n\n6. The Institute for Youth in Policy\n\n7. Legal Intern\n\n8. local law firm\n\n9. State Youth Council (SYC)\n\n10. Youth Leader for state Workforce Development Council (CWDC)\n\n11. Student & Elected Secretary of Student Board\n\n12. state governor's school/leadership program\n\n13. Youth Council on Mental Health\n\n14. Youth Leader\n\n15. associated with children's hospital\n\n16. Co-Founder & Co-President\n\n17. Diversity Alliance (school's first club based on ethnic/racial diversity)\n\n18. Mock Trial attorney (with a different school\n\n19. my school didn't have mock trial)\n\n20. President\n\n21. Key Club\n\nAwards\n\n1. National History Day State Finalist\n\n2. AP Scholar w/ Distinction\n\n3. ALA Colorado Girls State Delegate\n\n4. Mock Trial Best Opener\n\n5. All-County 6th Chair Clarinet\n\nAcceptances\n\n1. Brown University",
    "structured_profile": {
      "demographics": {
        "gender": "Female",
        "race_ethnicity": "Asian",
        "residence": null,
        "income_bracket": "100k-200k",
        "type_of_school": "Public School",
        "hooks": null,
        "intended_majors": "Political Science"
      },
      "academics": {
        "gpa": {
          "unweighted": 4.0,
          "weighted": 4.7
        },
        "course_count": {
          "honors": null,
          "ap": 12,
          "ib": null,
          "dual_enrollment": null
        },
        "senior_year_course_load": null
      },
      "standardized_testing": {
        "sat_i": {
          "total": 1530,
          "reading_writing": null,
          "math": null
        },
        "act": null
      },
      "extracurriculars": [
        "Legislative Intern, Colorado State Senate",
        "Founder & President, Harmony House (volunteer performance group that played for assisted living homes)",
        "Assistant Chief People Officer, The Institute for Youth in Policy",
        "Legal Intern, local law firm",
        "State Youth Council (SYC)",
        "Youth Leader for state Workforce Development Council (CWDC)",
        "Student & Elected Secretary of Student Board, state governor's school/leadership program",
        "Youth Council on Mental Health",
        "Youth Leader associated with children's hospital",
        "Co-Founder & Co-President, Diversity Alliance (school's first club based on ethnic/racial diversity)",
        "Mock Trial attorney (with a different school, my school didn't have mock trial)",
        "President, Key Club"
      ],
      "awards_honors": [
        "National History Day State Finalist",
        "AP Scholar w/ Distinction",
        "ALA Colorado Girls State Delegate",
        "Mock Trial Best Opener",
        "All-County 6th Chair Clarinet"
      ],
      "letters_of_recommendation": null,
      "essays": null,
      "decisions": {
        "acceptances": [
          {
            "university": "Brown University",
            "decision_plan": "N/A"
          }
        ],
        "waitlists": null,
        "rejections": null
      },
      "additional_information": null
    }
  },

  {
    "post_text": "Accounting Major ðŸŽ“\n\nDemographics\n\nAsian\nMale\n100k-200k\nPrivate School\nAcademics\n\n1420 SAT\n10 AP's\n3.8 UW\n4.2 W\nExtracurriculars\n\n1. Worked at a boba shop part-time\n\n2. JROTC cadet corporal\n\n3. 3rd Grade Assistant Teacher for underrepresented minorities\n\n4. Internship for independent film crew\n\n5. Student Government Committee Chair\n\n6. Admissions tour guide\n\n7. Freelance video editor\n\nAwards\n\n1. 1st Place Award in regional film festival\n\n2. Scholastic Art and Writing Bronze Award\n\n3. Top Scholar at school\n\n4. AP Scholar with Distinction\n\nAcceptances\n\n1. Loyola University Chicago\n\n2. Arizona State University\n\n3. Colorado State University\n\n4. UNIVERSITY OF RICHMOND",
    "structured_profile": {
      "demographics": {
        "gender": "Male",
        "race_ethnicity": "Asian",
        "residence": null,
        "income_bracket": "100k-200k",
        "type_of_school": "Private School",
        "hooks": null,
        "intended_majors": "Accounting"
      },
      "academics": {
        "gpa": {
          "unweighted": 3.8,
          "weighted": 4.2
        },
        "course_count": {
          "honors": null,
          "ap": 10,
          "ib": null,
          "dual_enrollment": null
        },
        "senior_year_course_load": null
      },
      "standardized_testing": {
        "sat_i": {
          "total": 1420,
          "reading_writing": null,
          "math": null
        },
        "act": null
      },
      "extracurriculars": [
        "Worked at a boba shop part-time",
        "JROTC cadet corporal",
        "3rd Grade Assistant Teacher for underrepresented minorities",
        "Internship for independent film crew",
        "Student Government Committee Chair",
        "Admissions tour guide",
        "Freelance video editor"
      ],
      "awards_honors": [
        "1st Place Award in regional film festival",
        "Scholastic Art and Writing Bronze Award",
        "Top Scholar at school",
        "AP Scholar with Distinction"
      ],
      "letters_of_recommendation": null,
      "essays": null,
      "decisions": {
        "acceptances": [
          {
            "university": "Loyola University Chicago",
            "decision_plan": "N/A"
          },
          {
            "university": "Arizona State University",
            "decision_plan": "N/A"
          },
          {
            "university": "Colorado State University",
            "decision_plan": "N/A"
          },
          {
            "university": "University of Richmond",
            "decision_plan": "N/A"
          }
        ],
        "waitlists": null,
        "rejections": null
      },
      "additional_information": null
    }
  },

  {
    "post_text": "Material Science Engineering Major ðŸŽ“\n\nDemographics\n\nWhite\nFemale\n50k-100k\nPublic School\nAcademics\n\n1440 SAT\n12 AP's\nExtracurriculars\n\n1. Technology competition/club (8 state awards\n\n2. 1 national award)\n\n3. FBLA (2 regional\n\n4. 1 state award)\n\n5. Club for suicide prevention (Treasurer)\n\n6. Model UN (Secretary\n\n7. President)\n\n8. Varsity Tennis (team captain)\n\n9. Social justice club (Secretary)\n\n10. Jazz band (section leader)\n\n11. Key club\n\n12. NHS and Tri-M\n\n13. Part-time job waitressing\n\nAwards\n\n1. State level awards in technology/business clubs\n\nAcceptances\n\n1. UDel\n\n2. Columbia Engineering",
    "structured_profile": {
      "demographics": {
        "gender": "Female",
        "race_ethnicity": "White",
        "residence": null,
        "income_bracket": "50k-100k",
        "type_of_school": "Public School",
        "hooks": null,
        "intended_majors": "Material Science Engineering"
      },
      "academics": {
        "gpa": null,
        "course_count": {
          "honors": null,
          "ap": 12,
          "ib": null,
          "dual_enrollment": null
        },
        "senior_year_course_load": null
      },
      "standardized_testing": {
        "sat_i": {
          "total": 1440,
          "reading_writing": null,
          "math": null
        },
        "act": null
      },
      "extracurriculars": [
        "Technology competition/club",
        "FBLA",
        "Club for suicide prevention (Treasurer)",
        "Model UN (Secretary, President)",
        "Varsity Tennis (team captain)",
        "Social justice club (Secretary)",
        "Jazz band (section leader)",
        "Key club",
        "NHS",
        "Tri-M",
        "Part-time job waitressing"
      ],
      "awards_honors": [
        "8 state awards (Technology competition/club)",
        "1 national award (Technology competition/club)",
        "2 regional awards (FBLA)",
        "1 state award (FBLA)",
        "State level awards in technology/business clubs"
      ],
      "letters_of_recommendation": null,
      "essays": null,
      "decisions": {
        "acceptances": [
          {
            "university": "UDel",
            "decision_plan": "N/A"
          },
          {
            "university": "Columbia Engineering",
            "decision_plan": "N/A"
          }
        ],
        "waitlists": null,
        "rejections": null
      },
      "additional_information": null
    }
  },

  {
    "post_text": "Accounting Major ðŸŽ“\n\nDemographics\n\nWhite\nMale\n200k+\nPublic School\nAcademics\n\n1480 SAT\n35 ACT\n6 AP's\n3.63 UW\n4.23 W\nExtracurriculars\n\n1. Playing my instrument\n\n2. President of music honor society\n\n3. Vice Pres. of speech and debate club\n\n4. Summer IT internship\n\n5. Volunteer SAT/ACT tutor\n\nAwards\n\n1. National merit commendation\n\n2. All-state orchestra participant\n\n3. All-county orchestra participant\n\n4. Superior rating @ FL solo & ensemble (2x)\n\n5. AP scholar w/ distinction\n\nAcceptances\n\n1. University of North Florida\n\n2. University of South Florida\n\n3. Florida State University",
    "structured_profile": {
      "demographics": {
        "gender": "Male",
        "race_ethnicity": "White",
        "residence": null,
        "income_bracket": "200k+",
        "type_of_school": "Public School",
        "hooks": null,
        "intended_majors": "Accounting"
      },
      "academics": {
        "gpa": {
          "unweighted": 3.63,
          "weighted": 4.23
        },
        "course_count": {
          "honors": null,
          "ap": 6,
          "ib": null,
          "dual_enrollment": null
        },
        "senior_year_course_load": null
      },
      "standardized_testing": {
        "sat_i": {
          "total": 1480,
          "reading_writing": null,
          "math": null
        },
        "act": 35
      },
      "extracurriculars": [
        "Playing my instrument",
        "President of music honor society",
        "Vice Pres. of speech and debate club",
        "Summer IT internship",
        "Volunteer SAT/ACT tutor"
      ],
      "awards_honors": [
        "National merit commendation",
        "All-state orchestra participant",
        "All-county orchestra participant",
        "Superior rating @ FL solo & ensemble (2x)",
        "AP scholar w/ distinction"
      ],
      "letters_of_recommendation": null,
      "essays": null,
      "decisions": {
        "acceptances": [
          {
            "university": "University of North Florida",
            "decision_plan": "N/A"
          },
          {
            "university": "University of South Florida",
            "decision_plan": "N/A"
          },
          {
            "university": "Florida State University",
            "decision_plan": "N/A"
          }
        ],
        "waitlists": null,
        "rejections": null
      },
      "additional_information": null
    }
  },

  {
    "post_text": "N/A Major ðŸŽ“\n\nDemographics\n\nWhite\nMale\n0-50k\nPublic School\nAcademics\n\n1190 SAT\n5 AP's\n2.79 UW\n2.99 W\nExtracurriculars\n\n1. Model UN\n\nAwards\n\n1. Sophomore Honors Society at school\n\nAcceptances\n\n1. Millikin University\n\n2. University of Illinois-Springfield\n\n3. Eastern Illinois University\n\n4. Creighton University\n\n5. Georgia Southern University\n\n6. University of Northern Iowa\n\n7. Western Kentucky University\n\n8. Wittenberg University\n\n9. Cal State San Marcos",
    "structured_profile": {
      "demographics": {
        "gender": "Male",
        "race_ethnicity": "White",
        "residence": null,
        "income_bracket": "0-50k",
        "type_of_school": "Public School",
        "hooks": null,
        "intended_majors": "N/A"
      },
      "academics": {
        "gpa": {
          "unweighted": 2.79,
          "weighted": 2.99
        },
        "course_count": {
          "honors": null,
          "ap": 5,
          "ib": null,
          "dual_enrollment": null
        },
        "senior_year_course_load": null
      },
      "standardized_testing": {
        "sat_i": {
          "total": 1190,
          "reading_writing": null,
          "math": null
        },
        "act": null
      },
      "extracurriculars": ["Model UN"],
      "awards_honors": ["Sophomore Honors Society at school"],
      "letters_of_recommendation": null,
      "essays": null,
      "decisions": {
        "acceptances": [
          {
            "university": "Millikin University",
            "decision_plan": "N/A"
          },
          {
            "university": "University of Illinois-Springfield",
            "decision_plan": "N/A"
          },
          {
            "university": "Eastern Illinois University",
            "decision_plan": "N/A"
          },
          {
            "university": "Creighton University",
            "decision_plan": "N/A"
          },
          {
            "university": "Georgia Southern University",
            "decision_plan": "N/A"
          },
          {
            "university": "University of Northern Iowa",
            "decision_plan": "N/A"
          },
          {
            "university": "Western Kentucky University",
            "decision_plan": "N/A"
          },
          {
            "university": "Wittenberg University",
            "decision_plan": "N/A"
          },
          {
            "university": "Cal State San Marcos",
            "decision_plan": "N/A"
          }
        ],
        "waitlists": null,
        "rejections": null
      },
      "additional_information": null
    }
  },

  {
    "post_text": "Political Science Major ðŸŽ“\n\nDemographics\n\nWhite\nMale\n50k-100k\nPrivate School\nAcademics\n\n1440 SAT\n9 AP's\n3.94 UW\nExtracurriculars\n\n1. Run/co-founded a scholarship nonprofit\n\n2. raised 100k+ since 2021\n\n3. Run/co-founded political non-profit that aids young candidates\n\n4. Serve as legislative director at youth-focused non-profit\n\n5. Co-Prez of schoolâ€™s investment club\n\n6. Worked at Jersey Mikes for two years\n\n7. Tour guide/ambassador for two years\n\n8. Debated for three years\n\n9. Play rugby varsity\n\n10. Served on Youth Advisory Council of US house member freshman and sophomore year\n\nAwards\n\n1. Presidential Service Award\n\n2. Governor volunteerism award\n\n3. AP Scholar with Honor\n\n4. 4 school level club awards\n\nAcceptances\n\n1. University of St Andrewâ€™s\n\n2. Catholic University",
    "structured_profile": {
      "demographics": {
        "gender": "Male",
        "race_ethnicity": "White",
        "residence": null,
        "income_bracket": "50k-100k",
        "type_of_school": "Private School",
        "hooks": null,
        "intended_majors": "Political Science"
      },
      "academics": {
        "gpa": {
          "unweighted": 3.94,
          "weighted": null
        },
        "course_count": {
          "honors": null,
          "ap": 9,
          "ib": null,
          "dual_enrollment": null
        },
        "senior_year_course_load": null
      },
      "standardized_testing": {
        "sat_i": {
          "total": 1440,
          "reading_writing": null,
          "math": null
        },
        "act": null
      },
      "extracurriculars": [
        "Run/co-founded a scholarship nonprofit",
        "raised 100k+ since 2021",
        "Run/co-founded political non-profit that aids young candidates",
        "Serve as legislative director at youth-focused non-profit",
        "Co-Prez of schoolâ€™s investment club",
        "Worked at Jersey Mikes for two years",
        "Tour guide/ambassador for two years",
        "Debated for three years",
        "Play rugby varsity",
        "Served on Youth Advisory Council of US house member freshman and sophomore year"
      ],
      "awards_honors": [
        "Presidential Service Award",
        "Governor volunteerism award",
        "AP Scholar with Honor",
        "4 school level club awards"
      ],
      "letters_of_recommendation": null,
      "essays": null,
      "decisions": {
        "acceptances": [
          {
            "university": "University of St Andrew's",
            "decision_plan": "N/A"
          },
          {
            "university": "Catholic University",
            "decision_plan": "N/A"
          }
        ],
        "waitlists": null,
        "rejections": null
      },
      "additional_information": null
    }
  },

  {
    "post_text": "Biology Major ðŸŽ“\n\nDemographics\n\nAsian\nMale\n200k+\nPrivate School\nAcademics\n\n1500 SAT\n7 AP's\n4 UW\n4.63 W\nExtracurriculars\n\n1. Neuroscience Research\n\n2. ISEF\n\n3. Taekwondo\n\n4. LLS campaign manager\n\n5. representative on schoolâ€™s community service committee\n\n6. teen ambassador at local hospital\n\n7. student leader at local temple\n\n8. football manager\n\n9. chemistry club\n\n10. ride operator\n\nAwards\n\n1. ISEF Finalist\n\n2. National Merit Semifinalist\n\n3. Princeton Book Award\n\n4. LLS Man/Woman of the Year\n\n5. 4th degree black belt recipient\n\nAcceptances\n\n1. Pitt\n\n2. Alabama\n\n3. Fordham\n\n4. Brown",
    "structured_profile": {
      "demographics": {
        "gender": "Male",
        "race_ethnicity": "Asian",
        "residence": null,
        "income_bracket": "200k+",
        "type_of_school": "Private School",
        "hooks": null,
        "intended_majors": "Biology"
      },
      "academics": {
        "gpa": {
          "unweighted": 4.0,
          "weighted": 4.63
        },
        "course_count": {
          "honors": null,
          "ap": 7,
          "ib": null,
          "dual_enrollment": null
        },
        "senior_year_course_load": null
      },
      "standardized_testing": {
        "sat_i": {
          "total": 1500,
          "reading_writing": null,
          "math": null
        },
        "act": null
      },
      "extracurriculars": [
        "Neuroscience Research",
        "ISEF",
        "Taekwondo",
        "LLS campaign manager",
        "representative on schoolâ€™s community service committee",
        "teen ambassador at local hospital",
        "student leader at local temple",
        "football manager",
        "chemistry club",
        "ride operator"
      ],
      "awards_honors": [
        "ISEF Finalist",
        "National Merit Semifinalist",
        "Princeton Book Award",
        "LLS Man/Woman of the Year",
        "4th degree black belt recipient"
      ],
      "letters_of_recommendation": null,
      "essays": null,
      "decisions": {
        "acceptances": [
          {
            "university": "Pitt",
            "decision_plan": "N/A"
          },
          {
            "university": "Alabama",
            "decision_plan": "N/A"
          },
          {
            "university": "Fordham",
            "decision_plan": "N/A"
          },
          {
            "university": "Brown",
            "decision_plan": "N/A"
          }
        ],
        "waitlists": null,
        "rejections": null
      },
      "additional_information": null
    }
  },

  {
    "post_text": "Political Economy Major ðŸŽ“\n\nDemographics\n\nAfrican American\nMale\n200k+\nPublic School\nAcademics\n\n1470 SAT\n10 AP's\n4 UW\n4.72 W\nExtracurriculars\n\n1. Mock Trial (president 12th)\n\n2. Politics Club (anticipated president 12)\n\n3. Book Club (co-founder 11th)\n\n4. Club Tennis\n\n5. Boys State\n\n6. Relay for Life Finance Board (Member 11th-12th)\n\n7. AP Macroeconomics Fed Challenge Team (11th Grade)\n\n8. Soup Kitchen (100 hours)\n\n9. Local soccer camp for children on the autistic spectrum (11th-12th)\n\n10. Job working at the summer camp where I grew up (10th-12th)\n\nAwards\n\n1. N/A\n\nAcceptances\n\n1. Georgetown",
    "structured_profile": {
      "demographics": {
        "gender": "Male",
        "race_ethnicity": "African American",
        "residence": null,
        "income_bracket": "200k+",
        "type_of_school": "Public School",
        "hooks": null,
        "intended_majors": "Political Economy"
      },
      "academics": {
        "gpa": {
          "unweighted": 4.0,
          "weighted": 4.72
        },
        "course_count": {
          "honors": null,
          "ap": 10,
          "ib": null,
          "dual_enrollment": null
        },
        "senior_year_course_load": null
      },
      "standardized_testing": {
        "sat_i": {
          "total": 1470,
          "reading_writing": null,
          "math": null
        },
        "act": null
      },
      "extracurriculars": [
        "Mock Trial (president 12th)",
        "Politics Club (anticipated president 12)",
        "Book Club (co-founder 11th)",
        "Club Tennis",
        "Boys State",
        "Relay for Life Finance Board (Member 11th-12th)",
        "AP Macroeconomics Fed Challenge Team (11th Grade)",
        "Soup Kitchen (100 hours)",
        "Local soccer camp for children on the autistic spectrum (11th-12th)",
        "Job working at the summer camp where I grew up (10th-12th)"
      ],
      "awards_honors": null,
      "letters_of_recommendation": null,
      "essays": null,
      "decisions": {
        "acceptances": [
          {
            "university": "Georgetown",
            "decision_plan": "N/A"
          }
        ],
        "waitlists": null,
        "rejections": null
      },
      "additional_information": null
    }
  },

  {
    "post_text": "Economics Major ðŸŽ“\n\nDemographics\n\nWhite\nMale\n100k-200k\nPublic School\nAcademics\n\n1520 SAT\n4 UW\n4 W\nExtracurriculars\n\n1. Competitive swimming 8yr\n\n2. model UN secretary + 10 simulations including international oneâ€™s\n\n3. internship political campaign of a national congressman\n\n4. internship with the CFO of a 2 billion dollars pharmaceutical company (during all gap year)\n\n5. founder of a organization that concedes diapers to the city shelters with partnership with the company that I work and with the biggest local soccer team\n\n6. 60 volunteer hours tutoring poor kids (11th and 12th year)\n\n7. Founder and Co-Owner of a supplements stores with 10.000 BRL in sales\n\n8. Actor and Co-Director of school musical\n\n9. content creator in TikTok with 20.000 viewers about 2022 Brazilian election\n\nAwards\n\n1. 109 swimming titles (including 12 international)\n\n2. 6 All state team\n\n3. 3x honorable mention National Science Olympics\n\n4. finalist national investment Olympics\n\nAcceptances\n\n1. Dartmouth",
    "structured_profile": {
      "demographics": {
        "gender": "Male",
        "race_ethnicity": "White",
        "residence": null,
        "income_bracket": "100k-200k",
        "type_of_school": "Public School",
        "hooks": null,
        "intended_majors": "Economics"
      },
      "academics": {
        "gpa": {
          "unweighted": 4.0,
          "weighted": 4.0
        },
        "course_count": null,
        "senior_year_course_load": null
      },
      "standardized_testing": {
        "sat_i": {
          "total": 1520,
          "reading_writing": null,
          "math": null
        },
        "act": null
      },
      "extracurriculars": [
        "Competitive swimming 8yr",
        "model UN secretary + 10 simulations including international oneâ€™s",
        "internship political campaign of a national congressman",
        "internship with the CFO of a 2 billion dollars pharmaceutical company (during all gap year)",
        "founder of a organization that concedes diapers to the city shelters with partnership with the company that I work and with the biggest local soccer team",
        "60 volunteer hours tutoring poor kids (11th and 12th year)",
        "Founder and Co-Owner of a supplements stores with 10.000 BRL in sales",
        "Actor and Co-Director of school musical",
        "content creator in TikTok with 20.000 viewers about 2022 Brazilian election"
      ],
      "awards_honors": [
        "109 swimming titles (including 12 international)",
        "6 All state team",
        "3x honorable mention National Science Olympics",
        "finalist national investment Olympics"
      ],
      "letters_of_recommendation": null,
      "essays": null,
      "decisions": {
        "acceptances": [
          {
            "university": "Dartmouth",
            "decision_plan": "N/A"
          }
        ],
        "waitlists": null,
        "rejections": null
      },
      "additional_information": null
    }
  },

  {
    "post_text": "Earth Science Major ðŸŽ“\n\nDemographics\n\nAsian\nMale\n200k+\nPublic School\nAcademics\n\n35 ACT\n5 AP's\n3.95 UW\nExtracurriculars\n\n1. Created an org using blacksmithing hobby to build furniture for impoverished families\n\n2. Environmental Lobbyist\n\n3. Wildfire Earth Systems Research\n\n4. President of org providing free music education\n\n5. Selective Summer Research Program @ NASA\n\n6. Oboe player\n\nAwards\n\n1. Presented at Research Conference\n\n2. National medals for scioly\n\n3. State 1st National History Day\n\n4. ABC7 news segment on EC\n\n5. All State Orchestra Musician\n\nAcceptances\n\n1. Yale",
    "structured_profile": {
      "demographics": {
        "gender": "Male",
        "race_ethnicity": "Asian",
        "residence": null,
        "income_bracket": "200k+",
        "type_of_school": "Public School",
        "hooks": null,
        "intended_majors": "Earth Science"
      },
      "academics": {
        "gpa": {
          "unweighted": 3.95,
          "weighted": null
        },
        "course_count": {
          "honors": null,
          "ap": 5,
          "ib": null,
          "dual_enrollment": null
        },
        "senior_year_course_load": null
      },
      "standardized_testing": {
        "sat_i": null,
        "act": 35
      },
      "extracurriculars": [
        "Created an org using blacksmithing hobby to build furniture for impoverished families",
        "Environmental Lobbyist",
        "Wildfire Earth Systems Research",
        "President of org providing free music education",
        "Selective Summer Research Program @ NASA",
        "Oboe player"
      ],
      "awards_honors": [
        "Presented at Research Conference",
        "National medals for scioly",
        "State 1st National History Day",
        "ABC7 news segment on EC",
        "All State Orchestra Musician"
      ],
      "letters_of_recommendation": null,
      "essays": null,
      "decisions": {
        "acceptances": [
          {
            "university": "Yale",
            "decision_plan": "N/A"
          }
        ],
        "waitlists": null,
        "rejections": null
      },
      "additional_information": null
    }
  },

  {
    "post_text": "Biology Major ðŸŽ“\n\nDemographics\n\nOther\nMale\n100k-200k\nPublic School\nAcademics\n\n1560 SAT\n35 ACT\n8 AP's\n4 UW\n4 W\nExtracurriculars\n\n1. FTC (9\n\n2. 10) Worlds Qualifier both years\n\n3. FRC (11\n\n4. 12) Worlds Qualifer 2023\n\n5. Violin (9\n\n6. 10\n\n7. 11\n\n8. 12) 14 years\n\n9. Competitons + Money\n\n10. State Orchestra (9\n\n11. 10\n\n12. 11\n\n13. 12) Auditioned and performed for PBS in selective state orchestra\n\n14. Piano (9\n\n15. 10\n\n16. 11\n\n17. 12) 14 years\n\n18. Competitons\n\n19. DECA (10) Leadership Team\n\n20. ICDC qualifier\n\n21. School Newspaper (10\n\n22. 11\n\n23. 12) Editor\n\n24. Key Club (9\n\n25. 10\n\n26. 11\n\n27. 12) Recognized by state down syndrome association for volunteering efforts\n\n28. NJCL (10\n\n29. 11\n\n30. 12) State and National Competitor and Placed top 3 at national events\n\n31. Language (9\n\n32. 10\n\n33. 11\n\n34. 12) Latin\n\n35. Greek\n\n36. German\n\n37. Korean\n\nAwards\n\n1. National Latin Exam 3x Gold Medal\n\n2. 1x Perfect Score\n\n3. National Greek Exam Highest Honor\n\n4. National Junior Classical League 1st Place Creative Arts\n\n5. State Violin Competiton winner (300+ in prize money)\n\n6. NMSQT semifinalist\n\nAcceptances\n\n1. Harvard",
    "structured_profile": {
      "demographics": {
        "gender": "Male",
        "race_ethnicity": null,
        "residence": null,
        "income_bracket": "100k-200k",
        "type_of_school": "Public School",
        "hooks": null,
        "intended_majors": "Biology"
      },
      "academics": {
        "gpa": {
          "unweighted": 4.0,
          "weighted": 4.0
        },
        "course_count": {
          "honors": null,
          "ap": 8,
          "ib": null,
          "dual_enrollment": null
        },
        "senior_year_course_load": null
      },
      "standardized_testing": {
        "sat_i": {
          "total": 1560,
          "reading_writing": null,
          "math": null
        },
        "act": 35
      },
      "extracurriculars": [
        "FTC (9-10) Worlds Qualifier both years",
        "FRC (11-12) Worlds Qualifer 2023",
        "Violin (9-12) 14 years, Competitions + Money",
        "State Orchestra (9-12) Auditioned and performed for PBS in selective state orchestra",
        "Piano (9-12) 14 years, Competitions",
        "DECA (10) Leadership Team, ICDC qualifier",
        "School Newspaper (10-12) Editor",
        "Key Club (9-12) Recognized by state down syndrome association for volunteering efforts",
        "NJCL (10-12) State and National Competitor and Placed top 3 at national events",
        "Language (9-12) Latin, Greek, German, Korean"
      ],
      "awards_honors": [
        "National Latin Exam 3x Gold Medal, 1x Perfect Score",
        "National Greek Exam Highest Honor",
        "National Junior Classical League 1st Place Creative Arts",
        "State Violin Competiton winner (300+ in prize money)",
        "NMSQT semifinalist"
      ],
      "letters_of_recommendation": null,
      "essays": null,
      "decisions": {
        "acceptances": [
          {
            "university": "Harvard",
            "decision_plan": "N/A"
          }
        ],
        "waitlists": null,
        "rejections": null
      },
      "additional_information": null
    }
  },

  {
    "post_text": "Chemistry Major ðŸŽ“\n\nDemographics\n\nAsian\nNon-Binary\n0-50k\nPublic School\nAcademics\n\n36 ACT\n14 AP's\n3.972 UW\n4.528 W\nExtracurriculars\n\n1. Project assistant for public health project focused on COVID-19 and AAPI health\n\n2. Lab assistant at molecular neurobiology lab\n\n3. Co-president and founder of school's GSA\n\n4. President of a social outreach club\n\n5. Selective science summer program\n\n6. Volunteer at a local ranch\n\n7. Volunteer as an online tutor\n\n8. Treasurer turned president of APUSH club\n\n9. Member of Science Olympiad\n\n10. Member of Creative Writing Club\n\nAwards\n\n1. USNCO National Qualifier\n\n2. National Merit Semifinalist\n\n3. AP Scholar with Distinction\n\nAcceptances\n\n1. Rice University\n\n2. Barrett ASU",
    "structured_profile": {
      "demographics": {
        "gender": "Non-Binary",
        "race_ethnicity": "Asian",
        "residence": null,
        "income_bracket": "0-50k",
        "type_of_school": "Public School",
        "hooks": null,
        "intended_majors": "Chemistry"
      },
      "academics": {
        "gpa": {
          "unweighted": 3.972,
          "weighted": 4.528
        },
        "course_count": {
          "honors": null,
          "ap": 14,
          "ib": null,
          "dual_enrollment": null
        },
        "senior_year_course_load": null
      },
      "standardized_testing": {
        "sat_i": null,
        "act": 36
      },
      "extracurriculars": [
        "Project assistant for public health project focused on COVID-19 and AAPI health",
        "Lab assistant at molecular neurobiology lab",
        "Co-president and founder of school's GSA",
        "President of a social outreach club",
        "Selective science summer program",
        "Volunteer at a local ranch",
        "Volunteer as an online tutor",
        "Treasurer turned president of APUSH club",
        "Member of Science Olympiad",
        "Member of Creative Writing Club"
      ],
      "awards_honors": [
        "USNCO National Qualifier",
        "National Merit Semifinalist",
        "AP Scholar with Distinction"
      ],
      "letters_of_recommendation": null,
      "essays": null,
      "decisions": {
        "acceptances": [
          {
            "university": "Rice University",
            "decision_plan": "N/A"
          },
          {
            "university": "Barrett ASU",
            "decision_plan": "N/A"
          }
        ],
        "waitlists": null,
        "rejections": null
      },
      "additional_information": null
    }
  },

  {
    "post_text": "Symbolic Systems Major ðŸŽ“\n\nDemographics\n\nHispanic\nFemale\n0-50k\nPublic School\nAcademics\n\n1480 SAT\n0.352 UW\nExtracurriculars\n\n1. Co-founder of a women's clothing business\n\n2. Creator and developer of a mobile app addressing domestic violence\n\n3. Co-founder of a math-teaching NGO to low-income youth\n\n4. Co-Founder of a math-teaching NGO to low-income youth\n\n5. PROMYS\n\n6. Research in the most prominent math institute in my country\n\n7. Polyglot\n\n8. self-study foreign languages\n\nAwards\n\n1. Top 1 worldwide in the largest techpreneur comp worldwide\n\n2. RISE Finalist 2023\n\n3. Recognized as a young changemaker by the largest e-commerce in global south\n\n4. Intl award for being an avid entrepreneur\n\n5. EGMO qualifier\n\nAcceptances\n\n1. Stanford",
    "structured_profile": {
      "demographics": {
        "gender": "Female",
        "race_ethnicity": "Hispanic",
        "residence": null,
        "income_bracket": "0-50k",
        "type_of_school": "Public School",
        "hooks": null,
        "intended_majors": "Symbolic Systems"
      },
      "academics": {
        "gpa": {
          "unweighted": 3.52,
          "weighted": null
        },
        "course_count": null,
        "senior_year_course_load": null
      },
      "standardized_testing": {
        "sat_i": {
          "total": 1480,
          "reading_writing": null,
          "math": null
        },
        "act": null
      },
      "extracurriculars": [
        "Co-founder of a women's clothing business",
        "Creator and developer of a mobile app addressing domestic violence",
        "Co-founder of a math-teaching NGO to low-income youth",
        "Co-Founder of a math-teaching NGO to low-income youth",
        "PROMYS",
        "Research in the most prominent math institute in my country",
        "Polyglot",
        "self-study foreign languages"
      ],
      "awards_honors": [
        "Top 1 worldwide in the largest techpreneur comp worldwide",
        "RISE Finalist 2023",
        "Recognized as a young changemaker by the largest e-commerce in global south",
        "Intl award for being an avid entrepreneur",
        "EGMO qualifier"
      ],
      "letters_of_recommendation": null,
      "essays": null,
      "decisions": {
        "acceptances": [
          {
            "university": "Stanford",
            "decision_plan": "N/A"
          }
        ],
        "waitlists": null,
        "rejections": null
      },
      "additional_information": null
    }
  },

  {
    "post_text": "Political Science Major ðŸŽ“\n\nDemographics\n\nWhite\nMale\n50k-100k\nPublic School\nAcademics\n\n1250 SAT\n7 AP's\n3.26 UW\n3.53 W\nExtracurriculars\n\n1. Captain of the debate team\n\n2. Editor of school paper\n\n3. Student council\n\n4. Internship\n\nAwards\n\n1. State debate title\n\n2. High placement at nationals for debate\n\nAcceptances\n\n1. Clark\n\n2. Fordham\n\n3. Abeline Christian University\n\n4. Wells College\n\n5. University of San Francisco\n\n6. U of O",
    "structured_profile": {
      "demographics": {
        "gender": "Male",
        "race_ethnicity": "White",
        "residence": null,
        "income_bracket": "50k-100k",
        "type_of_school": "Public School",
        "hooks": null,
        "intended_majors": "Political Science"
      },
      "academics": {
        "gpa": {
          "unweighted": 3.26,
          "weighted": 3.53
        },
        "course_count": {
          "honors": null,
          "ap": 7,
          "ib": null,
          "dual_enrollment": null
        },
        "senior_year_course_load": null
      },
      "standardized_testing": {
        "sat_i": {
          "total": 1250,
          "reading_writing": null,
          "math": null
        },
        "act": null
      },
      "extracurriculars": [
        "Captain of the debate team",
        "Editor of school paper",
        "Student council",
        "Internship"
      ],
      "awards_honors": [
        "State debate title",
        "High placement at nationals for debate"
      ],
      "letters_of_recommendation": null,
      "essays": null,
      "decisions": {
        "acceptances": [
          {
            "university": "Clark",
            "decision_plan": "N/A"
          },
          {
            "university": "Fordham",
            "decision_plan": "N/A"
          },
          {
            "university": "Abeline Christian University",
            "decision_plan": "N/A"
          },
          {
            "university": "Wells College",
            "decision_plan": "N/A"
          },
          {
            "university": "University of San Francisco",
            "decision_plan": "N/A"
          },
          {
            "university": "U of O",
            "decision_plan": "N/A"
          }
        ],
        "waitlists": null,
        "rejections": null
      },
      "additional_information": null
    }
  },

  {
    "post_text": "Data Science Major ðŸŽ“\n\nDemographics\n\nWhite\nMale\n50k-100k\nPublic School\nAcademics\n\n1560 SAT\n10 AP's\n4 UW\n5.379 W\nExtracurriculars\n\n1. Marching Band\n\n2. Drum Major\n\n3. All-Region Band Euphonium\n\n4. All-County Band\n\n5. Beta Club\n\n6. Student Council Representative\n\n7. Spanish Honor Society\n\n8. Science National Honor Society/Science Club\n\n9. National English Honor Society\n\nAwards\n\n1. All Region Band x3\n\n2. All County Band 1st chair x2\n\n3. National Merit Semifinalist\n\n4. Social Studies Department Award\n\n5. Rho Kappa\n\n6. African American Recognition Award\n\nAcceptances\n\n1. Duke University",
    "structured_profile": {
      "demographics": {
        "gender": "Male",
        "race_ethnicity": "White",
        "residence": null,
        "income_bracket": "50k-100k",
        "type_of_school": "Public School",
        "hooks": null,
        "intended_majors": "Data Science"
      },
      "academics": {
        "gpa": {
          "unweighted": 4.0,
          "weighted": 5.379
        },
        "course_count": {
          "honors": null,
          "ap": 10,
          "ib": null,
          "dual_enrollment": null
        },
        "senior_year_course_load": null
      },
      "standardized_testing": {
        "sat_i": {
          "total": 1560,
          "reading_writing": null,
          "math": null
        },
        "act": null
      },
      "extracurriculars": [
        "Marching Band",
        "Drum Major",
        "All-Region Band Euphonium",
        "All-County Band",
        "Beta Club",
        "Student Council Representative",
        "Spanish Honor Society",
        "Science National Honor Society/Science Club",
        "National English Honor Society"
      ],
      "awards_honors": [
        "All Region Band x3",
        "All County Band 1st chair x2",
        "National Merit Semifinalist",
        "Social Studies Department Award",
        "Rho Kappa",
        "African American Recognition Award"
      ],
      "letters_of_recommendation": null,
      "essays": null,
      "decisions": {
        "acceptances": [
          {
            "university": "Duke University",
            "decision_plan": "N/A"
          }
        ],
        "waitlists": null,
        "rejections": null
      },
      "additional_information": null
    }
  },

  {
    "post_text": "Neuroscience Major ðŸŽ“\n\nDemographics\n\nWhite\nFemale\n200k+\nPublic School\nAcademics\n\n34 ACT\n14 AP's\n3.82 UW\n4.35 W\nExtracurriculars\n\n1. Varsity Rowing\n\n2. Varsity Coxswain (15hrs/45wks)\n\n3. Independent Research (11)\n\n4. Student Leadership Task Force Member (12)\n\n5. Student Leader Volunteer (9-10)\n\n6. Volunteer Coach (10)\n\n7. National Youth Leadership Forum in Advanced Medicine (40hrs/2wks) (12)\n\n8. Speech and Debate (9\n\n9. 12)\n\n10. Piano (9-10\n\n11. 12)\n\nAwards\n\n1. AP Scholar with Distinction\n\n2. AP Capstone Diploma\n\n3. California Scholarship Federation Lifetime Member\n\n4. CPR/BLS Certification\n\nAcceptances\n\n1. Emory University",
    "structured_profile": {
      "demographics": {
        "gender": "Female",
        "race_ethnicity": "White",
        "residence": null,
        "income_bracket": "200k+",
        "type_of_school": "Public School",
        "hooks": null,
        "intended_majors": "Neuroscience"
      },
      "academics": {
        "gpa": {
          "unweighted": 3.82,
          "weighted": 4.35
        },
        "course_count": {
          "honors": null,
          "ap": 14,
          "ib": null,
          "dual_enrollment": null
        },
        "senior_year_course_load": null
      },
      "standardized_testing": {
        "sat_i": null,
        "act": 34
      },
      "extracurriculars": [
        "Varsity Rowing",
        "Varsity Coxswain",
        "Independent Research",
        "Student Leadership Task Force Member",
        "Student Leader Volunteer",
        "Volunteer Coach",
        "National Youth Leadership Forum in Advanced Medicine",
        "Speech and Debate",
        "Piano"
      ],
      "awards_honors": [
        "AP Scholar with Distinction",
        "AP Capstone Diploma",
        "California Scholarship Federation Lifetime Member",
        "CPR/BLS Certification"
      ],
      "letters_of_recommendation": null,
      "essays": null,
      "decisions": {
        "acceptances": [
          {
            "university": "Emory University",
            "decision_plan": "N/A"
          }
        ],
        "waitlists": null,
        "rejections": null
      },
      "additional_information": null
    }
  },

  {
    "post_text": "Biology Major ðŸŽ“\n\nDemographics\n\nAsian\nFemale\n200k+\nPublic School\nAcademics\n\n32 ACT\n9 AP's\n3.8 UW\n4.4 W\nExtracurriculars\n\n1. JV Basketball\n\n2. Concert Band (1st chair\n\n3. section leader)\n\n4. Marching Band\n\n5. Jazz Band (2nd chair)\n\n6. Wind Ensemble (skipped symphonic band\n\n7. 3rd chair)\n\n8. Marching Band\n\n9. Jazz Band (1st chair\n\n10. section leader)\n\n11. Wind Ensemble (2nd chair)\n\n12. Jazz Band (1st chair\n\n13. section leader)\n\n14. National Honor Society\n\n15. Started working a minimum wage job\n\nAwards\n\n1. Concert Band - Freshman of the Year\n\n2. Brass Player of the Year\n\n3. Marching Band - Freshman of the Year\n\n4. Jazz Band - Freshman of the Year\n\n5. Marching Band - Sophomore of the Year\n\n6. Jazz Band - Sophomore of the Year\n\nAcceptances\n\n1. UCSD\n\n2. UCSB\n\n3. UCI\n\n4. UCD\n\n5. Cal Poly SLO\n\n6. UIUC",
    "structured_profile": {
      "demographics": {
        "gender": "Female",
        "race_ethnicity": "Asian",
        "residence": null,
        "income_bracket": "200k+",
        "type_of_school": "Public School",
        "hooks": null,
        "intended_majors": "Biology"
      },
      "academics": {
        "gpa": {
          "unweighted": 3.8,
          "weighted": 4.4
        },
        "course_count": {
          "honors": null,
          "ap": 9,
          "ib": null,
          "dual_enrollment": null
        },
        "senior_year_course_load": null
      },
      "standardized_testing": {
        "sat_i": null,
        "act": 32
      },
      "extracurriculars": [
        "JV Basketball",
        "Concert Band (1st chair, section leader)",
        "Marching Band",
        "Jazz Band (1st chair, section leader)",
        "Wind Ensemble (skipped symphonic band, 2nd chair)",
        "National Honor Society",
        "Minimum wage job"
      ],
      "awards_honors": [
        "Concert Band - Freshman of the Year",
        "Brass Player of the Year",
        "Marching Band - Freshman of the Year",
        "Jazz Band - Freshman of the Year",
        "Marching Band - Sophomore of the Year",
        "Jazz Band - Sophomore of the Year"
      ],
      "letters_of_recommendation": null,
      "essays": null,
      "decisions": {
        "acceptances": [
          {
            "university": "UCSD",
            "decision_plan": "N/A"
          },
          {
            "university": "UCSB",
            "decision_plan": "N/A"
          },
          {
            "university": "UCI",
            "decision_plan": "N/A"
          },
          {
            "university": "UCD",
            "decision_plan": "N/A"
          },
          {
            "university": "Cal Poly SLO",
            "decision_plan": "N/A"
          },
          {
            "university": "UIUC",
            "decision_plan": "N/A"
          }
        ],
        "waitlists": null,
        "rejections": null
      },
      "additional_information": null
    }
  },

  {
    "post_text": "Political Science Major ðŸŽ“\n\nDemographics\n\nWhite\nFemale\n0-50k\nPublic School\nAcademics\n\n34 ACT\n8 AP's\n3.58 UW\n4.1 W\nExtracurriculars\n\n1. Varsity Cross Country (team captain)\n\n2. Varsity Track\n\n3. NHS\n\n4. a couple other clubs\n\nAwards\n\n1. National Merit commended\n\nAcceptances\n\n1. Santa Clara University",
    "structured_profile": {
      "demographics": {
        "gender": "Female",
        "race_ethnicity": "White",
        "residence": null,
        "income_bracket": "0-50k",
        "type_of_school": "Public School",
        "hooks": null,
        "intended_majors": "Political Science"
      },
      "academics": {
        "gpa": {
          "unweighted": 3.58,
          "weighted": 4.1
        },
        "course_count": {
          "honors": null,
          "ap": 8,
          "ib": null,
          "dual_enrollment": null
        },
        "senior_year_course_load": null
      },
      "standardized_testing": {
        "sat_i": null,
        "act": 34
      },
      "extracurriculars": [
        "Varsity Cross Country (team captain)",
        "Varsity Track",
        "NHS",
        "a couple other clubs"
      ],
      "awards_honors": ["National Merit commended"],
      "letters_of_recommendation": null,
      "essays": null,
      "decisions": {
        "acceptances": [
          {
            "university": "Santa Clara University",
            "decision_plan": "N/A"
          }
        ],
        "waitlists": null,
        "rejections": null
      },
      "additional_information": null
    }
  },

  {
    "post_text": "Astrophysics Major ðŸŽ“\n\nDemographics\n\nAsian\nMale\n100k-200k\nPublic School\nAcademics\n\n1570 SAT\n7 AP's\n3.9304 UW\n4.1608 W\nExtracurriculars\n\n1. Student Researcher @ Columbia\n\n2. Vice President\n\n3. Science/quiz bowl club\n\n4. Science Olympiad varsity team member\n\n5. President\n\n6. Computer Science Club\n\n7. Trombone Section Leader in wind ensemble and marching band\n\n8. Student researcher at summer research program at local university\n\n9. Student researcher at math research program\n\n10. Student researcher for science research program at school\n\n11. Coding instructor for online CS class\n\n12. Teaching assistant for local Chinese school\n\nAwards\n\n1. Science Olympiad National (2nd)\n\n2. NY State Tournament (1st)\n\n3. Regional (1st) in Astronomy\n\n4. Science Bowl Regional Winner and National Qualifier\n\n5. National Quiz Bowl Qualifier\n\n6. Toshiba ExploraVision Honorable Mention Paper (top ~100 nationally)\n\n7. USA Computing Olympiad - Silver Division\n\n8. Perfect score on AP CS Principles Exam\n\n9. National Merit Semifinalist\n\n10. AP Scholar w/ Distinction\n\nAcceptances\n\n1. Columbia University",
    "structured_profile": {
      "demographics": {
        "gender": "Male",
        "race_ethnicity": "Asian",
        "residence": null,
        "income_bracket": "100k-200k",
        "type_of_school": "Public School",
        "hooks": null,
        "intended_majors": "Astrophysics"
      },
      "academics": {
        "gpa": {
          "unweighted": 3.9304,
          "weighted": 4.1608
        },
        "course_count": {
          "honors": null,
          "ap": 7,
          "ib": null,
          "dual_enrollment": null
        },
        "senior_year_course_load": null
      },
      "standardized_testing": {
        "sat_i": {
          "total": 1570,
          "reading_writing": null,
          "math": null
        },
        "act": null
      },
      "extracurriculars": [
        "Student Researcher @ Columbia",
        "Vice President",
        "Science/quiz bowl club",
        "Science Olympiad varsity team member",
        "President",
        "Computer Science Club",
        "Trombone Section Leader in wind ensemble and marching band",
        "Student researcher at summer research program at local university",
        "Student researcher at math research program",
        "Student researcher for science research program at school",
        "Coding instructor for online CS class",
        "Teaching assistant for local Chinese school"
      ],
      "awards_honors": [
        "Science Olympiad National (2nd)",
        "NY State Tournament (1st)",
        "Regional (1st) in Astronomy",
        "Science Bowl Regional Winner and National Qualifier",
        "National Quiz Bowl Qualifier",
        "Toshiba ExploraVision Honorable Mention Paper (top ~100 nationally)",
        "USA Computing Olympiad - Silver Division",
        "Perfect score on AP CS Principles Exam",
        "National Merit Semifinalist",
        "AP Scholar w/ Distinction"
      ],
      "letters_of_recommendation": null,
      "essays": null,
      "decisions": {
        "acceptances": [
          {
            "university": "Columbia University",
            "decision_plan": "N/A"
          }
        ],
        "waitlists": null,
        "rejections": null
      },
      "additional_information": null
    }
  },

  {
    "post_text": "Psychology Major ðŸŽ“\n\nDemographics\n\nAsian\nMale\n0-50k\nPublic School\nAcademics\n\n1590 SAT\n11 AP's\n3.95 UW\n4.23 W\nExtracurriculars\n\n1. Family Responsibilities\n\n2. Social Justice\n\n3. Mental Health Business for Teens\n\n4. School Tutoring Program\n\n5. Marin Food Bank Volunteer\n\n6. New York Supermarket Cashier\n\n7. Nail Salon Cashier and Receptionist\n\n8. Symphonic Band\n\n9. ABRSM Clarinet Grade 8 Merit\n\n10. National Merit Commended\n\n11. Presidential Volunteer Service Award Gold\n\nAwards\n\n1. N/A\n\nAcceptances\n\n1. Brown University",
    "structured_profile": {
      "demographics": {
        "gender": "Male",
        "race_ethnicity": "Asian",
        "residence": null,
        "income_bracket": "0-50k",
        "type_of_school": "Public School",
        "hooks": null,
        "intended_majors": "Psychology"
      },
      "academics": {
        "gpa": {
          "unweighted": 3.95,
          "weighted": 4.23
        },
        "course_count": {
          "honors": null,
          "ap": 11,
          "ib": null,
          "dual_enrollment": null
        },
        "senior_year_course_load": null
      },
      "standardized_testing": {
        "sat_i": {
          "total": 1590,
          "reading_writing": null,
          "math": null
        },
        "act": null
      },
      "extracurriculars": [
        "Family Responsibilities",
        "Social Justice",
        "Mental Health Business for Teens",
        "School Tutoring Program",
        "Marin Food Bank Volunteer",
        "New York Supermarket Cashier",
        "Nail Salon Cashier and Receptionist",
        "Symphonic Band"
      ],
      "awards_honors": [
        "National Merit Commended",
        "Presidential Volunteer Service Award Gold",
        "ABRSM Clarinet Grade 8 Merit"
      ],
      "letters_of_recommendation": null,
      "essays": null,
      "decisions": {
        "acceptances": [
          {
            "university": "Brown University",
            "decision_plan": "N/A"
          }
        ],
        "waitlists": null,
        "rejections": null
      },
      "additional_information": null
    }
  },

  {
    "post_text": "Economics Major ðŸŽ“\n\nDemographics\n\nWhite\nMale\n0-50k\nPublic School\nAcademics\n\n1440 SAT\n10 AP's\n3.8 UW\n4.76 W\nExtracurriculars\n\n1. Secured an internship at BlueSky Financial Investments\n\n2. SwiftShopper\n\n3. Varsity Golf\n\n4. JV Golf\n\n5. Mammoth Mountain Ski Team\n\n6. Investment Club\n\n7. SAT Tutor\n\n8. President Food Bank Club\n\n9. Wharton Investment Competition\n\nAwards\n\n1. N/A\n\nAcceptances\n\n1. Brown",
    "structured_profile": {
      "demographics": {
        "gender": "Male",
        "race_ethnicity": "White",
        "residence": null,
        "income_bracket": "0-50k",
        "type_of_school": "Public School",
        "hooks": null,
        "intended_majors": "Economics"
      },
      "academics": {
        "gpa": {
          "unweighted": 3.8,
          "weighted": 4.76
        },
        "course_count": {
          "honors": null,
          "ap": 10,
          "ib": null,
          "dual_enrollment": null
        },
        "senior_year_course_load": null
      },
      "standardized_testing": {
        "sat_i": {
          "total": 1440,
          "reading_writing": null,
          "math": null
        },
        "act": null
      },
      "extracurriculars": [
        "Secured an internship at BlueSky Financial Investments",
        "SwiftShopper",
        "Varsity Golf",
        "JV Golf",
        "Mammoth Mountain Ski Team",
        "Investment Club",
        "SAT Tutor",
        "President Food Bank Club",
        "Wharton Investment Competition"
      ],
      "awards_honors": [],
      "letters_of_recommendation": null,
      "essays": null,
      "decisions": {
        "acceptances": [
          {
            "university": "Brown",
            "decision_plan": "N/A"
          }
        ],
        "waitlists": null,
        "rejections": null
      },
      "additional_information": null
    }
  },

  {
    "post_text": "Psychology Major ðŸŽ“\n\nDemographics\n\nAfrican American\nMale\n0-50k\nPublic School\nAcademics\n\n33 ACT\n20 AP's\n4 UW\n4.38 W\nExtracurriculars\n\n1. President\n\n2. Gender Sexuality Association\n\n3. Secondary Secretary\n\n4. HOSA - Future Health Professionals\n\n5. Laboratory Intern (Biotechnology)\n\n6. State President\n\n7. Tutoring Nonprofit\n\n8. National Academic Quiz Tournaments (Scholar's Bowl/Academic Team)\n\n9. Professorâ€™s Aid & Participant\n\n10. STEM/Healthcare Educational Programs\n\n11. Associate\n\n12. Walmart\n\n13. High School Student Ambassador\n\n14. Member\n\n15. Senior Beta Club\n\nAwards\n\n1. Top 3 at HOSA Competition\n\n2. Questbridge College Prep Scholar + National College Match Finalist\n\n3. National African American + Rural & Small Town Recognition Scholar\n\n4. Top 10% of Graduating Class\n\n5. Basic Life Support Certified\n\nAcceptances\n\n1. Harvard University",
    "structured_profile": {
      "demographics": {
        "gender": "Male",
        "race_ethnicity": "African American",
        "residence": null,
        "income_bracket": "0-50k",
        "type_of_school": "Public School",
        "hooks": null,
        "intended_majors": "Psychology"
      },
      "academics": {
        "gpa": {
          "unweighted": 4.0,
          "weighted": 4.38
        },
        "course_count": {
          "honors": null,
          "ap": 20,
          "ib": null,
          "dual_enrollment": null
        },
        "senior_year_course_load": null
      },
      "standardized_testing": {
        "sat_i": null,
        "act": 33
      },
      "extracurriculars": [
        "President",
        "Gender Sexuality Association",
        "Secondary Secretary",
        "HOSA - Future Health Professionals",
        "Laboratory Intern (Biotechnology)",
        "State President",
        "Tutoring Nonprofit",
        "National Academic Quiz Tournaments (Scholar's Bowl/Academic Team)",
        "Professorâ€™s Aid & Participant",
        "STEM/Healthcare Educational Programs",
        "Associate",
        "Walmart",
        "High School Student Ambassador",
        "Member",
        "Senior Beta Club"
      ],
      "awards_honors": [
        "Top 3 at HOSA Competition",
        "Questbridge College Prep Scholar + National College Match Finalist",
        "National African American + Rural & Small Town Recognition Scholar",
        "Top 10% of Graduating Class",
        "Basic Life Support Certified"
      ],
      "letters_of_recommendation": null,
      "essays": null,
      "decisions": {
        "acceptances": [
          {
            "university": "Harvard University",
            "decision_plan": "N/A"
          }
        ],
        "waitlists": null,
        "rejections": null
      },
      "additional_information": null
    }
  },

  {
    "post_text": "Biology Major ðŸŽ“\n\nDemographics\n\nAsian\nFemale\n0-50k\nPublic School\nAcademics\n\n1470 SAT\n12 AP's\n3.98 UW\n4.57 W\nExtracurriculars\n\n1. FFA - Trained Nationals team for competitive CDE\n\n2. Student Council: Senior Class Officer\n\n3. Volunteering Achievement\n\n4. Choir\n\n5. Internship at vet clinic\n\n6. Scrapbooking\n\n7. School Student Ambassador\n\n8. National Art Honor Society\n\n9. National Honor Society\n\nAwards\n\n1. QuestBridge National College Match Finalist\n\n2. Top 10 individual at Nationals FFA\n\n3. 1st Place team at State in FFA\n\n4. 2nd Individual & Top 5 team in FFA\n\n5. Junior of the Year in FFA\n\nAcceptances\n\n1. Cornell CALS",
    "structured_profile": {
      "demographics": {
        "gender": "Female",
        "race_ethnicity": "Asian",
        "residence": null,
        "income_bracket": "0-50k",
        "type_of_school": "Public School",
        "hooks": ["QuestBridge National College Match Finalist"],
        "intended_majors": "Biology"
      },
      "academics": {
        "gpa": {
          "unweighted": 3.98,
          "weighted": 4.57
        },
        "course_count": {
          "honors": null,
          "ap": 12,
          "ib": null,
          "dual_enrollment": null
        },
        "senior_year_course_load": null
      },
      "standardized_testing": {
        "sat_i": {
          "total": 1470,
          "reading_writing": null,
          "math": null
        },
        "act": null
      },
      "extracurriculars": [
        "FFA - Trained Nationals team for competitive CDE",
        "Student Council: Senior Class Officer",
        "Volunteering Achievement",
        "Choir",
        "Internship at vet clinic",
        "Scrapbooking",
        "School Student Ambassador",
        "National Art Honor Society",
        "National Honor Society"
      ],
      "awards_honors": [
        "QuestBridge National College Match Finalist",
        "Top 10 individual at Nationals FFA",
        "1st Place team at State in FFA",
        "2nd Individual & Top 5 team in FFA",
        "Junior of the Year in FFA"
      ],
      "letters_of_recommendation": null,
      "essays": null,
      "decisions": {
        "acceptances": [
          {
            "university": "Cornell CALS",
            "decision_plan": "N/A"
          }
        ],
        "waitlists": null,
        "rejections": null
      },
      "additional_information": null
    }
  },

  {
    "post_text": "Law Major ðŸŽ“\n\nDemographics\n\nWhite\nFemale\n0-50k\nPublic School\nAcademics\n\n1380 SAT\n12 AP's\n3.6 UW\nExtracurriculars\n\n1. mock trial\n\n2. speech and debate captain\n\n3. MUN board\n\n4. Founded a volunteer club\n\nAwards\n\n1. AP scholar\n\n2. IB diploma\n\n3. some MUN and debate awards\n\nAcceptances\n\n1. Dartmouth",
    "structured_profile": {
      "demographics": {
        "gender": "Female",
        "race_ethnicity": "White",
        "residence": null,
        "income_bracket": "0-50k",
        "type_of_school": "Public School",
        "hooks": null,
        "intended_majors": "Law"
      },
      "academics": {
        "gpa": {
          "unweighted": 3.6,
          "weighted": null
        },
        "course_count": {
          "honors": null,
          "ap": 12,
          "ib": null,
          "dual_enrollment": null
        },
        "senior_year_course_load": null
      },
      "standardized_testing": {
        "sat_i": {
          "total": 1380,
          "reading_writing": null,
          "math": null
        },
        "act": null
      },
      "extracurriculars": [
        "mock trial",
        "speech and debate captain",
        "MUN board",
        "Founded a volunteer club"
      ],
      "awards_honors": [
        "AP scholar",
        "IB diploma",
        "some MUN and debate awards"
      ],
      "letters_of_recommendation": null,
      "essays": null,
      "decisions": {
        "acceptances": [
          {
            "university": "Dartmouth",
            "decision_plan": "N/A"
          }
        ],
        "waitlists": null,
        "rejections": null
      },
      "additional_information": null
    }
  },

  {
    "post_text": "Economics Major ðŸŽ“\n\nDemographics\n\nHispanic\nMale\n200k+\nPrivate School\nAcademics\n\n36 ACT\n16 AP's\n4 UW\n4.7 W\nExtracurriculars\n\n1. Very selective summer program in humanities\n\n2. Debate (Team Captain)\n\n3. Online selective finance education program\n\n4. Hispanic government/civics program\n\n5. Student Council (Senior Class Delegate)\n\n6. DECA (State Champ)\n\n7. Local transit non-profit\n\n8. NHS (Treasurer)\n\n9. Varsity Sport\n\n10. Externship program at school\n\nAwards\n\n1. Highly selective nationwide program for government\n\n2. Another highly selective scholarship\n\n3. Debate awards\n\n4. DECA Awards\n\n5. Swimming awards\n\nAcceptances\n\n1. UMiami\n\n2. USC\n\n3. Stanford\n\n4. Brown\n\n5. UCF\n\n6. Columbia\n\n7. Dartmouth\n\n8. Duke\n\n9. UF\n\n10. Georgetown\n\n11. NYU\n\n12. Northwestern\n\n13. Notre Dame\n\n14. UPenn Huntsman\n\n15. Vanderbilt\n\n16. WUSTL\n\n17. Yale",
    "structured_profile": {
      "demographics": {
        "gender": "Male",
        "race_ethnicity": "Hispanic",
        "residence": null,
        "income_bracket": "200k+",
        "type_of_school": "Private School",
        "hooks": null,
        "intended_majors": "Economics"
      },
      "academics": {
        "gpa": {
          "unweighted": 4.0,
          "weighted": 4.7
        },
        "course_count": {
          "honors": null,
          "ap": 16,
          "ib": null,
          "dual_enrollment": null
        },
        "senior_year_course_load": null
      },
      "standardized_testing": {
        "sat_i": null,
        "act": 36
      },
      "extracurriculars": [
        "Very selective summer program in humanities",
        "Debate (Team Captain)",
        "Online selective finance education program",
        "Hispanic government/civics program",
        "Student Council (Senior Class Delegate)",
        "DECA (State Champ)",
        "Local transit non-profit",
        "NHS (Treasurer)",
        "Varsity Sport",
        "Externship program at school"
      ],
      "awards_honors": [
        "Highly selective nationwide program for government",
        "Another highly selective scholarship",
        "Debate awards",
        "DECA Awards",
        "Swimming awards"
      ],
      "letters_of_recommendation": null,
      "essays": null,
      "decisions": {
        "acceptances": [
          {
            "university": "UMiami",
            "decision_plan": "N/A"
          },
          {
            "university": "USC",
            "decision_plan": "N/A"
          },
          {
            "university": "Stanford",
            "decision_plan": "N/A"
          },
          {
            "university": "Brown",
            "decision_plan": "N/A"
          },
          {
            "university": "UCF",
            "decision_plan": "N/A"
          },
          {
            "university": "Columbia",
            "decision_plan": "N/A"
          },
          {
            "university": "Dartmouth",
            "decision_plan": "N/A"
          },
          {
            "university": "Duke",
            "decision_plan": "N/A"
          },
          {
            "university": "UF",
            "decision_plan": "N/A"
          },
          {
            "university": "Georgetown",
            "decision_plan": "N/A"
          },
          {
            "university": "NYU",
            "decision_plan": "N/A"
          },
          {
            "university": "Northwestern",
            "decision_plan": "N/A"
          },
          {
            "university": "Notre Dame",
            "decision_plan": "N/A"
          },
          {
            "university": "UPenn Huntsman",
            "decision_plan": "N/A"
          },
          {
            "university": "Vanderbilt",
            "decision_plan": "N/A"
          },
          {
            "university": "WUSTL",
            "decision_plan": "N/A"
          },
          {
            "university": "Yale",
            "decision_plan": "N/A"
          }
        ],
        "waitlists": null,
        "rejections": null
      },
      "additional_information": null
    }
  },

  {
    "post_text": "English Major ðŸŽ“\n\nDemographics\n\nAsian\nNon-Binary\n0-50k\nPrivate School\nAcademics\n\n1450 SAT\n13 AP's\n3.77 UW\n4.05 W\nExtracurriculars\n\n1. Creative Writing - Published a poetry book\n\n2. Horoscopes Columnist / Newspaper editor\n\n3. History internship / youth council member\n\n4. NSLI Y-esque government immersion program for Russian\n\n5. Maple sugar boiling / pancake club co pres\n\n6. Asian student alliance / Southeast asian alliance co pres\n\n7. Gender sexuality alliance co pres\n\n8. Vars debate co captain\n\n9. Writing center leader\n\n10. Tour guide\n\nAwards\n\n1. State youth poet laureate\n\n2. Intl writing contest for poetry\n\n3. Yet another intl writing contest for poetry\n\n4. State grant writing pitch and columbia entrepreneurship writing contest\n\n5. Global studies travel fellowship grant\n\nAcceptances\n\n1. Yale",
    "structured_profile": {
      "demographics": {
        "gender": "Non-Binary",
        "race_ethnicity": "Asian",
        "residence": null,
        "income_bracket": "0-50k",
        "type_of_school": "Private School",
        "hooks": null,
        "intended_majors": "English"
      },
      "academics": {
        "gpa": {
          "unweighted": 3.77,
          "weighted": 4.05
        },
        "course_count": {
          "honors": null,
          "ap": 13,
          "ib": null,
          "dual_enrollment": null
        },
        "senior_year_course_load": null
      },
      "standardized_testing": {
        "sat_i": {
          "total": 1450,
          "reading_writing": null,
          "math": null
        },
        "act": null
      },
      "extracurriculars": [
        "Creative Writing - Published a poetry book",
        "Horoscopes Columnist / Newspaper editor",
        "History internship / youth council member",
        "NSLI Y-esque government immersion program for Russian",
        "Maple sugar boiling / pancake club co pres",
        "Asian student alliance / Southeast asian alliance co pres",
        "Gender sexuality alliance co pres",
        "Vars debate co captain",
        "Writing center leader",
        "Tour guide"
      ],
      "awards_honors": [
        "State youth poet laureate",
        "Intl writing contest for poetry",
        "Yet another intl writing contest for poetry",
        "State grant writing pitch and columbia entrepreneurship writing contest",
        "Global studies travel fellowship grant"
      ],
      "letters_of_recommendation": null,
      "essays": null,
      "decisions": {
        "acceptances": [
          {
            "university": "Yale",
            "decision_plan": "N/A"
          }
        ],
        "waitlists": null,
        "rejections": null
      },
      "additional_information": null
    }
  },

  {
    "post_text": "Computer Science Major ðŸŽ“\n\nDemographics\n\nAfrican American\nMale\n0-50k\nPublic School\nAcademics\n\n1460 SAT\n7 AP's\n2.9 UW\n3.3 W\nExtracurriculars\n\n1. Paid research internship at T100 school (40 hrs/week)\n\n2. Concert band member\n\n3. Board Game Design\n\n4. Board Game Organizing\n\n5. Online Admin\n\n6. CGI Video Game Artist\n\n7. TSA Member\n\nAwards\n\n1. N/A\n\nAcceptances\n\n1. Milwaukee School of Engineering\n\n2. University of Pittsburgh\n\n3. Kettering University\n\n4. Florida Institute of Technology\n\n5. Rose-Hulman Institute of Technology",
    "structured_profile": {
      "demographics": {
        "gender": "Male",
        "race_ethnicity": "African American",
        "residence": null,
        "income_bracket": "0-50k",
        "type_of_school": "Public School",
        "hooks": null,
        "intended_majors": "Computer Science"
      },
      "academics": {
        "gpa": {
          "unweighted": 2.9,
          "weighted": 3.3
        },
        "course_count": {
          "honors": null,
          "ap": 7,
          "ib": null,
          "dual_enrollment": null
        },
        "senior_year_course_load": null
      },
      "standardized_testing": {
        "sat_i": {
          "total": 1460,
          "reading_writing": null,
          "math": null
        },
        "act": null
      },
      "extracurriculars": [
        "Paid research internship at T100 school (40 hrs/week)",
        "Concert band member",
        "Board Game Design",
        "Board Game Organizing",
        "Online Admin",
        "CGI Video Game Artist",
        "TSA Member"
      ],
      "awards_honors": [],
      "letters_of_recommendation": null,
      "essays": null,
      "decisions": {
        "acceptances": [
          {
            "university": "Milwaukee School of Engineering",
            "decision_plan": "N/A"
          },
          {
            "university": "University of Pittsburgh",
            "decision_plan": "N/A"
          },
          {
            "university": "Kettering University",
            "decision_plan": "N/A"
          },
          {
            "university": "Florida Institute of Technology",
            "decision_plan": "N/A"
          },
          {
            "university": "Rose-Hulman Institute of Technology",
            "decision_plan": "N/A"
          }
        ],
        "waitlists": null,
        "rejections": null
      },
      "additional_information": null
    }
  },

  {
    "post_text": "Liberal Studies Major ðŸŽ“\n\nDemographics\n\nAfrican American\nFemale\n0-50k\nPublic School\nAcademics\n\n4 AP's\n3.9 UW\n4.1 W\nExtracurriculars\n\n1. 1. taking piano + guitar lessons while mentoring young musicians in songwriting\n\n2. 2. NHS since 11th grade\n\n3. 3. secretary of student council\n\n4. 4. passion project - podcast about music and how it impacts peopleâ€™s lives based on their culture\n\n5. religion\n\n6. etc.\n\n7. 5. interact club: 20+ hrs volunteer work\n\n8. 6. a program where i got to film music content\n\n9. take photos at concerts\n\n10. create posters for events\n\n11. write and perform original songs\n\n12. music production\n\n13. and i wanna say more but i canâ€™t remember\n\n14. 7. fast food jobs to try to provide for my family cause iâ€™m poor and the only one working ðŸ˜­ iâ€™ve been working two jobs since like sophomore year\n\nAwards\n\n1. N/A\n\nAcceptances\n\n1. NYU\n\n2. Morgan State\n\n3. Pitt\n\n4. Norfolk State University\n\n5. Penn West Edinboro",
    "structured_profile": {
      "demographics": {
        "gender": "Female",
        "race_ethnicity": "African American",
        "residence": null,
        "income_bracket": "0-50k",
        "type_of_school": "Public School",
        "hooks": null,
        "intended_majors": "Liberal Studies"
      },
      "academics": {
        "gpa": {
          "unweighted": 3.9,
          "weighted": 4.1
        },
        "course_count": {
          "honors": null,
          "ap": 4,
          "ib": null,
          "dual_enrollment": null
        },
        "senior_year_course_load": null
      },
      "standardized_testing": null,
      "extracurriculars": [
        "Piano and guitar lessons, mentoring young musicians in songwriting",
        "NHS (since 11th grade)",
        "Secretary of student council",
        "Passion project: Podcast about music and its cultural impact",
        "Interact Club (20+ hours volunteer work)",
        "Music program: Filming music content, taking photos at concerts, creating posters for events, writing and performing original songs, music production",
        "Fast food jobs (two jobs since sophomore year to provide for family)"
      ],
      "awards_honors": [],
      "letters_of_recommendation": null,
      "essays": null,
      "decisions": {
        "acceptances": [
          {
            "university": "NYU",
            "decision_plan": "N/A"
          },
          {
            "university": "Morgan State",
            "decision_plan": "N/A"
          },
          {
            "university": "Pitt",
            "decision_plan": "N/A"
          },
          {
            "university": "Norfolk State University",
            "decision_plan": "N/A"
          },
          {
            "university": "Penn West Edinboro",
            "decision_plan": "N/A"
          }
        ],
        "waitlists": null,
        "rejections": null
      },
      "additional_information": null
    }
  },

  {
    "post_text": "Computer Science Major ðŸŽ“\n\nDemographics\n\nAsian\nMale\n0-50k\nPublic School\nAcademics\n\n1570 SAT\n3.88 W\nExtracurriculars\n\n1. The Founder and web developer behind the platform for teaching coding - consistent user base of 1-5k users daily\n\n2. President of the school engineering club for 2 years\n\n3. with 4 years of experience as a member\n\n4. Founder\n\n5. web developer\n\n6. and marketing manager of an e-commerce website selling sneakers and apparel\n\n7. generating 3-5racks monthly\n\n8. Internship at a leading IT company in my country as a full-stack\n\n9. independent mechanical engineering projects including a 6-axis robotic arm\n\n10. a ball-balancing robot\n\n11. and a self-driving RC car\n\n12. EXO EXO-looking RWD electric car\n\n13. president of the student council\n\n14. School basketball - captain\n\n15. Independent study English\n\n16. Programming\n\n17. member at Rocket Club\n\nAwards\n\n1. state Physics olympiad - 2x silver\n\n2. National Mathematics olympiad - 1x bronze\n\n3. National English olympiad - 1x bronze\n\nAcceptances\n\n1. Harvard EA\n\n2. Stanford RD\n\n3. Purdue RD\n\n4. Yale RD\n\n5. Princeton University RD\n\n6. Columbia RD",
    "structured_profile": {
      "demographics": {
        "gender": "Male",
        "race_ethnicity": "Asian",
        "residence": null,
        "income_bracket": "0-50k",
        "type_of_school": "Public School",
        "hooks": null,
        "intended_majors": "Computer Science"
      },
      "academics": {
        "gpa": {
          "unweighted": null,
          "weighted": 3.88
        },
        "course_count": null,
        "senior_year_course_load": null
      },
      "standardized_testing": {
        "sat_i": {
          "total": 1570,
          "reading_writing": null,
          "math": null
        },
        "act": null
      },
      "extracurriculars": [
        "Founder and web developer of a coding education platform (consistent user base of 1-5k users daily)",
        "President (2 years) and member (4 years) of school engineering club",
        "Founder, web developer, and marketing manager of an e-commerce website selling sneakers and apparel (generating 3-5k monthly)",
        "Internship at a leading IT company as a full-stack developer",
        "Independent mechanical engineering projects (6-axis robotic arm, ball-balancing robot, self-driving RC car, EXO-looking RWD electric car)",
        "President of the student council",
        "School basketball - captain",
        "Independent study (English, Programming)",
        "Member at Rocket Club"
      ],
      "awards_honors": [
        "State Physics Olympiad - 2x silver",
        "National Mathematics Olympiad - 1x bronze",
        "National English Olympiad - 1x bronze"
      ],
      "letters_of_recommendation": null,
      "essays": null,
      "decisions": {
        "acceptances": [
          {
            "university": "Harvard",
            "decision_plan": "EA"
          },
          {
            "university": "Stanford",
            "decision_plan": "RD"
          },
          {
            "university": "Purdue",
            "decision_plan": "RD"
          },
          {
            "university": "Yale",
            "decision_plan": "RD"
          },
          {
            "university": "Princeton University",
            "decision_plan": "RD"
          },
          {
            "university": "Columbia",
            "decision_plan": "RD"
          }
        ],
        "waitlists": null,
        "rejections": null
      },
      "additional_information": null
    }
  },

  {
    "post_text": "Computer Science Major ðŸŽ“\n\nDemographics\n\nAsian\nMale\n200k+\nPublic School\nAcademics\n\n1560 SAT\n3 AP's\n3.6 UW\nExtracurriculars\n\n1. On a robotics team that went to Vex worlds\n\n2. Did a bunch of volunteer clubs in 11th grade\n\n3. JV athletics running and swimming\n\n4. Coded a tutor resource website\n\n5. Technology Student Association made a website and went to nationals\n\n6. DECA\n\nAwards\n\n1. N/A\n\nAcceptances\n\n1. University of Washington\n\n2. WSU\n\n3. MSU\n\n4. ASU\n\n5. Purdue\n\n6. University of Wisconsin\n\n7. OSU\n\n8. Northeastern\n\n9. University of Maryland\n\n10. Penn State\n\n11. University of Minnesota\n\n12. Rutgers\n\n13. Virginia Tech",
    "structured_profile": {
      "demographics": {
        "gender": "Male",
        "race_ethnicity": "Asian",
        "residence": null,
        "income_bracket": "200k+",
        "type_of_school": "Public School",
        "hooks": null,
        "intended_majors": "Computer Science"
      },
      "academics": {
        "gpa": {
          "unweighted": 3.6,
          "weighted": null
        },
        "course_count": {
          "honors": null,
          "ap": 3,
          "ib": null,
          "dual_enrollment": null
        },
        "senior_year_course_load": null
      },
      "standardized_testing": {
        "sat_i": {
          "total": 1560,
          "reading_writing": null,
          "math": null
        },
        "act": null
      },
      "extracurriculars": [
        "On a robotics team that went to Vex worlds",
        "Did a bunch of volunteer clubs in 11th grade",
        "JV athletics running and swimming",
        "Coded a tutor resource website",
        "Technology Student Association made a website and went to nationals",
        "DECA"
      ],
      "awards_honors": null,
      "letters_of_recommendation": null,
      "essays": null,
      "decisions": {
        "acceptances": [
          {
            "university": "University of Washington",
            "decision_plan": "N/A"
          },
          {
            "university": "WSU",
            "decision_plan": "N/A"
          },
          {
            "university": "MSU",
            "decision_plan": "N/A"
          },
          {
            "university": "ASU",
            "decision_plan": "N/A"
          },
          {
            "university": "Purdue",
            "decision_plan": "N/A"
          },
          {
            "university": "University of Wisconsin",
            "decision_plan": "N/A"
          },
          {
            "university": "OSU",
            "decision_plan": "N/A"
          },
          {
            "university": "Northeastern",
            "decision_plan": "N/A"
          },
          {
            "university": "University of Maryland",
            "decision_plan": "N/A"
          },
          {
            "university": "Penn State",
            "decision_plan": "N/A"
          },
          {
            "university": "University of Minnesota",
            "decision_plan": "N/A"
          },
          {
            "university": "Rutgers",
            "decision_plan": "N/A"
          },
          {
            "university": "Virginia Tech",
            "decision_plan": "N/A"
          }
        ],
        "waitlists": null,
        "rejections": null
      },
      "additional_information": null
    }
  },

  {
    "post_text": "Cognitive Brain Science Major ðŸŽ“\n\nDemographics\n\nAsian\nMale\n50k-100k\nPublic School\nAcademics\n\n1540 SAT\n11 AP's\n3.94 UW\n4.4 W\nExtracurriculars\n\n1. Research Assistant at a Cognitive Science Lab\n\n2. Published Web magazine on the teenager's Mind\n\n3. Competitive Electrochemistry program internship\n\n4. Internship on morals and ethics\n\n5. Presented research on time and memory\n\n6. Innovator for Conrad Challenge\n\n7. Business plan and group manufacture for IDEATE Source America Challenge\n\n8. Korean Volunteering\n\n9. Korean Teacher\n\n10. Club President researching Brain Diseases\n\nAwards\n\n1. National Merit Semifinalist\n\n2. AP Scholar with Distinction\n\n3. Congressional Award Certificate\n\n4. Certificate of Recognition from city\n\n5. Presenter for Symposium\n\nAcceptances\n\n1. Tufts",
    "structured_profile": {
      "demographics": {
        "gender": "Male",
        "race_ethnicity": "Asian",
        "residence": null,
        "income_bracket": "50k-100k",
        "type_of_school": "Public School",
        "hooks": null,
        "intended_majors": "Cognitive Brain Science"
      },
      "academics": {
        "gpa": {
          "unweighted": 3.94,
          "weighted": 4.4
        },
        "course_count": {
          "honors": null,
          "ap": 11,
          "ib": null,
          "dual_enrollment": null
        },
        "senior_year_course_load": null
      },
      "standardized_testing": {
        "sat_i": {
          "total": 1540,
          "reading_writing": null,
          "math": null
        },
        "act": null
      },
      "extracurriculars": [
        "Research Assistant at a Cognitive Science Lab",
        "Published Web magazine on the teenager's Mind",
        "Competitive Electrochemistry program internship",
        "Internship on morals and ethics",
        "Presented research on time and memory",
        "Innovator for Conrad Challenge",
        "Business plan and group manufacture for IDEATE Source America Challenge",
        "Korean Volunteering",
        "Korean Teacher",
        "Club President researching Brain Diseases"
      ],
      "awards_honors": [
        "National Merit Semifinalist",
        "AP Scholar with Distinction",
        "Congressional Award Certificate",
        "Certificate of Recognition from city",
        "Presenter for Symposium"
      ],
      "letters_of_recommendation": null,
      "essays": null,
      "decisions": {
        "acceptances": [
          {
            "university": "Tufts",
            "decision_plan": "N/A"
          }
        ],
        "waitlists": null,
        "rejections": null
      },
      "additional_information": null
    }
  },

  {
    "post_text": "Business Major ðŸŽ“\n\nDemographics\n\nAsian\nMale\n50k-100k\nPrivate School\nAcademics\n\n1580 SAT\n6 AP's\nExtracurriculars\n\n1. Some large interschool sports and cultural fest Finance Head of department\n\n2. Some Mid-size interschool Hackathon Finance Head of department\n\n3. A finance department internship/ shadow at an insurance firm\n\n4. IT department internship/ shadow at an insurance firm\n\n5. School volleyball team Captain and Outside hitter\n\n6. School soccer team Goalkeeper\n\n7. Founder of cycling club for boarding students\n\n8. Computer science club leader\n\n9. Staff for an east-african wide sports and cultural fest\n\n10. Taught english and SAT at a college counselling firm/ organization\n\nAwards\n\n1. Soccer national tournament gold medalist\n\n2. Finalist for a business and economics fest\n\n3. UWaterloo math contest distinction\n\n4. MVP at 2 national volleyball tournaments and 3 interschool tourneys\n\n5. IGCSE distinction with 8A*\n\nAcceptances\n\n1. Vanderbilt\n\n2. Trinity university\n\n3. San Antonio\n\n4. Indiana university- Bloomington",
    "structured_profile": {
      "demographics": {
        "gender": "Male",
        "race_ethnicity": "Asian",
        "residence": null,
        "income_bracket": "50k-100k",
        "type_of_school": "Private School",
        "hooks": null,
        "intended_majors": "Business"
      },
      "academics": {
        "gpa": null,
        "course_count": {
          "honors": null,
          "ap": 6,
          "ib": null,
          "dual_enrollment": null
        },
        "senior_year_course_load": null
      },
      "standardized_testing": {
        "sat_i": {
          "total": 1580,
          "reading_writing": null,
          "math": null
        },
        "act": null
      },
      "extracurriculars": [
        "Interschool sports and cultural fest Finance Head of department",
        "Mid-size interschool Hackathon Finance Head of department",
        "Finance department internship/shadow at an insurance firm",
        "IT department internship/shadow at an insurance firm",
        "School volleyball team Captain and Outside hitter",
        "School soccer team Goalkeeper",
        "Founder of cycling club for boarding students",
        "Computer science club leader",
        "Staff for an East-African wide sports and cultural fest",
        "Taught English and SAT at a college counselling firm/organization"
      ],
      "awards_honors": [
        "Soccer national tournament gold medalist",
        "Finalist for a business and economics fest",
        "UWaterloo math contest distinction",
        "MVP at 2 national volleyball tournaments and 3 interschool tourneys",
        "IGCSE distinction with 8A*"
      ],
      "letters_of_recommendation": null,
      "essays": null,
      "decisions": {
        "acceptances": [
          {
            "university": "Vanderbilt",
            "decision_plan": "N/A"
          },
          {
            "university": "Trinity University",
            "decision_plan": "N/A"
          },
          {
            "university": "San Antonio",
            "decision_plan": "N/A"
          },
          {
            "university": "Indiana University- Bloomington",
            "decision_plan": "N/A"
          }
        ],
        "waitlists": null,
        "rejections": null
      },
      "additional_information": null
    }
  },

  {
    "post_text": "Political Science Major ðŸŽ“\n\nDemographics\n\nWhite\nMale\n100k-200k\nPublic School\nAcademics\n\n35 ACT\n5 AP's\n3.87 UW\n5.27 W\nExtracurriculars\n\n1. Interned 4-6 hours a week at nonprofit legal center\n\n2. Editor for school newspaper\n\n3. Boys State\n\n4. Ambassador for board made by state attorney general\n\n5. Internship at local prosecutor's office\n\n6. Week long law program at university\n\n7. Volunteer counselor at local summer camp\n\n8. Marching band\n\n9. School cultural club\n\n10. School recycling club\n\nAwards\n\n1. Award for top students at each school in region\n\n2. National Rural and Small Town Award\n\n3. NHS\n\n4. National Merit Commended\n\n5. AP Scholar with Distinction\n\nAcceptances\n\n1. Ohio University\n\n2. OSU\n\n3. Columbia",
    "structured_profile": {
      "demographics": {
        "gender": "Male",
        "race_ethnicity": "White",
        "residence": null,
        "income_bracket": "100k-200k",
        "type_of_school": "Public School",
        "hooks": null,
        "intended_majors": "Political Science"
      },
      "academics": {
        "gpa": {
          "unweighted": 3.87,
          "weighted": 5.27
        },
        "course_count": {
          "honors": null,
          "ap": 5,
          "ib": null,
          "dual_enrollment": null
        },
        "senior_year_course_load": null
      },
      "standardized_testing": {
        "sat_i": null,
        "act": 35
      },
      "extracurriculars": [
        "Interned 4-6 hours a week at nonprofit legal center",
        "Editor for school newspaper",
        "Boys State",
        "Ambassador for board made by state attorney general",
        "Internship at local prosecutor's office",
        "Week long law program at university",
        "Volunteer counselor at local summer camp",
        "Marching band",
        "School cultural club",
        "School recycling club"
      ],
      "awards_honors": [
        "Award for top students at each school in region",
        "National Rural and Small Town Award",
        "NHS",
        "National Merit Commended",
        "AP Scholar with Distinction"
      ],
      "letters_of_recommendation": null,
      "essays": null,
      "decisions": {
        "acceptances": [
          {
            "university": "Ohio University",
            "decision_plan": "N/A"
          },
          {
            "university": "OSU",
            "decision_plan": "N/A"
          },
          {
            "university": "Columbia",
            "decision_plan": "N/A"
          }
        ],
        "waitlists": null,
        "rejections": null
      },
      "additional_information": null
    }
  },

  {
    "post_text": "Political Science Major ðŸŽ“\n\nDemographics\n\nAsian\nFemale\n0-50k\nPublic School\nAcademics\n\n1520 SAT\n3.985 UW\n4.375 W\nExtracurriculars\n\n1. Class President\n\n2. FBLA President\n\n3. Chief Editor and Co-Founder of school social media club\n\n4. Varsity Speech & Debate Interpreter\n\n5. President of NHS\n\n6. Arts Programming Leader at local library teen book club\n\n7. Self-started small art business\n\n8. Helped out at family restaurant\n\n9. Student Council\n\n10. Floor Hockey Club\n\nAwards\n\n1. 1st Place in Political Science Event at FBLA Competition\n\n2. 2nd Place at Speech & Debate District Tournament for Dramatic Interpretation\n\n3. National Rural and Small Town Recognition Program\n\n4. Principal's Honor Roll\n\nAcceptances\n\n1. University of Pennsylvania\n\n2. Yale University",
    "structured_profile": {
      "demographics": {
        "gender": "Female",
        "race_ethnicity": "Asian",
        "residence": null,
        "income_bracket": "0-50k",
        "type_of_school": "Public School",
        "hooks": null,
        "intended_majors": "Political Science"
      },
      "academics": {
        "gpa": {
          "unweighted": 3.985,
          "weighted": 4.375
        },
        "course_count": null,
        "senior_year_course_load": null
      },
      "standardized_testing": {
        "sat_i": {
          "total": 1520,
          "reading_writing": null,
          "math": null
        },
        "act": null
      },
      "extracurriculars": [
        "Class President",
        "FBLA President",
        "Chief Editor and Co-Founder of school social media club",
        "Varsity Speech & Debate Interpreter",
        "President of NHS",
        "Arts Programming Leader at local library teen book club",
        "Self-started small art business",
        "Helped out at family restaurant",
        "Student Council",
        "Floor Hockey Club"
      ],
      "awards_honors": [
        "1st Place in Political Science Event at FBLA Competition",
        "2nd Place at Speech & Debate District Tournament for Dramatic Interpretation",
        "National Rural and Small Town Recognition Program",
        "Principal's Honor Roll"
      ],
      "letters_of_recommendation": null,
      "essays": null,
      "decisions": {
        "acceptances": [
          {
            "university": "University of Pennsylvania",
            "decision_plan": "N/A"
          },
          {
            "university": "Yale University",
            "decision_plan": "N/A"
          }
        ],
        "waitlists": null,
        "rejections": null
      },
      "additional_information": null
    }
  },

  {
    "post_text": "Philosophy Major ðŸŽ“\n\nDemographics\n\nWhite\nFemale\n50k-100k\nPublic School\nAcademics\n\n1590 SAT\n4 UW\n4.92 W\nExtracurriculars\n\n1. GSA president\n\n2. Paid internship in humanities research\n\n3. Paid cancer research internship\n\n4. Varsity girls soccer\n\n5. Political discussion group president\n\n6. Academic challenge\n\n7. Community orchard youth mentor\n\n8. Study skills club\n\n9. NHS\n\n10. Baking\n\nAwards\n\n1. 5k STEM scholarship\n\n2. Academic challenge TV show winner\n\n3. All-league for soccer\n\n4. NMSF\n\n5. AP Scholar w/ Distinction\n\nAcceptances\n\n1. Yale\n\n2. Amherst\n\n3. Pomona\n\n4. Williams\n\n5. Brown\n\n6. Harvard\n\n7. Stanford",
    "structured_profile": {
      "demographics": {
        "gender": "Female",
        "race_ethnicity": "White",
        "residence": null,
        "income_bracket": "50k-100k",
        "type_of_school": "Public School",
        "hooks": null,
        "intended_majors": "Philosophy"
      },
      "academics": {
        "gpa": {
          "unweighted": 4.0,
          "weighted": 4.92
        },
        "course_count": null,
        "senior_year_course_load": null
      },
      "standardized_testing": {
        "sat_i": {
          "total": 1590,
          "reading_writing": null,
          "math": null
        },
        "act": null
      },
      "extracurriculars": [
        "GSA president",
        "Paid internship in humanities research",
        "Paid cancer research internship",
        "Varsity girls soccer",
        "Political discussion group president",
        "Academic challenge",
        "Community orchard youth mentor",
        "Study skills club",
        "NHS",
        "Baking"
      ],
      "awards_honors": [
        "5k STEM scholarship",
        "Academic challenge TV show winner",
        "All-league for soccer",
        "NMSF",
        "AP Scholar w/ Distinction"
      ],
      "letters_of_recommendation": null,
      "essays": null,
      "decisions": {
        "acceptances": [
          {
            "university": "Yale",
            "decision_plan": "N/A"
          },
          {
            "university": "Amherst",
            "decision_plan": "N/A"
          },
          {
            "university": "Pomona",
            "decision_plan": "N/A"
          },
          {
            "university": "Williams",
            "decision_plan": "N/A"
          },
          {
            "university": "Brown",
            "decision_plan": "N/A"
          },
          {
            "university": "Harvard",
            "decision_plan": "N/A"
          },
          {
            "university": "Stanford",
            "decision_plan": "N/A"
          }
        ],
        "waitlists": null,
        "rejections": null
      },
      "additional_information": null
    }
  },

  {
    "post_text": "Mechanical Engineering Major ðŸŽ“\n\nDemographics\n\nAsian\nMale\n200k+\nPrivate School\nAcademics\n\n1580 SAT\n35 ACT\n7 AP's\n3.8 UW\n4.45 W\nExtracurriculars\n\n1. Local community org (8 years)\n\n2. Eagle Scout\n\n3. Robotics (FRC main fabricator)\n\n4. Research at universities\n\n5. Math and tech club leader\n\n6. Science Olympiad\n\n7. Wrestling\n\n8. Stats competition\n\nAwards\n\n1. 2-time AIME qualifier\n\n2. Eagle Scout + Order of the Arrow + Bronze Palm\n\n3. FRC Imagery Award\n\n4. National Merit Semifinalist\n\n5. ACSL Intermediate Division Finalist\n\nAcceptances\n\n1. Rice University",
    "structured_profile": {
      "demographics": {
        "gender": "Male",
        "race_ethnicity": "Asian",
        "residence": null,
        "income_bracket": "200k+",
        "type_of_school": "Private School",
        "hooks": null,
        "intended_majors": "Mechanical Engineering"
      },
      "academics": {
        "gpa": {
          "unweighted": 3.8,
          "weighted": 4.45
        },
        "course_count": {
          "honors": null,
          "ap": 7,
          "ib": null,
          "dual_enrollment": null
        },
        "senior_year_course_load": null
      },
      "standardized_testing": {
        "sat_i": {
          "total": 1580,
          "reading_writing": null,
          "math": null
        },
        "act": 35
      },
      "extracurriculars": [
        "Local community org (8 years)",
        "Eagle Scout",
        "Robotics (FRC main fabricator)",
        "Research at universities",
        "Math and tech club leader",
        "Science Olympiad",
        "Wrestling",
        "Stats competition"
      ],
      "awards_honors": [
        "2-time AIME qualifier",
        "Eagle Scout + Order of the Arrow + Bronze Palm",
        "FRC Imagery Award",
        "National Merit Semifinalist",
        "ACSL Intermediate Division Finalist"
      ],
      "letters_of_recommendation": null,
      "essays": null,
      "decisions": {
        "acceptances": [
          {
            "university": "Rice University",
            "decision_plan": "N/A"
          }
        ],
        "waitlists": null,
        "rejections": null
      },
      "additional_information": null
    }
  },

  {
    "post_text": "Health Science Major ðŸŽ“\n\nDemographics\n\nAsian\nMale\n0-50k\nPublic School\nAcademics\n\n1210 SAT\n3 AP's\n4 UW\nExtracurriculars\n\n1. NHS (1yr)\n\n2. Boy Scouts (7yrs)\n\n3. Varsity Rowing (2yrs)\n\n4. Wrestling/Lacrosse (1-2yrs)\n\n5. Church Student Leader (4yrs)\n\n6. Part Time Job (2yr)\n\n7. Camp Counselor (4yr)\n\n8. Piano (10yr)\n\nAwards\n\n1. Helped raise 25k for annual fundraiser\n\n2. Helped team place 3rd at a team wrestling meet\n\nAcceptances\n\n1. Northeastern",
    "structured_profile": {
      "demographics": {
        "gender": "Male",
        "race_ethnicity": "Asian",
        "residence": null,
        "income_bracket": "0-50k",
        "type_of_school": "Public School",
        "hooks": null,
        "intended_majors": "Health Science"
      },
      "academics": {
        "gpa": {
          "unweighted": 4.0,
          "weighted": null
        },
        "course_count": {
          "honors": null,
          "ap": 3,
          "ib": null,
          "dual_enrollment": null
        },
        "senior_year_course_load": null
      },
      "standardized_testing": {
        "sat_i": {
          "total": 1210,
          "reading_writing": null,
          "math": null
        },
        "act": null
      },
      "extracurriculars": [
        "NHS (1yr)",
        "Boy Scouts (7yrs)",
        "Varsity Rowing (2yrs)",
        "Wrestling/Lacrosse (1-2yrs)",
        "Church Student Leader (4yrs)",
        "Part Time Job (2yr)",
        "Camp Counselor (4yr)",
        "Piano (10yr)"
      ],
      "awards_honors": [
        "Helped raise 25k for annual fundraiser",
        "Helped team place 3rd at a team wrestling meet"
      ],
      "letters_of_recommendation": null,
      "essays": null,
      "decisions": {
        "acceptances": [
          {
            "university": "Northeastern",
            "decision_plan": "N/A"
          }
        ],
        "waitlists": null,
        "rejections": null
      },
      "additional_information": null
    }
  },

  {
    "post_text": "Business Major ðŸŽ“\n\nDemographics\n\nAsian\nMale\n0-50k\nPublic School\nAcademics\n\n1540 SAT\n7 AP's\n4.14 W\nExtracurriculars\n\n1. Local entrepreneur club\n\n2. Student government president\n\n3. Business club founder & president\n\n4. Cofounder of an international NGO\n\n5. Business advisor\n\n6. Helping local businesses\n\n7. Predicting future sale & cash flow\n\n8. Intern\n\n9. Volunteer\n\nAwards\n\n1. Academic Distinction\n\n2. National Economic Challenge Individual Distinction\n\n3. Model Entrepreneurship Competition finalist\n\n4. PwC ESG challenge semi finalist\n\n5. Campus basketball champion\n\nAcceptances\n\n1. IU Kelley\n\n2. UMich LSA Organizational studies\n\n3. UC Berkeley\n\n4. UCI\n\n5. UCD\n\n6. UCSB\n\n7. UCLA\n\n8. UCSD",
    "structured_profile": {
      "demographics": {
        "gender": "Male",
        "race_ethnicity": "Asian",
        "residence": null,
        "income_bracket": "0-50k",
        "type_of_school": "Public School",
        "hooks": null,
        "intended_majors": "Business"
      },
      "academics": {
        "gpa": {
          "unweighted": null,
          "weighted": 4.14
        },
        "course_count": {
          "honors": null,
          "ap": 7,
          "ib": null,
          "dual_enrollment": null
        },
        "senior_year_course_load": null
      },
      "standardized_testing": {
        "sat_i": {
          "total": 1540,
          "reading_writing": null,
          "math": null
        },
        "act": null
      },
      "extracurriculars": [
        "Local entrepreneur club",
        "Student government president",
        "Business club founder & president",
        "Cofounder of an international NGO",
        "Business advisor",
        "Helping local businesses",
        "Predicting future sale & cash flow",
        "Intern",
        "Volunteer"
      ],
      "awards_honors": [
        "Academic Distinction",
        "National Economic Challenge Individual Distinction",
        "Model Entrepreneurship Competition finalist",
        "PwC ESG challenge semi finalist",
        "Campus basketball champion"
      ],
      "letters_of_recommendation": null,
      "essays": null,
      "decisions": {
        "acceptances": [
          {
            "university": "IU Kelley",
            "decision_plan": "N/A"
          },
          {
            "university": "UMich LSA Organizational studies",
            "decision_plan": "N/A"
          },
          {
            "university": "UC Berkeley",
            "decision_plan": "N/A"
          },
          {
            "university": "UCI",
            "decision_plan": "N/A"
          },
          {
            "university": "UCD",
            "decision_plan": "N/A"
          },
          {
            "university": "UCSB",
            "decision_plan": "N/A"
          },
          {
            "university": "UCLA",
            "decision_plan": "N/A"
          },
          {
            "university": "UCSD",
            "decision_plan": "N/A"
          }
        ],
        "waitlists": null,
        "rejections": null
      },
      "additional_information": null
    }
  }
]
